Workbook

Sheet Dashboard
B1: IFA CONTACT DASHBOARD
B2: Live overview of every contact in the database. Add or edit a contact on the RawData tab and every number here moves with it.
B3: ="Contacts in database: "&TEXT(COUNTA(c_Name),"#,##0")&" | Refreshed: "&TEXT(TODAY(),"d mmm yyyy") -> Contacts in database: 369 | Refreshed: 7 Aug 2026
B5: TOTAL CONTACTS | E5: FIRMS COVERED | H5: CONTACTS MET | K5: MEETING COVERAGE
B6: =COUNTA(c_Name) -> 369 | E6: =SUMPRODUCT((c_Firm<>"")/COUNTIF(c_Firm,c_Firm&"")) -> 22 | H6: =COUNTIF(c_Met,"Yes") -> 51 | K6: =IFERROR(COUNTIF(c_Met,"Yes")/COUNTA(c_Name),0) -> 0.13821138
B8: TOTAL MEETINGS | E8: INVITED TO AN EVENT | H8: ATTENDED AN EVENT | K8: EVENT ATTENDANCE RATE
B9: =SUM(c_Mtgs) -> 51 | E9: =COUNTIF(c_EvtInv,">0") -> 128 | H9: =COUNTIF(c_EvtAtt,">0") -> 77 | K9: =IFERROR(COUNTIF(c_EvtAtt,">0")/COUNTIF(c_EvtInv,">0"),0) -> 0.6015625
B11: MET IN LAST 90 DAYS | E11: NEVER CONTACTED | H11: INVESTORS | K11: ILP AUM TRACKED (S$M)
B12: =COUNTIFS(c_Date,">="&TODAY()-90) -> 0 | E12: =COUNTIF(c_Engage,"Not yet contacted") -> 91 | H12: =COUNTIF(c_Invested,"Yes") -> 7 | K12: =SUM(c_AUM)/1000000 -> 922
B14: WHERE THEY COME FROM — CONTACTS BY FIRM | F14: sorted by size; % Met = share of that firm you have already met
B15: Firm | C15: Contacts | D15: % of DB | E15: Met | F15: % Met | G15: Meetings | H15: Invited to events | I15: Attended events | J15: Investors | K15: ILP AUM (S$m)
B16: PIAS | C16: =COUNTIF(c_Firm,$B16) -> 117 | D16: =IFERROR($C16/COUNTA(c_Name),0) -> 0.31707317 | E16: =COUNTIFS(c_Firm,$B16,c_Met,"Yes") -> 7 | F16: =IFERROR($E16/$C16,0) -> 0.05982906 | G16: =SUMIF(c_Firm,$B16,c_Mtgs) -> 7 | H16: =COUNTIFS(c_Firm,$B16,c_EvtInv,">0") -> 8 | I16: =COUNTIFS(c_Firm,$B16,c_EvtAtt,">0") -> 5 | J16: =COUNTIFS(c_Firm,$B16,c_Invested,"Yes") -> 1 | K16: =SUMIF(c_Firm,$B16,c_AUM)/1000000 -> 125
B17: Finexis Advisory | C17: =COUNTIF(c_Firm,$B17) -> 50 | D17: =IFERROR($C17/COUNTA(c_Name),0) -> 0.13550136 | E17: =COUNTIFS(c_Firm,$B17,c_Met,"Yes") -> 7 | F17: =IFERROR($E17/$C17,0) -> 0.14 | G17: =SUMIF(c_Firm,$B17,c_Mtgs) -> 7 | H17: =COUNTIFS(c_Firm,$B17,c_EvtInv,">0") -> 11 | I17: =COUNTIFS(c_Firm,$B17,c_EvtAtt,">0") -> 9 | J17: =COUNTIFS(c_Firm,$B17,c_Invested,"Yes") -> 2 | K17: =SUMIF(c_Firm,$B17,c_AUM)/1000000 -> 247
B18: Manulife FA | C18: =COUNTIF(c_Firm,$B18) -> 38 | D18: =IFERROR($C18/COUNTA(c_Name),0) -> 0.10298103 | E18: =COUNTIFS(c_Firm,$B18,c_Met,"Yes") -> 0 | F18: =IFERROR($E18/$C18,0) -> 0 | G18: =SUMIF(c_Firm,$B18,c_Mtgs) -> 0 | H18: =COUNTIFS(c_Firm,$B18,c_EvtInv,">0") -> 0 | I18: =COUNTIFS(c_Firm,$B18,c_EvtAtt,">0") -> 0 | J18: =COUNTIFS(c_Firm,$B18,c_Invested,"Yes") -> 0 | K18: =SUMIF(c_Firm,$B18,c_AUM)/1000000 -> 0
B19: Synergy | C19: =COUNTIF(c_Firm,$B19) -> 34 | D19: =IFERROR($C19/COUNTA(c_Name),0) -> 0.092140921 | E19: =COUNTIFS(c_Firm,$B19,c_Met,"Yes") -> 7 | F19: =IFERROR($E19/$C19,0) -> 0.20588235 | G19: =SUMIF(c_Firm,$B19,c_Mtgs) -> 7 | H19: =COUNTIFS(c_Firm,$B19,c_EvtInv,">0") -> 30 | I19: =COUNTIFS(c_Firm,$B19,c_EvtAtt,">0") -> 15 | J19: =COUNTIFS(c_Firm,$B19,c_Invested,"Yes") -> 2 | K19: =SUMIF(c_Firm,$B19,c_AUM)/1000000 -> 142
B20: iFast | C20: =COUNTIF(c_Firm,$B20) -> 27 | D20: =IFERROR($C20/COUNTA(c_Name),0) -> 0.073170732 | E20: =COUNTIFS(c_Firm,$B20,c_Met,"Yes") -> 2 | F20: =IFERROR($E20/$C20,0) -> 0.074074074 | G20: =SUMIF(c_Firm,$B20,c_Mtgs) -> 2 | H20: =COUNTIFS(c_Firm,$B20,c_EvtInv,">0") -> 8 | I20: =COUNTIFS(c_Firm,$B20,c_EvtAtt,">0") -> 7 | J20: =COUNTIFS(c_Firm,$B20,c_Invested,"Yes") -> 1 | K20: =SUMIF(c_Firm,$B20,c_AUM)/1000000 -> 148
B21: Financial Alliance | C21: =COUNTIF(c_Firm,$B21) -> 23 | D21: =IFERROR($C21/COUNTA(c_Name),0) -> 0.062330623 | E21: =COUNTIFS(c_Firm,$B21,c_Met,"Yes") -> 9 | F21: =IFERROR($E21/$C21,0) -> 0.39130435 | G21: =SUMIF(c_Firm,$B21,c_Mtgs) -> 9 | H21: =COUNTIFS(c_Firm,$B21,c_EvtInv,">0") -> 23 | I21: =COUNTIFS(c_Firm,$B21,c_EvtAtt,">0") -> 15 | J21: =COUNTIFS(c_Firm,$B21,c_Invested,"Yes") -> 1 | K21: =SUMIF(c_Firm,$B21,c_AUM)/1000000 -> 75
B22: Phillip Capital | C22: =COUNTIF(c_Firm,$B22) -> 23 | D22: =IFERROR($C22/COUNTA(c_Name),0) -> 0.062330623 | E22: =COUNTIFS(c_Firm,$B22,c_Met,"Yes") -> 7 | F22: =IFERROR($E22/$C22,0) -> 0.30434783 | G22: =SUMIF(c_Firm,$B22,c_Mtgs) -> 7 | H22: =COUNTIFS(c_Firm,$B22,c_EvtInv,">0") -> 18 | I22: =COUNTIFS(c_Firm,$B22,c_EvtAtt,">0") -> 9 | J22: =COUNTIFS(c_Firm,$B22,c_Invested,"Yes") -> 0 | K22: =SUMIF(c_Firm,$B22,c_AUM)/1000000 -> 102
B23: Singlife | C23: =COUNTIF(c_Firm,$B23) -> 15 | D23: =IFERROR($C23/COUNTA(c_Name),0) -> 0.040650407 | E23: =COUNTIFS(c_Firm,$B23,c_Met,"Yes") -> 3 | F23: =IFERROR($E23/$C23,0) -> 0.2 | G23: =SUMIF(c_Firm,$B23,c_Mtgs) -> 3 | H23: =COUNTIFS(c_Firm,$B23,c_EvtInv,">0") -> 5 | I23: =COUNTIFS(c_Firm,$B23,c_EvtAtt,">0") -> 3 | J23: =COUNTIFS(c_Firm,$B23,c_Invested,"Yes") -> 0 | K23: =SUMIF(c_Firm,$B23,c_AUM)/1000000 -> 0
B24: Infinity FA | C24: =COUNTIF(c_Firm,$B24) -> 12 | D24: =IFERROR($C24/COUNTA(c_Name),0) -> 0.032520325 | E24: =COUNTIFS(c_Firm,$B24,c_Met,"Yes") -> 2 | F24: =IFERROR($E24/$C24,0) -> 0.16666667 | G24: =SUMIF(c_Firm,$B24,c_Mtgs) -> 2 | H24: =COUNTIFS(c_Firm,$B24,c_EvtInv,">0") -> 12 | I24: =COUNTIFS(c_Firm,$B24,c_EvtAtt,">0") -> 9 | J24: =COUNTIFS(c_Firm,$B24,c_Invested,"Yes") -> 0 | K24: =SUMIF(c_Firm,$B24,c_AUM)/1000000 -> 67
B25: Income Advisory | C25: =COUNTIF(c_Firm,$B25) -> 11 | D25: =IFERROR($C25/COUNTA(c_Name),0) -> 0.029810298 | E25: =COUNTIFS(c_Firm,$B25,c_Met,"Yes") -> 0 | F25: =IFERROR($E25/$C25,0) -> 0 | G25: =SUMIF(c_Firm,$B25,c_Mtgs) -> 0 | H25: =COUNTIFS(c_Firm,$B25,c_EvtInv,">0") -> 0 | I25: =COUNTIFS(c_Firm,$B25,c_EvtAtt,">0") -> 0 | J25: =COUNTIFS(c_Firm,$B25,c_Invested,"Yes") -> 0 | K25: =SUMIF(c_Firm,$B25,c_AUM)/1000000 -> 0
B26: PromiseLand | C26: =COUNTIF(c_Firm,$B26) -> 5 | D26: =IFERROR($C26/COUNTA(c_Name),0) -> 0.013550136 | E26: =COUNTIFS(c_Firm,$B26,c_Met,"Yes") -> 1 | F26: =IFERROR($E26/$C26,0) -> 0.2 | G26: =SUMIF(c_Firm,$B26,c_Mtgs) -> 1 | H26: =COUNTIFS(c_Firm,$B26,c_EvtInv,">0") -> 1 | I26: =COUNTIFS(c_Firm,$B26,c_EvtAtt,">0") -> 0 | J26: =COUNTIFS(c_Firm,$B26,c_Invested,"Yes") -> 0 | K26: =SUMIF(c_Firm,$B26,c_AUM)/1000000 -> 5
B27: Alpha Wealth | C27: =COUNTIF(c_Firm,$B27) -> 3 | D27: =IFERROR($C27/COUNTA(c_Name),0) -> 0.0081300813 | E27: =COUNTIFS(c_Firm,$B27,c_Met,"Yes") -> 0 | F27: =IFERROR($E27/$C27,0) -> 0 | G27: =SUMIF(c_Firm,$B27,c_Mtgs) -> 0 | H27: =COUNTIFS(c_Firm,$B27,c_EvtInv,">0") -> 3 | I27: =COUNTIFS(c_Firm,$B27,c_EvtAtt,">0") -> 2 | J27: =COUNTIFS(c_Firm,$B27,c_Invested,"Yes") -> 0 | K27: =SUMIF(c_Firm,$B27,c_AUM)/1000000 -> 0
... B37: SG Alliance | C37: =COUNTIF(c_Firm,$B37) -> 1 | D37: =IFERROR($C37/COUNTA(c_Name),0) -> 0.0027100271 | E37: =COUNTIFS(c_Firm,$B37,c_Met,"Yes") -> 0 | F37: =IFERROR($E37/$C37,0) -> 0 | G37: =SUMIF(c_Firm,$B37,c_Mtgs) -> 0 | H37: =COUNTIFS(c_Firm,$B37,c_EvtInv,">0") -> 1 | I37: =COUNTIFS(c_Firm,$B37,c_EvtAtt,">0") -> 1 | J37: =COUNTIFS(c_Firm,$B37,c_Invested,"Yes") -> 0 | K37: =SUMIF(c_Firm,$B37,c_AUM)/1000000 -> 0
B38: TOTAL | C38: =SUM(C16:C37) -> 369 | D38: =IFERROR($C38/COUNTA(c_Name),0) -> 1 | E38: =SUM(E16:E37) -> 51 | F38: =IFERROR($E38/$C38,0) -> 0.13821138 | G38: =SUM(G16:G37) -> 51 | H38: =SUM(H16:H37) -> 128 | I38: =SUM(I16:I37) -> 77 | J38: =SUM(J16:J37) -> 7 | K38: =SUM(K16:K37) -> 922
B39: Contacts whose firm is missing from the Setup list (should be 0): | F39: =COUNTA(c_Name)-$C$38 -> 0
B41: WHICH EVENT THEY CAME TO | F41: status per contact lives in RawData columns N–R
B42: Event | C42: Date | D42: Invited | E42: Attended | F42: No show | G42: Declined | H42: No reply | I42: Pending | J42: Attendance rate
B43: =IF(Setup!$C$15="","(free slot 1)",Setup!$C$15) -> H2O AM IFA Symposium (October 2025) | C43: =IF(Setup!$E$15="","",Setup!$E$15) -> 45931 | D43: =COUNTA(c_E1)-COUNTIF(c_E1,"Not Invited") -> 75 | E43: =COUNTIF(c_E1,"Attended") -> 34 | F43: =COUNTIF(c_E1,"No Show") -> 0 | G43: =COUNTIF(c_E1,"Declined") -> 24 | H43: =COUNTIF(c_E1,"No Reply") -> 17 | I43: =COUNTIF(c_E1,"Invited")+COUNTIF(c_E1,"Accepted") -> 0 | J43: =IFERROR($E43/$D43,"") -> 0.45333333
B44: =IF(Setup!$C$16="","(free slot 2)",Setup!$C$16) -> 2nd Edition H2O AM IFA Symposium (May 2026) | C44: =IF(Setup!$E$16="","",Setup!$E$16) -> 46143 | D44: =COUNTA(c_E2)-COUNTIF(c_E2,"Not Invited") -> 123 | E44: =COUNTIF(c_E2,"Attended") -> 55 | F44: =COUNTIF(c_E2,"No Show") -> 11 | G44: =COUNTIF(c_E2,"Declined") -> 32 | H44: =COUNTIF(c_E2,"No Reply") -> 24 | I44: =COUNTIF(c_E2,"Invited")+COUNTIF(c_E2,"Accepted") -> 1 | J44: =IFERROR($E44/$D44,"") -> 0.44715447
B45: =IF(Setup!$C$17="","(free slot 3)",Setup!$C$17) -> Macro Lunch series | C45: =IF(Setup!$E$17="","",Setup!$E$17) -> 46226 | D45: =COUNTA(c_E3)-COUNTIF(c_E3,"Not Invited") -> 3 | E45: =COUNTIF(c_E3,"Attended") -> 0 | F45: =COUNTIF(c_E3,"No Show") -> 0 | G45: =COUNTIF(c_E3,"Declined") -> 0 | H45: =COUNTIF(c_E3,"No Reply") -> 0 | I45: =COUNTIF(c_E3,"Invited")+COUNTIF(c_E3,"Accepted") -> 3 | J45: =IFERROR($E45/$D45,"") -> 0
B46: =IF(Setup!$C$18="","(free slot 4)",Setup!$C$18) -> (free slot 4) | C46: =IF(Setup!$E$18="","",Setup!$E$18) | D46: =COUNTA(c_E4)-COUNTIF(c_E4,"Not Invited") -> 0 | E46: =COUNTIF(c_E4,"Attended") -> 0 | F46: =COUNTIF(c_E4,"No Show") -> 0 | G46: =COUNTIF(c_E4,"Declined") -> 0 | H46: =COUNTIF(c_E4,"No Reply") -> 0 | I46: =COUNTIF(c_E4,"Invited")+COUNTIF(c_E4,"Accepted") -> 0 | J46: =IFERROR($E46/$D46,"")
B47: =IF(Setup!$C$19="","(free slot 5)",Setup!$C$19) -> (free slot 5) | C47: =IF(Setup!$E$19="","",Setup!$E$19) | D47: =COUNTA(c_E5)-COUNTIF(c_E5,"Not Invited") -> 0 | E47: =COUNTIF(c_E5,"Attended") -> 0 | F47: =COUNTIF(c_E5,"No Show") -> 0 | G47: =COUNTIF(c_E5,"Declined") -> 0 | H47: =COUNTIF(c_E5,"No Reply") -> 0 | I47: =COUNTIF(c_E5,"Invited")+COUNTIF(c_E5,"Accepted") -> 0 | J47: =IFERROR($E47/$D47,"")
B49: HOW WARM THEY ARE | F49: WHICH LIST THEY CAME FROM
B50: Stage | C50: Contacts | D50: % of DB | F50: Source list | G50: Contacts | H50: % of DB
B51: Event attendee | C51: =COUNTIF(c_Engage,$B51) -> 77 | D51: =IFERROR($C51/COUNTA(c_Name),0) -> 0.20867209 | F51: Meeting List | G51: =COUNTIF(c_Source,"*"&$F51&"*") -> 129 | H51: =IFERROR($G51/COUNTA(c_Name),0) -> 0.3495935
B52: Met (no event) | C52: =COUNTIF(c_Engage,$B52) -> 28 | D52: =IFERROR($C52/COUNTA(c_Name),0) -> 0.075880759 | F52: Branch Directors | G52: =COUNTIF(c_Source,"*"&$F52&"*") -> 173 | H52: =IFERROR($G52/COUNTA(c_Name),0) -> 0.46883469
B53: Invited only | C53: =COUNTIF(c_Engage,$B53) -> 24 | D53: =IFERROR($C53/COUNTA(c_Name),0) -> 0.06504065 | F53: Mass Email PIAS | G53: =COUNTIF(c_Source,"*"&$F53&"*") -> 85 | H53: =IFERROR($G53/COUNTA(c_Name),0) -> 0.2303523
B54: Contacted only | C54: =COUNTIF(c_Engage,$B54) -> 149 | D54: =IFERROR($C54/COUNTA(c_Name),0) -> 0.40379404 | F54: ILP Data | G54: =COUNTIF(c_Source,"*"&$F54&"*") -> 73 | H54: =IFERROR($G54/COUNTA(c_Name),0) -> 0.19783198
B55: Not yet contacted | C55: =COUNTIF(c_Engage,$B55) -> 91 | D55: =IFERROR($C55/COUNTA(c_Name),0) -> 0.24661247
F56: A contact can sit on more than one list, so these add up to more than the total.

Sheet Meeting Stats
B1: MEETING STATISTICS
B2: Built from the Met? / Last Meeting / # Meetings columns of RawData. The source file records one LAST MEETING date per contact, so the monthly split below shows each contact once, in the month you last saw them.
B5: TOTAL MEETINGS | E5: CONTACTS MET | H5: DATABASE MET | K5: MEETINGS PER CONTACT
B6: =SUM(c_Mtgs) -> 51 | E6: =COUNTIF(c_Met,"Yes") -> 51 | H6: =IFERROR(COUNTIF(c_Met,"Yes")/COUNTA(c_Name),0) -> 0.13821138 | K6: =IFERROR(SUM(c_Mtgs)/COUNTIF(c_Met,"Yes"),0) -> 1
B8: FIRST MEETING | E8: MOST RECENT MEETING | H8: MET IN LAST 30 DAYS | K8: OVERDUE (>120 DAYS)
B9: =IFERROR(MIN(c_Date),"") -> 45412 | E9: =IFERROR(MAX(c_Date),"") -> 46134 | H9: =COUNTIFS(c_Date,">="&TODAY()-30) -> 0 | K9: =COUNTIF(c_Days,">120") -> 49
B11: MEETING ACTIVITY BY MONTH | F11: rolling 18 months
B12: Month | C12: Contacts met | D12: Cumulative (window)
B13: =EOMONTH(TODAY(),-18)+1 -> 45717 | C13: =COUNTIFS(c_Date,">="&$B13,c_Date,"<="&EOMONTH($B13,0)) -> 1 | D13: =$C13 -> 1
B14: =EOMONTH($B13,0)+1 -> 45748 | C14: =COUNTIFS(c_Date,">="&$B14,c_Date,"<="&EOMONTH($B14,0)) -> 0 | D14: =$D13+$C14 -> 1
B15: =EOMONTH($B14,0)+1 -> 45778 | C15: =COUNTIFS(c_Date,">="&$B15,c_Date,"<="&EOMONTH($B15,0)) -> 0 | D15: =$D14+$C15 -> 1
B16: =EOMONTH($B15,0)+1 -> 45809 | C16: =COUNTIFS(c_Date,">="&$B16,c_Date,"<="&EOMONTH($B16,0)) -> 4 | D16: =$D15+$C16 -> 5
B17: =EOMONTH($B16,0)+1 -> 45839 | C17: =COUNTIFS(c_Date,">="&$B17,c_Date,"<="&EOMONTH($B17,0)) -> 0 | D17: =$D16+$C17 -> 5
B18: =EOMONTH($B17,0)+1 -> 45870 | C18: =COUNTIFS(c_Date,">="&$B18,c_Date,"<="&EOMONTH($B18,0)) -> 2 | D18: =$D17+$C18 -> 7
B19: =EOMONTH($B18,0)+1 -> 45901 | C19: =COUNTIFS(c_Date,">="&$B19,c_Date,"<="&EOMONTH($B19,0)) -> 12 | D19: =$D18+$C19 -> 19
B20: =EOMONTH($B19,0)+1 -> 45931 | C20: =COUNTIFS(c_Date,">="&$B20,c_Date,"<="&EOMONTH($B20,0)) -> 7 | D20: =$D19+$C20 -> 26
B21: =EOMONTH($B20,0)+1 -> 45962 | C21: =COUNTIFS(c_Date,">="&$B21,c_Date,"<="&EOMONTH($B21,0)) -> 5 | D21: =$D20+$C21 -> 31
B22: =EOMONTH($B21,0)+1 -> 45992 | C22: =COUNTIFS(c_Date,">="&$B22,c_Date,"<="&EOMONTH($B22,0)) -> 4 | D22: =$D21+$C22 -> 35
B23: =EOMONTH($B22,0)+1 -> 46023 | C23: =COUNTIFS(c_Date,">="&$B23,c_Date,"<="&EOMONTH($B23,0)) -> 4 | D23: =$D22+$C23 -> 39
B24: =EOMONTH($B23,0)+1 -> 46054 | C24: =COUNTIFS(c_Date,">="&$B24,c_Date,"<="&EOMONTH($B24,0)) -> 2 | D24: =$D23+$C24 -> 41
B25: =EOMONTH($B24,0)+1 -> 46082 | C25: =COUNTIFS(c_Date,">="&$B25,c_Date,"<="&EOMONTH($B25,0)) -> 4 | D25: =$D24+$C25 -> 45
... B30: =EOMONTH($B29,0)+1 -> 46235 | C30: =COUNTIFS(c_Date,">="&$B30,c_Date,"<="&EOMONTH($B30,0)) -> 0 | D30: =$D29+$C30 -> 47
B32: MEETING COVERAGE BY FIRM | F32: which firms you have actually worked
B33: Firm | C33: Contacts | D33: Met | E33: Coverage | F33: Meetings | G33: Last meeting | H33: Days since | I33: Attended an event
B34: Financial Alliance | C34: =COUNTIF(c_Firm,$B34) -> 23 | D34: =COUNTIFS(c_Firm,$B34,c_Met,"Yes") -> 9 | E34: =IFERROR($D34/$C34,0) -> 0.39130435 | F34: =SUMIF(c_Firm,$B34,c_Mtgs) -> 9 | G34: =IF(_xlfn.MAXIFS(c_Date,c_Firm,$B34)=0,"",_xlfn.MAXIFS(c_Date,c_Firm,$B34)) -> 46043 | H34: =IF($G34="","",TODAY()-$G34) -> 198 | I34: =COUNTIFS(c_Firm,$B34,c_EvtAtt,">0") -> 15
B35: Finexis Advisory | C35: =COUNTIF(c_Firm,$B35) -> 50 | D35: =COUNTIFS(c_Firm,$B35,c_Met,"Yes") -> 7 | E35: =IFERROR($D35/$C35,0) -> 0.14 | F35: =SUMIF(c_Firm,$B35,c_Mtgs) -> 7 | G35: =IF(_xlfn.MAXIFS(c_Date,c_Firm,$B35)=0,"",_xlfn.MAXIFS(c_Date,c_Firm,$B35)) -> 46007 | H35: =IF($G35="","",TODAY()-$G35) -> 234 | I35: =COUNTIFS(c_Firm,$B35,c_EvtAtt,">0") -> 9
B36: PIAS | C36: =COUNTIF(c_Firm,$B36) -> 117 | D36: =COUNTIFS(c_Firm,$B36,c_Met,"Yes") -> 7 | E36: =IFERROR($D36/$C36,0) -> 0.05982906 | F36: =SUMIF(c_Firm,$B36,c_Mtgs) -> 7 | G36: =IF(_xlfn.MAXIFS(c_Date,c_Firm,$B36)=0,"",_xlfn.MAXIFS(c_Date,c_Firm,$B36)) -> 46090 | H36: =IF($G36="","",TODAY()-$G36) -> 151 | I36: =COUNTIFS(c_Firm,$B36,c_EvtAtt,">0") -> 5
B37: Phillip Capital | C37: =COUNTIF(c_Firm,$B37) -> 23 | D37: =COUNTIFS(c_Firm,$B37,c_Met,"Yes") -> 7 | E37: =IFERROR($D37/$C37,0) -> 0.30434783 | F37: =SUMIF(c_Firm,$B37,c_Mtgs) -> 7 | G37: =IF(_xlfn.MAXIFS(c_Date,c_Firm,$B37)=0,"",_xlfn.MAXIFS(c_Date,c_Firm,$B37)) -> 46045 | H37: =IF($G37="","",TODAY()-$G37) -> 196 | I37: =COUNTIFS(c_Firm,$B37,c_EvtAtt,">0") -> 9
B38: Synergy | C38: =COUNTIF(c_Firm,$B38) -> 34 | D38: =COUNTIFS(c_Firm,$B38,c_Met,"Yes") -> 7 | E38: =IFERROR($D38/$C38,0) -> 0.20588235 | F38: =SUMIF(c_Firm,$B38,c_Mtgs) -> 7 | G38: =IF(_xlfn.MAXIFS(c_Date,c_Firm,$B38)=0,"",_xlfn.MAXIFS(c_Date,c_Firm,$B38)) -> 46091 | H38: =IF($G38="","",TODAY()-$G38) -> 150 | I38: =COUNTIFS(c_Firm,$B38,c_EvtAtt,">0") -> 15
B39: Singlife | C39: =COUNTIF(c_Firm,$B39) -> 15 | D39: =COUNTIFS(c_Firm,$B39,c_Met,"Yes") -> 3 | E39: =IFERROR($D39/$C39,0) -> 0.2 | F39: =SUMIF(c_Firm,$B39,c_Mtgs) -> 3 | G39: =IF(_xlfn.MAXIFS(c_Date,c_Firm,$B39)=0,"",_xlfn.MAXIFS(c_Date,c_Firm,$B39)) -> 45897 | H39: =IF($G39="","",TODAY()-$G39) -> 344 | I39: =COUNTIFS(c_Firm,$B39,c_EvtAtt,">0") -> 3
B40: GYC Financial Advisory | C40: =COUNTIF(c_Firm,$B40) -> 2 | D40: =COUNTIFS(c_Firm,$B40,c_Met,"Yes") -> 2 | E40: =IFERROR($D40/$C40,0) -> 1 | F40: =SUMIF(c_Firm,$B40,c_Mtgs) -> 2 | G40: =IF(_xlfn.MAXIFS(c_Date,c_Firm,$B40)=0,"",_xlfn.MAXIFS(c_Date,c_Firm,$B40)) -> 45412 | H40: =IF($G40="","",TODAY()-$G40) -> 829 | I40: =COUNTIFS(c_Firm,$B40,c_EvtAtt,">0") -> 0
B41: Infinity FA | C41: =COUNTIF(c_Firm,$B41) -> 12 | D41: =COUNTIFS(c_Firm,$B41,c_Met,"Yes") -> 2 | E41: =IFERROR($D41/$C41,0) -> 0.16666667 | F41: =SUMIF(c_Firm,$B41,c_Mtgs) -> 2 | G41: =IF(_xlfn.MAXIFS(c_Date,c_Firm,$B41)=0,"",_xlfn.MAXIFS(c_Date,c_Firm,$B41)) -> 46056 | H41: =IF($G41="","",TODAY()-$G41) -> 185 | I41: =COUNTIFS(c_Firm,$B41,c_EvtAtt,">0") -> 9
B42: iFast | C42: =COUNTIF(c_Firm,$B42) -> 27 | D42: =COUNTIFS(c_Firm,$B42,c_Met,"Yes") -> 2 | E42: =IFERROR($D42/$C42,0) -> 0.074074074 | F42: =SUMIF(c_Firm,$B42,c_Mtgs) -> 2 | G42: =IF(_xlfn.MAXIFS(c_Date,c_Firm,$B42)=0,"",_xlfn.MAXIFS(c_Date,c_Firm,$B42)) -> 46132 | H42: =IF($G42="","",TODAY()-$G42) -> 109 | I42: =COUNTIFS(c_Firm,$B42,c_EvtAtt,">0") -> 7
B43: Great Eastern Life | C43: =COUNTIF(c_Firm,$B43) -> 1 | D43: =COUNTIFS(c_Firm,$B43,c_Met,"Yes") -> 1 | E43: =IFERROR($D43/$C43,0) -> 1 | F43: =SUMIF(c_Firm,$B43,c_Mtgs) -> 1 | G43: =IF(_xlfn.MAXIFS(c_Date,c_Firm,$B43)=0,"",_xlfn.MAXIFS(c_Date,c_Firm,$B43)) -> 45989 | H43: =IF($G43="","",TODAY()-$G43) -> 252 | I43: =COUNTIFS(c_Firm,$B43,c_EvtAtt,">0") -> 1
B44: HSBC Life | C44: =COUNTIF(c_Firm,$B44) -> 1 | D44: =COUNTIFS(c_Firm,$B44,c_Met,"Yes") -> 1 | E44: =IFERROR($D44/$C44,0) -> 1 | F44: =SUMIF(c_Firm,$B44,c_Mtgs) -> 1 | G44: =IF(_xlfn.MAXIFS(c_Date,c_Firm,$B44)=0,"",_xlfn.MAXIFS(c_Date,c_Firm,$B44)) -> 46062 | H44: =IF($G44="","",TODAY()-$G44) -> 179 | I44: =COUNTIFS(c_Firm,$B44,c_EvtAtt,">0") -> 0
B45: IPP FA | C45: =COUNTIF(c_Firm,$B45) -> 1 | D45: =COUNTIFS(c_Firm,$B45,c_Met,"Yes") -> 1 | E45: =IFERROR($D45/$C45,0) -> 1 | F45: =SUMIF(c_Firm,$B45,c_Mtgs) -> 1 | G45: =IF(_xlfn.MAXIFS(c_Date,c_Firm,$B45)=0,"",_xlfn.MAXIFS(c_Date,c_Firm,$B45)) -> 46084 | H45: =IF($G45="","",TODAY()-$G45) -> 157 | I45: =COUNTIFS(c_Firm,$B45,c_EvtAtt,">0") -> 0
... B55: SG Alliance | C55: =COUNTIF(c_Firm,$B55) -> 1 | D55: =COUNTIFS(c_Firm,$B55,c_Met,"Yes") -> 0 | E55: =IFERROR($D55/$C55,0) -> 0 | F55: =SUMIF(c_Firm,$B55,c_Mtgs) -> 0 | G55: =IF(_xlfn.MAXIFS(c_Date,c_Firm,$B55)=0,"",_xlfn.MAXIFS(c_Date,c_Firm,$B55)) | H55: =IF($G55="","",TODAY()-$G55) | I55: =COUNTIFS(c_Firm,$B55,c_EvtAtt,">0") -> 1
B57: OLDEST RELATIONSHIPS — FOLLOW UP FIRST | F57: the contacts you have met whose last meeting is furthest in the past
B58: Name | C58: Firm | D58: Last meeting | E58: Days since | F58: Events attended | G58: Invested? | H58: Email
A59: =IFERROR(MATCH(1,c_FUp,0),"") -> 79 | B59: =IF($A59="","",INDEX(c_Name,$A59)) -> Bruce Tan | C59: =IF($A59="","",INDEX(c_Firm,$A59)) -> GYC Financial Advisory | D59: =IF($A59="","",INDEX(c_Date,$A59)) -> 45412 | E59: =IF($A59="","",INDEX(c_Days,$A59)) -> 829 | F59: =IF($A59="","",INDEX(c_EvtNames,$A59)&"") | G59: =IF($A59="","",INDEX(c_Invested,$A59)) -> TBC | H59: =IF($A59="","",INDEX(c_Email,$A59)&"") -> brucetan@gyc.com.sg
A60: =IFERROR(MATCH(2,c_FUp,0),"") -> 80 | B60: =IF($A60="","",INDEX(c_Name,$A60)) -> Carl Chay | C60: =IF($A60="","",INDEX(c_Firm,$A60)) -> GYC Financial Advisory | D60: =IF($A60="","",INDEX(c_Date,$A60)) -> 45412 | E60: =IF($A60="","",INDEX(c_Days,$A60)) -> 829 | F60: =IF($A60="","",INDEX(c_EvtNames,$A60)&"") | G60: =IF($A60="","",INDEX(c_Invested,$A60)) -> TBC | H60: =IF($A60="","",INDEX(c_Email,$A60)&"") -> carlchay@gyc.com.sg
A61: =IFERROR(MATCH(3,c_FUp,0),"") -> 338 | B61: =IF($A61="","",INDEX(c_Name,$A61)) -> Andrew Fong | C61: =IF($A61="","",INDEX(c_Firm,$A61)) -> Synergy | D61: =IF($A61="","",INDEX(c_Date,$A61)) -> 45552 | E61: =IF($A61="","",INDEX(c_Days,$A61)) -> 689 | F61: =IF($A61="","",INDEX(c_EvtNames,$A61)&"") -> Oct-25 Symposium, May-26 Symposium | G61: =IF($A61="","",INDEX(c_Invested,$A61)) -> No | H61: =IF($A61="","",INDEX(c_Email,$A61)&"") -> andrewfong@synergy.com.sg
A62: =IFERROR(MATCH(4,c_FUp,0),"") -> 317 | B62: =IF($A62="","",INDEX(c_Name,$A62)) -> Lawrence Koh | C62: =IF($A62="","",INDEX(c_Firm,$A62)) -> PromiseLand | D62: =IF($A62="","",INDEX(c_Date,$A62)) -> 45693 | E62: =IF($A62="","",INDEX(c_Days,$A62)) -> 548 | F62: =IF($A62="","",INDEX(c_EvtNames,$A62)&"") | G62: =IF($A62="","",INDEX(c_Invested,$A62)) -> No | H62: =IF($A62="","",INDEX(c_Email,$A62)&"") -> lawrence.koh@promiseland.com.sg
A63: =IFERROR(MATCH(5,c_FUp,0),"") -> 341 | B63: =IF($A63="","",INDEX(c_Name,$A63)) -> Danny Lee | C63: =IF($A63="","",INDEX(c_Firm,$A63)) -> Synergy | D63: =IF($A63="","",INDEX(c_Date,$A63)) -> 45734 | E63: =IF($A63="","",INDEX(c_Days,$A63)) -> 507 | F63: =IF($A63="","",INDEX(c_EvtNames,$A63)&"") -> Oct-25 Symposium | G63: =IF($A63="","",INDEX(c_Invested,$A63)) -> Yes | H63: =IF($A63="","",INDEX(c_Email,$A63)&"") -> dannylee@synergy.com.sg
A64: =IFERROR(MATCH(6,c_FUp,0),"") -> 330 | B64: =IF($A64="","",INDEX(c_Name,$A64)) -> Mavis Tan | C64: =IF($A64="","",INDEX(c_Firm,$A64)) -> Singlife | D64: =IF($A64="","",INDEX(c_Date,$A64)) -> 45812 | E64: =IF($A64="","",INDEX(c_Days,$A64)) -> 429 | F64: =IF($A64="","",INDEX(c_EvtNames,$A64)&"") | G64: =IF($A64="","",INDEX(c_Invested,$A64)) -> No | H64: =IF($A64="","",INDEX(c_Email,$A64)&"") -> mavis.tan@singlife.com
A65: =IFERROR(MATCH(7,c_FUp,0),"") -> 21 | B65: =IF($A65="","",INDEX(c_Name,$A65)) -> Sani Amid | C65: =IF($A65="","",INDEX(c_Firm,$A65)) -> Financial Alliance | D65: =IF($A65="","",INDEX(c_Date,$A65)) -> 45819 | E65: =IF($A65="","",INDEX(c_Days,$A65)) -> 422 | F65: =IF($A65="","",INDEX(c_EvtNames,$A65)&"") -> Oct-25 Symposium | G65: =IF($A65="","",INDEX(c_Invested,$A65)) -> No | H65: =IF($A65="","",INDEX(c_Email,$A65)&"") -> sanihamid@fa.sg
A66: =IFERROR(MATCH(8,c_FUp,0),"") -> 19 | B66: =IF($A66="","",INDEX(c_Name,$A66)) -> Raymund Ng | C66: =IF($A66="","",INDEX(c_Firm,$A66)) -> Financial Alliance | D66: =IF($A66="","",INDEX(c_Date,$A66)) -> 45829 | E66: =IF($A66="","",INDEX(c_Days,$A66)) -> 412 | F66: =IF($A66="","",INDEX(c_EvtNames,$A66)&"") | G66: =IF($A66="","",INDEX(c_Invested,$A66)) -> Yes | H66: =IF($A66="","",INDEX(c_Email,$A66)&"") -> raymundng@fapl.sg
A67: =IFERROR(MATCH(9,c_FUp,0),"") -> 272 | B67: =IF($A67="","",INDEX(c_Name,$A67)) -> Moses Lim | C67: =IF($A67="","",INDEX(c_Firm,$A67)) -> PIAS | D67: =IF($A67="","",INDEX(c_Date,$A67)) -> 45838 | E67: =IF($A67="","",INDEX(c_Days,$A67)) -> 403 | F67: =IF($A67="","",INDEX(c_EvtNames,$A67)&"") | G67: =IF($A67="","",INDEX(c_Invested,$A67)) -> No | H67: =IF($A67="","",INDEX(c_Email,$A67)&"") -> moses.lim@promiseland.com.sg
A68: =IFERROR(MATCH(10,c_FUp,0),"") -> 323 | B68: =IF($A68="","",INDEX(c_Name,$A68)) -> Claire Tan | C68: =IF($A68="","",INDEX(c_Firm,$A68)) -> Singlife | D68: =IF($A68="","",INDEX(c_Date,$A68)) -> 45897 | E68: =IF($A68="","",INDEX(c_Days,$A68)) -> 344 | F68: =IF($A68="","",INDEX(c_EvtNames,$A68)&"") -> Oct-25 Symposium | G68: =IF($A68="","",INDEX(c_Invested,$A68)) -> No | H68: =IF($A68="","",INDEX(c_Email,$A68)&"") -> claire.tan@singlife.com
A69: =IFERROR(MATCH(11,c_FUp,0),"") -> 331 | B69: =IF($A69="","",INDEX(c_Name,$A69)) -> Reuben Sim | C69: =IF($A69="","",INDEX(c_Firm,$A69)) -> Singlife | D69: =IF($A69="","",INDEX(c_Date,$A69)) -> 45897 | E69: =IF($A69="","",INDEX(c_Days,$A69)) -> 344 | F69: =IF($A69="","",INDEX(c_EvtNames,$A69)&"") -> Oct-25 Symposium, May-26 Symposium | G69: =IF($A69="","",INDEX(c_Invested,$A69)) -> No | H69: =IF($A69="","",INDEX(c_Email,$A69)&"") -> reuben_sim@singlife.com
A70: =IFERROR(MATCH(12,c_FUp,0),"") -> 357 | B70: =IF($A70="","",INDEX(c_Name,$A70)) -> Nick Anderson | C70: =IF($A70="","",INDEX(c_Firm,$A70)) -> Synergy | D70: =IF($A70="","",INDEX(c_Date,$A70)) -> 45902 | E70: =IF($A70="","",INDEX(c_Days,$A70)) -> 339 | F70: =IF($A70="","",INDEX(c_EvtNames,$A70)&"") | G70: =IF($A70="","",INDEX(c_Invested,$A70)) -> No | H70: =IF($A70="","",INDEX(c_Email,$A70)&"") -> nick@aam-advisory.com
A71: =IFERROR(MATCH(13,c_FUp,0),"") -> 178 | B71: =IF($A71="","",INDEX(c_Name,$A71)) -> Brian See Toh | C71: =IF($A71="","",INDEX(c_Firm,$A71)) -> Phillip Capital | D71: =IF($A71="","",INDEX(c_Date,$A71)) -> 45912 | E71: =IF($A71="","",INDEX(c_Days,$A71)) -> 329 | F71: =IF($A71="","",INDEX(c_EvtNames,$A71)&"") -> May-26 Symposium | G71: =IF($A71="","",INDEX(c_Invested,$A71)) -> No | H71: =IF($A71="","",INDEX(c_Email,$A71)&"") -> brianst@phillip.com.sg
A72: =IFERROR(MATCH(14,c_FUp,0),"") -> 4 | B72: =IF($A72="","",INDEX(c_Name,$A72)) -> Alvin Low | C72: =IF($A72="","",INDEX(c_Firm,$A72)) -> Financial Alliance | D72: =IF($A72="","",INDEX(c_Date,$A72)) -> 45918 | E72: =IF($A72="","",INDEX(c_Days,$A72)) -> 323 | F72: =IF($A72="","",INDEX(c_EvtNames,$A72)&"") | G72: =IF($A72="","",INDEX(c_Invested,$A72)) -> No | H72: =IF($A72="","",INDEX(c_Email,$A72)&"") -> alvinlow@fapl.sg
A73: =IFERROR(MATCH(15,c_FUp,0),"") -> 6 | B73: =IF($A73="","",INDEX(c_Name,$A73)) -> Edmond Goh | C73: =IF($A73="","",INDEX(c_Firm,$A73)) -> Financial Alliance | D73: =IF($A73="","",INDEX(c_Date,$A73)) -> 45918 | E73: =IF($A73="","",INDEX(c_Days,$A73)) -> 323 | F73: =IF($A73="","",INDEX(c_EvtNames,$A73)&"") -> Oct-25 Symposium, May-26 Symposium | G73: =IF($A73="","",INDEX(c_Invested,$A73)) -> No | H73: =IF($A73="","",INDEX(c_Email,$A73)&"") -> edmondgoh@fapl.sg

Sheet Contacts
B1: CONTACT DIRECTORY
B2: Every contact, sorted by firm then name. Change any of the yellow filter boxes below and the list rebuilds instantly.
B3: Firm: | C3: (All) | D3: Met?: | E3: (All) | F3: Attended: | G3: (All) | H3: Warmth: | I3: (All) | J3: Search: | M3: =TEXT(COUNTIF(c_Pass,1),"#,##0")&" of "&TEXT(COUNTA(c_Name),"#,##0")&" contacts shown" -> 369 of 369 contacts shown
B5: Name | C5: Firm | D5: Type | E5: Email | F5: Met? | G5: Last meeting | H5: Days since | I5: # Mtgs | J5: Events attended | K5: Invested? | L5: AUM (S$) | M5: Source | N5: Notes
A6: =IFERROR(MATCH(ROW()-5,c_Seq,0),"") -> 1 | B6: =IF($A6="","",INDEX(c_Name,$A6)&"") -> Ang hui | C6: =IF($A6="","",INDEX(c_Firm,$A6)&"") -> Alpha Wealth | D6: =IF($A6="","",INDEX(c_Type,$A6)&"") -> Adviser | E6: =IF($A6="","",INDEX(c_Email,$A6)&"") -> anghuichin@awfa.com.sg | F6: =IF($A6="","",INDEX(c_Met,$A6)&"") -> No | G6: =IF($A6="","",IF(INDEX(c_Date,$A6)="","",INDEX(c_Date,$A6))) | H6: =IF($A6="","",IF(INDEX(c_Days,$A6)="","",INDEX(c_Days,$A6))) | I6: =IF($A6="","",IF(INDEX(c_Mtgs,$A6)="","",INDEX(c_Mtgs,$A6))) -> 0 | J6: =IF($A6="","",INDEX(c_EvtNames,$A6)&"") | K6: =IF($A6="","",INDEX(c_Invested,$A6)&"") -> No | L6: =IF($A6="","",IF(INDEX(c_AUM,$A6)="","",INDEX(c_AUM,$A6))) | M6: =IF($A6="","",INDEX(c_Source,$A6)&"") -> Meeting List | N6: =IF($A6="","",INDEX(c_Notes,$A6)&"")
A7: =IFERROR(MATCH(ROW()-5,c_Seq,0),"") -> 2 | B7: =IF($A7="","",INDEX(c_Name,$A7)&"") -> Jason Yin | C7: =IF($A7="","",INDEX(c_Firm,$A7)&"") -> Alpha Wealth | D7: =IF($A7="","",INDEX(c_Type,$A7)&"") -> Adviser | E7: =IF($A7="","",INDEX(c_Email,$A7)&"") -> jasonyin@awfa.com.sg | F7: =IF($A7="","",INDEX(c_Met,$A7)&"") -> No | G7: =IF($A7="","",IF(INDEX(c_Date,$A7)="","",INDEX(c_Date,$A7))) | H7: =IF($A7="","",IF(INDEX(c_Days,$A7)="","",INDEX(c_Days,$A7))) | I7: =IF($A7="","",IF(INDEX(c_Mtgs,$A7)="","",INDEX(c_Mtgs,$A7))) -> 0 | J7: =IF($A7="","",INDEX(c_EvtNames,$A7)&"") -> May-26 Symposium | K7: =IF($A7="","",INDEX(c_Invested,$A7)&"") -> No | L7: =IF($A7="","",IF(INDEX(c_AUM,$A7)="","",INDEX(c_AUM,$A7))) | M7: =IF($A7="","",INDEX(c_Source,$A7)&"") -> Meeting List | N7: =IF($A7="","",INDEX(c_Notes,$A7)&"")
A8: =IFERROR(MATCH(ROW()-5,c_Seq,0),"") -> 3 | B8: =IF($A8="","",INDEX(c_Name,$A8)&"") -> Lee Jia Hao | C8: =IF($A8="","",INDEX(c_Firm,$A8)&"") -> Alpha Wealth | D8: =IF($A8="","",INDEX(c_Type,$A8)&"") -> Adviser | E8: =IF($A8="","",INDEX(c_Email,$A8)&"") -> leejiahao@awfa.com.sg | F8: =IF($A8="","",INDEX(c_Met,$A8)&"") -> No | G8: =IF($A8="","",IF(INDEX(c_Date,$A8)="","",INDEX(c_Date,$A8))) | H8: =IF($A8="","",IF(INDEX(c_Days,$A8)="","",INDEX(c_Days,$A8))) | I8: =IF($A8="","",IF(INDEX(c_Mtgs,$A8)="","",INDEX(c_Mtgs,$A8))) -> 0 | J8: =IF($A8="","",INDEX(c_EvtNames,$A8)&"") -> May-26 Symposium | K8: =IF($A8="","",INDEX(c_Invested,$A8)&"") -> No | L8: =IF($A8="","",IF(INDEX(c_AUM,$A8)="","",INDEX(c_AUM,$A8))) | M8: =IF($A8="","",INDEX(c_Source,$A8)&"") -> Meeting List | N8: =IF($A8="","",INDEX(c_Notes,$A8)&"")
A9: =IFERROR(MATCH(ROW()-5,c_Seq,0),"") -> 4 | B9: =IF($A9="","",INDEX(c_Name,$A9)&"") -> Alvin Low | C9: =IF($A9="","",INDEX(c_Firm,$A9)&"") -> Financial Alliance | D9: =IF($A9="","",INDEX(c_Type,$A9)&"") -> Adviser | E9: =IF($A9="","",INDEX(c_Email,$A9)&"") -> alvinlow@fapl.sg | F9: =IF($A9="","",INDEX(c_Met,$A9)&"") -> Yes | G9: =IF($A9="","",IF(INDEX(c_Date,$A9)="","",INDEX(c_Date,$A9))) -> 45918 | H9: =IF($A9="","",IF(INDEX(c_Days,$A9)="","",INDEX(c_Days,$A9))) -> 323 | I9: =IF($A9="","",IF(INDEX(c_Mtgs,$A9)="","",INDEX(c_Mtgs,$A9))) -> 1 | J9: =IF($A9="","",INDEX(c_EvtNames,$A9)&"") | K9: =IF($A9="","",INDEX(c_Invested,$A9)&"") -> No | L9: =IF($A9="","",IF(INDEX(c_AUM,$A9)="","",INDEX(c_AUM,$A9))) -> 5000000 | M9: =IF($A9="","",INDEX(c_Source,$A9)&"") -> Meeting List + ILP Data | N9: =IF($A9="","",INDEX(c_Notes,$A9)&"")
A10: =IFERROR(MATCH(ROW()-5,c_Seq,0),"") -> 5 | B10: =IF($A10="","",INDEX(c_Name,$A10)&"") -> Chenise Lim | C10: =IF($A10="","",INDEX(c_Firm,$A10)&"") -> Financial Alliance | D10: =IF($A10="","",INDEX(c_Type,$A10)&"") -> Adviser | E10: =IF($A10="","",INDEX(c_Email,$A10)&"") -> cheniselim@fapl.sg | F10: =IF($A10="","",INDEX(c_Met,$A10)&"") -> Yes | G10: =IF($A10="","",IF(INDEX(c_Date,$A10)="","",INDEX(c_Date,$A10))) -> 45923 | H10: =IF($A10="","",IF(INDEX(c_Days,$A10)="","",INDEX(c_Days,$A10))) -> 318 | I10: =IF($A10="","",IF(INDEX(c_Mtgs,$A10)="","",INDEX(c_Mtgs,$A10))) -> 1 | J10: =IF($A10="","",INDEX(c_EvtNames,$A10)&"") | K10: =IF($A10="","",INDEX(c_Invested,$A10)&"") -> No | L10: =IF($A10="","",IF(INDEX(c_AUM,$A10)="","",INDEX(c_AUM,$A10))) -> 32000000 | M10: =IF($A10="","",INDEX(c_Source,$A10)&"") -> Meeting List + ILP Data | N10: =IF($A10="","",INDEX(c_Notes,$A10)&"") -> May-26: not available
A11: =IFERROR(MATCH(ROW()-5,c_Seq,0),"") -> 6 | B11: =IF($A11="","",INDEX(c_Name,$A11)&"") -> Edmond Goh | C11: =IF($A11="","",INDEX(c_Firm,$A11)&"") -> Financial Alliance | D11: =IF($A11="","",INDEX(c_Type,$A11)&"") -> Adviser | E11: =IF($A11="","",INDEX(c_Email,$A11)&"") -> edmondgoh@fapl.sg | F11: =IF($A11="","",INDEX(c_Met,$A11)&"") -> Yes | G11: =IF($A11="","",IF(INDEX(c_Date,$A11)="","",INDEX(c_Date,$A11))) -> 45918 | H11: =IF($A11="","",IF(INDEX(c_Days,$A11)="","",INDEX(c_Days,$A11))) -> 323 | I11: =IF($A11="","",IF(INDEX(c_Mtgs,$A11)="","",INDEX(c_Mtgs,$A11))) -> 1 | J11: =IF($A11="","",INDEX(c_EvtNames,$A11)&"") -> Oct-25 Symposium, May-26 Symposium | K11: =IF($A11="","",INDEX(c_Invested,$A11)&"") -> No | L11: =IF($A11="","",IF(INDEX(c_AUM,$A11)="","",INDEX(c_AUM,$A11))) -> 6000000 | M11: =IF($A11="","",INDEX(c_Source,$A11)&"") -> Meeting List + ILP Data | N11: =IF($A11="","",INDEX(c_Notes,$A11)&"")
A12: =IFERROR(MATCH(ROW()-5,c_Seq,0),"") -> 7 | B12: =IF($A12="","",INDEX(c_Name,$A12)&"") -> Edwin Tan | C12: =IF($A12="","",INDEX(c_Firm,$A12)&"") -> Financial Alliance | D12: =IF($A12="","",INDEX(c_Type,$A12)&"") -> Adviser | E12: =IF($A12="","",INDEX(c_Email,$A12)&"") -> edwintan@fapl.sg | F12: =IF($A12="","",INDEX(c_Met,$A12)&"") -> No | G12: =IF($A12="","",IF(INDEX(c_Date,$A12)="","",INDEX(c_Date,$A12))) | H12: =IF($A12="","",IF(INDEX(c_Days,$A12)="","",INDEX(c_Days,$A12))) | I12: =IF($A12="","",IF(INDEX(c_Mtgs,$A12)="","",INDEX(c_Mtgs,$A12))) -> 0 | J12: =IF($A12="","",INDEX(c_EvtNames,$A12)&"") -> May-26 Symposium | K12: =IF($A12="","",INDEX(c_Invested,$A12)&"") -> No | L12: =IF($A12="","",IF(INDEX(c_AUM,$A12)="","",INDEX(c_AUM,$A12))) | M12: =IF($A12="","",INDEX(c_Source,$A12)&"") -> Meeting List | N12: =IF($A12="","",INDEX(c_Notes,$A12)&"")
A13: =IFERROR(MATCH(ROW()-5,c_Seq,0),"") -> 8 | B13: =IF($A13="","",INDEX(c_Name,$A13)&"") -> Francis Hoan | C13: =IF($A13="","",INDEX(c_Firm,$A13)&"") -> Financial Alliance | D13: =IF($A13="","",INDEX(c_Type,$A13)&"") -> Adviser | E13: =IF($A13="","",INDEX(c_Email,$A13)&"") -> francishoan@fapl.sg | F13: =IF($A13="","",INDEX(c_Met,$A13)&"") -> No | G13: =IF($A13="","",IF(INDEX(c_Date,$A13)="","",INDEX(c_Date,$A13))) | H13: =IF($A13="","",IF(INDEX(c_Days,$A13)="","",INDEX(c_Days,$A13))) | I13: =IF($A13="","",IF(INDEX(c_Mtgs,$A13)="","",INDEX(c_Mtgs,$A13))) -> 0 | J13: =IF($A13="","",INDEX(c_EvtNames,$A13)&"") | K13: =IF($A13="","",INDEX(c_Invested,$A13)&"") -> No | L13: =IF($A13="","",IF(INDEX(c_AUM,$A13)="","",INDEX(c_AUM,$A13))) | M13: =IF($A13="","",INDEX(c_Source,$A13)&"") -> Meeting List | N13: =IF($A13="","",INDEX(c_Notes,$A13)&"")
A14: =IFERROR(MATCH(ROW()-5,c_Seq,0),"") -> 9 | B14: =IF($A14="","",INDEX(c_Name,$A14)&"") -> Gary Lim | C14: =IF($A14="","",INDEX(c_Firm,$A14)&"") -> Financial Alliance | D14: =IF($A14="","",INDEX(c_Type,$A14)&"") -> Adviser | E14: =IF($A14="","",INDEX(c_Email,$A14)&"") -> garylim@fapl.sg | F14: =IF($A14="","",INDEX(c_Met,$A14)&"") -> No | G14: =IF($A14="","",IF(INDEX(c_Date,$A14)="","",INDEX(c_Date,$A14))) | H14: =IF($A14="","",IF(INDEX(c_Days,$A14)="","",INDEX(c_Days,$A14))) | I14: =IF($A14="","",IF(INDEX(c_Mtgs,$A14)="","",INDEX(c_Mtgs,$A14))) -> 0 | J14: =IF($A14="","",INDEX(c_EvtNames,$A14)&"") -> Oct-25 Symposium | K14: =IF($A14="","",INDEX(c_Invested,$A14)&"") -> No | L14: =IF($A14="","",IF(INDEX(c_AUM,$A14)="","",INDEX(c_AUM,$A14))) -> 10000000 | M14: =IF($A14="","",INDEX(c_Source,$A14)&"") -> Meeting List + ILP Data | N14: =IF($A14="","",INDEX(c_Notes,$A14)&"")
A15: =IFERROR(MATCH(ROW()-5,c_Seq,0),"") -> 10 | B15: =IF($A15="","",INDEX(c_Name,$A15)&"") -> Guek Choo | C15: =IF($A15="","",INDEX(c_Firm,$A15)&"") -> Financial Alliance | D15: =IF($A15="","",INDEX(c_Type,$A15)&"") -> Adviser | E15: =IF($A15="","",INDEX(c_Email,$A15)&"") -> guekchoo@fapl.sg | F15: =IF($A15="","",INDEX(c_Met,$A15)&"") -> Yes | G15: =IF($A15="","",IF(INDEX(c_Date,$A15)="","",INDEX(c_Date,$A15))) -> 45923 | H15: =IF($A15="","",IF(INDEX(c_Days,$A15)="","",INDEX(c_Days,$A15))) -> 318 | I15: =IF($A15="","",IF(INDEX(c_Mtgs,$A15)="","",INDEX(c_Mtgs,$A15))) -> 1 | J15: =IF($A15="","",INDEX(c_EvtNames,$A15)&"") | K15: =IF($A15="","",INDEX(c_Invested,$A15)&"") -> No | L15: =IF($A15="","",IF(INDEX(c_AUM,$A15)="","",INDEX(c_AUM,$A15))) -> 4000000 | M15: =IF($A15="","",INDEX(c_Source,$A15)&"") -> Meeting List + ILP Data | N15: =IF($A15="","",INDEX(c_Notes,$A15)&"") -> May-26: not available
A16: =IFERROR(MATCH(ROW()-5,c_Seq,0),"") -> 11 | B16: =IF($A16="","",INDEX(c_Name,$A16)&"") -> Hadi Wijaya | C16: =IF($A16="","",INDEX(c_Firm,$A16)&"") -> Financial Alliance | D16: =IF($A16="","",INDEX(c_Type,$A16)&"") -> Adviser | E16: =IF($A16="","",INDEX(c_Email,$A16)&"") -> hadiwijaya@fapl.sg | F16: =IF($A16="","",INDEX(c_Met,$A16)&"") -> No | G16: =IF($A16="","",IF(INDEX(c_Date,$A16)="","",INDEX(c_Date,$A16))) | H16: =IF($A16="","",IF(INDEX(c_Days,$A16)="","",INDEX(c_Days,$A16))) | I16: =IF($A16="","",IF(INDEX(c_Mtgs,$A16)="","",INDEX(c_Mtgs,$A16))) -> 0 | J16: =IF($A16="","",INDEX(c_EvtNames,$A16)&"") | K16: =IF($A16="","",INDEX(c_Invested,$A16)&"") -> No | L16: =IF($A16="","",IF(INDEX(c_AUM,$A16)="","",INDEX(c_AUM,$A16))) | M16: =IF($A16="","",INDEX(c_Source,$A16)&"") -> Meeting List | N16: =IF($A16="","",INDEX(c_Notes,$A16)&"")
A17: =IFERROR(MATCH(ROW()-5,c_Seq,0),"") -> 12 | B17: =IF($A17="","",INDEX(c_Name,$A17)&"") -> Isaac Tang | C17: =IF($A17="","",INDEX(c_Firm,$A17)&"") -> Financial Alliance | D17: =IF($A17="","",INDEX(c_Type,$A17)&"") -> Adviser | E17: =IF($A17="","",INDEX(c_Email,$A17)&"") -> isaactang@fa.sg | F17: =IF($A17="","",INDEX(c_Met,$A17)&"") -> No | G17: =IF($A17="","",IF(INDEX(c_Date,$A17)="","",INDEX(c_Date,$A17))) | H17: =IF($A17="","",IF(INDEX(c_Days,$A17)="","",INDEX(c_Days,$A17))) | I17: =IF($A17="","",IF(INDEX(c_Mtgs,$A17)="","",INDEX(c_Mtgs,$A17))) -> 0 | J17: =IF($A17="","",INDEX(c_EvtNames,$A17)&"") -> May-26 Symposium | K17: =IF($A17="","",INDEX(c_Invested,$A17)&"") -> No | L17: =IF($A17="","",IF(INDEX(c_AUM,$A17)="","",INDEX(c_AUM,$A17))) | M17: =IF($A17="","",INDEX(c_Source,$A17)&"") -> Meeting List | N17: =IF($A17="","",INDEX(c_Notes,$A17)&"")
... A605: =IFERROR(MATCH(ROW()-5,c_Seq,0),"") | B605: =IF($A605="","",INDEX(c_Name,$A605)&"") | C605: =IF($A605="","",INDEX(c_Firm,$A605)&"") | D605: =IF($A605="","",INDEX(c_Type,$A605)&"") | E605: =IF($A605="","",INDEX(c_Email,$A605)&"") | F605: =IF($A605="","",INDEX(c_Met,$A605)&"") | G605: =IF($A605="","",IF(INDEX(c_Date,$A605)="","",INDEX(c_Date,$A605))) | H605: =IF($A605="","",IF(INDEX(c_Days,$A605)="","",INDEX(c_Days,$A605))) | I605: =IF($A605="","",IF(INDEX(c_Mtgs,$A605)="","",INDEX(c_Mtgs,$A605))) | J605: =IF($A605="","",INDEX(c_EvtNames,$A605)&"") | K605: =IF($A605="","",INDEX(c_Invested,$A605)&"") | L605: =IF($A605="","",IF(INDEX(c_AUM,$A605)="","",INDEX(c_AUM,$A605))) | M605: =IF($A605="","",INDEX(c_Source,$A605)&"") | N605: =IF($A605="","",INDEX(c_Notes,$A605)&"")

Sheet RawData
A1: ID | B1: Name | C1: Email | D1: Firm | E1: Contact Type | F1: Source | G1: Met? | H1: Last Meeting | I1: # Meetings | J1: Invested? | K1: AUM (S$) | L1: Email Sent | M1: LinkedIn Contacted | N1: =IF(Setup!$C$15="","Event 1 (free — name it in Setup)",Setup!$C$15) -> H2O AM IFA Symposium (October 2025) | O1: =IF(Setup!$C$16="","Event 2 (free — name it in Setup)",Setup!$C$16) -> 2nd Edition H2O AM IFA Symposium (May 2026) | P1: =IF(Setup!$C$17="","Event 3 (free — name it in Setup)",Setup!$C$17) -> Macro Lunch series | Q1: =IF(Setup!$C$18="","Event 4 (free — name it in Setup)",Setup!$C$18) -> Event 4 (free — name it in Setup) | R1: =IF(Setup!$C$19="","Event 5 (free — name it in Setup)",Setup!$C$19) -> Event 5 (free — name it in Setup) | S1: Notes | T1: # Events Invited | U1: # Events Attended | V1: Events Attended | W1: Days Since Meeting | X1: Engagement | Y1: _sort | Z1: _pass | AA1: _seq | AB1: _followup
A2: =IF($B2="","",COUNTA($B$2:$B2)) -> 1 | B2: Ang hui | C2: anghuichin@awfa.com.sg | D2: Alpha Wealth | E2: Adviser | F2: Meeting List | G2: No | I2: 0 | J2: No | N2: Not Invited | O2: No Show | P2: Not Invited | Q2: Not Invited | R2: Not Invited | T2: =IF($B2="","",COUNTA($N2:$R2)-COUNTIF($N2:$R2,"Not Invited")) -> 1 | U2: =IF($B2="","",COUNTIF($N2:$R2,"Attended")) -> 0 | V2: =IF($B2="","",_xlfn.TEXTJOIN(", ",TRUE(),IF($N2="Attended",Setup!$D$15,""),IF($O2="Attended",Setup!$D$16,""),IF($P2="Attended",Setup!$D$17,""),IF($Q2="Attended",Setup!$D$18,""),IF($R2="Attended",Setup!$D$19,""))) | W2: =IF(OR($B2="",NOT(ISNUMBER($H2))),"",TODAY()-$H2) | X2: =IF($B2="","",IF($U2>0,"Event attendee",IF($G2="Yes","Met (no event)",IF($T2>0,"Invited only",IF(OR($L2="Yes",$M2="Yes"),"Contacted only","Not yet contacted"))))) -> Invited only | Y2: =IF($B2="","",COUNTIF(c_Firm,"<"&$D2)+COUNTIFS(c_Firm,$D2,c_Name,"<"&$B2)+COUNTIFS($D$2:$D2,$D2,$B$2:$B2,$B2)) -> 1 | Z2: =IF($B2="","",IF(AND(OR(Contacts!$C$3="(All)",$D2=Contacts!$C$3),OR(Contacts!$E$3="(All)",$G2=Contacts!$E$3),OR(Contacts!$G$3="(All)",ISNUMBER(SEARCH(Contacts!$G$3,$V2))),OR(Contacts!$I$3="(All)",$X2=Contacts!$I$3),OR(Contacts!$K$3="",ISNUMBER(SEARCH(Contacts!$K$3,$B2&" "&$C2&" "&$D2&" "&$S2)))),1,0)) -> 1 | AA2: =IF($Z2=1,COUNTIFS(c_Pass,1,c_Sort,"<="&$Y2),"") -> 1 | AB2: =IF(OR($G2<>"Yes",NOT(ISNUMBER($H2))),"",COUNTIFS(c_Met,"Yes",c_Date,"<"&$H2)+COUNTIFS($G$2:$G2,"Yes",$H$2:$H2,$H2))
A3: =IF($B3="","",COUNTA($B$2:$B3)) -> 2 | B3: Jason Yin | C3: jasonyin@awfa.com.sg | D3: Alpha Wealth | E3: Adviser | F3: Meeting List | G3: No | I3: 0 | J3: No | N3: Not Invited | O3: Attended | P3: Not Invited | Q3: Not Invited | R3: Not Invited | T3: =IF($B3="","",COUNTA($N3:$R3)-COUNTIF($N3:$R3,"Not Invited")) -> 1 | U3: =IF($B3="","",COUNTIF($N3:$R3,"Attended")) -> 1 | V3: =IF($B3="","",_xlfn.TEXTJOIN(", ",TRUE(),IF($N3="Attended",Setup!$D$15,""),IF($O3="Attended",Setup!$D$16,""),IF($P3="Attended",Setup!$D$17,""),IF($Q3="Attended",Setup!$D$18,""),IF($R3="Attended",Setup!$D$19,""))) -> May-26 Symposium | W3: =IF(OR($B3="",NOT(ISNUMBER($H3))),"",TODAY()-$H3) | X3: =IF($B3="","",IF($U3>0,"Event attendee",IF($G3="Yes","Met (no event)",IF($T3>0,"Invited only",IF(OR($L3="Yes",$M3="Yes"),"Contacted only","Not yet contacted"))))) -> Event attendee | Y3: =IF($B3="","",COUNTIF(c_Firm,"<"&$D3)+COUNTIFS(c_Firm,$D3,c_Name,"<"&$B3)+COUNTIFS($D$2:$D3,$D3,$B$2:$B3,$B3)) -> 2 | Z3: =IF($B3="","",IF(AND(OR(Contacts!$C$3="(All)",$D3=Contacts!$C$3),OR(Contacts!$E$3="(All)",$G3=Contacts!$E$3),OR(Contacts!$G$3="(All)",ISNUMBER(SEARCH(Contacts!$G$3,$V3))),OR(Contacts!$I$3="(All)",$X3=Contacts!$I$3),OR(Contacts!$K$3="",ISNUMBER(SEARCH(Contacts!$K$3,$B3&" "&$C3&" "&$D3&" "&$S3)))),1,0)) -> 1 | AA3: =IF($Z3=1,COUNTIFS(c_Pass,1,c_Sort,"<="&$Y3),"") -> 2 | AB3: =IF(OR($G3<>"Yes",NOT(ISNUMBER($H3))),"",COUNTIFS(c_Met,"Yes",c_Date,"<"&$H3)+COUNTIFS($G$2:$G3,"Yes",$H$2:$H3,$H3))
A4: =IF($B4="","",COUNTA($B$2:$B4)) -> 3 | B4: Lee Jia Hao | C4: leejiahao@awfa.com.sg | D4: Alpha Wealth | E4: Adviser | F4: Meeting List | G4: No | I4: 0 | J4: No | N4: Not Invited | O4: Attended | P4: Not Invited | Q4: Not Invited | R4: Not Invited | T4: =IF($B4="","",COUNTA($N4:$R4)-COUNTIF($N4:$R4,"Not Invited")) -> 1 | U4: =IF($B4="","",COUNTIF($N4:$R4,"Attended")) -> 1 | V4: =IF($B4="","",_xlfn.TEXTJOIN(", ",TRUE(),IF($N4="Attended",Setup!$D$15,""),IF($O4="Attended",Setup!$D$16,""),IF($P4="Attended",Setup!$D$17,""),IF($Q4="Attended",Setup!$D$18,""),IF($R4="Attended",Setup!$D$19,""))) -> May-26 Symposium | W4: =IF(OR($B4="",NOT(ISNUMBER($H4))),"",TODAY()-$H4) | X4: =IF($B4="","",IF($U4>0,"Event attendee",IF($G4="Yes","Met (no event)",IF($T4>0,"Invited only",IF(OR($L4="Yes",$M4="Yes"),"Contacted only","Not yet contacted"))))) -> Event attendee | Y4: =IF($B4="","",COUNTIF(c_Firm,"<"&$D4)+COUNTIFS(c_Firm,$D4,c_Name,"<"&$B4)+COUNTIFS($D$2:$D4,$D4,$B$2:$B4,$B4)) -> 3 | Z4: =IF($B4="","",IF(AND(OR(Contacts!$C$3="(All)",$D4=Contacts!$C$3),OR(Contacts!$E$3="(All)",$G4=Contacts!$E$3),OR(Contacts!$G$3="(All)",ISNUMBER(SEARCH(Contacts!$G$3,$V4))),OR(Contacts!$I$3="(All)",$X4=Contacts!$I$3),OR(Contacts!$K$3="",ISNUMBER(SEARCH(Contacts!$K$3,$B4&" "&$C4&" "&$D4&" "&$S4)))),1,0)) -> 1 | AA4: =IF($Z4=1,COUNTIFS(c_Pass,1,c_Sort,"<="&$Y4),"") -> 3 | AB4: =IF(OR($G4<>"Yes",NOT(ISNUMBER($H4))),"",COUNTIFS(c_Met,"Yes",c_Date,"<"&$H4)+COUNTIFS($G$2:$G4,"Yes",$H$2:$H4,$H4))
A5: =IF($B5="","",COUNTA($B$2:$B5)) -> 4 | B5: Alvin Low | C5: alvinlow@fapl.sg | D5: Financial Alliance | E5: Adviser | F5: Meeting List + ILP Data | G5: Yes | H5: 45918 | I5: 1 | J5: No | K5: 5000000 | N5: Declined | O5: No Reply | P5: Not Invited | Q5: Not Invited | R5: Not Invited | T5: =IF($B5="","",COUNTA($N5:$R5)-COUNTIF($N5:$R5,"Not Invited")) -> 2 | U5: =IF($B5="","",COUNTIF($N5:$R5,"Attended")) -> 0 | V5: =IF($B5="","",_xlfn.TEXTJOIN(", ",TRUE(),IF($N5="Attended",Setup!$D$15,""),IF($O5="Attended",Setup!$D$16,""),IF($P5="Attended",Setup!$D$17,""),IF($Q5="Attended",Setup!$D$18,""),IF($R5="Attended",Setup!$D$19,""))) | W5: =IF(OR($B5="",NOT(ISNUMBER($H5))),"",TODAY()-$H5) -> 323 | X5: =IF($B5="","",IF($U5>0,"Event attendee",IF($G5="Yes","Met (no event)",IF($T5>0,"Invited only",IF(OR($L5="Yes",$M5="Yes"),"Contacted only","Not yet contacted"))))) -> Met (no event) | Y5: =IF($B5="","",COUNTIF(c_Firm,"<"&$D5)+COUNTIFS(c_Firm,$D5,c_Name,"<"&$B5)+COUNTIFS($D$2:$D5,$D5,$B$2:$B5,$B5)) -> 4 | Z5: =IF($B5="","",IF(AND(OR(Contacts!$C$3="(All)",$D5=Contacts!$C$3),OR(Contacts!$E$3="(All)",$G5=Contacts!$E$3),OR(Contacts!$G$3="(All)",ISNUMBER(SEARCH(Contacts!$G$3,$V5))),OR(Contacts!$I$3="(All)",$X5=Contacts!$I$3),OR(Contacts!$K$3="",ISNUMBER(SEARCH(Contacts!$K$3,$B5&" "&$C5&" "&$D5&" "&$S5)))),1,0)) -> 1 | AA5: =IF($Z5=1,COUNTIFS(c_Pass,1,c_Sort,"<="&$Y5),"") -> 4 | AB5: =IF(OR($G5<>"Yes",NOT(ISNUMBER($H5))),"",COUNTIFS(c_Met,"Yes",c_Date,"<"&$H5)+COUNTIFS($G$2:$G5,"Yes",$H$2:$H5,$H5)) -> 14
A6: =IF($B6="","",COUNTA($B$2:$B6)) -> 5 | B6: Chenise Lim | C6: cheniselim@fapl.sg | D6: Financial Alliance | E6: Adviser | F6: Meeting List + ILP Data | G6: Yes | H6: 45923 | I6: 1 | J6: No | K6: 32000000 | N6: Declined | O6: Declined | P6: Not Invited | Q6: Not Invited | R6: Not Invited | S6: May-26: not available | T6: =IF($B6="","",COUNTA($N6:$R6)-COUNTIF($N6:$R6,"Not Invited")) -> 2 | U6: =IF($B6="","",COUNTIF($N6:$R6,"Attended")) -> 0 | V6: =IF($B6="","",_xlfn.TEXTJOIN(", ",TRUE(),IF($N6="Attended",Setup!$D$15,""),IF($O6="Attended",Setup!$D$16,""),IF($P6="Attended",Setup!$D$17,""),IF($Q6="Attended",Setup!$D$18,""),IF($R6="Attended",Setup!$D$19,""))) | W6: =IF(OR($B6="",NOT(ISNUMBER($H6))),"",TODAY()-$H6) -> 318 | X6: =IF($B6="","",IF($U6>0,"Event attendee",IF($G6="Yes","Met (no event)",IF($T6>0,"Invited only",IF(OR($L6="Yes",$M6="Yes"),"Contacted only","Not yet contacted"))))) -> Met (no event) | Y6: =IF($B6="","",COUNTIF(c_Firm,"<"&$D6)+COUNTIFS(c_Firm,$D6,c_Name,"<"&$B6)+COUNTIFS($D$2:$D6,$D6,$B$2:$B6,$B6)) -> 5 | Z6: =IF($B6="","",IF(AND(OR(Contacts!$C$3="(All)",$D6=Contacts!$C$3),OR(Contacts!$E$3="(All)",$G6=Contacts!$E$3),OR(Contacts!$G$3="(All)",ISNUMBER(SEARCH(Contacts!$G$3,$V6))),OR(Contacts!$I$3="(All)",$X6=Contacts!$I$3),OR(Contacts!$K$3="",ISNUMBER(SEARCH(Contacts!$K$3,$B6&" "&$C6&" "&$D6&" "&$S6)))),1,0)) -> 1 | AA6: =IF($Z6=1,COUNTIFS(c_Pass,1,c_Sort,"<="&$Y6),"") -> 5 | AB6: =IF(OR($G6<>"Yes",NOT(ISNUMBER($H6))),"",COUNTIFS(c_Met,"Yes",c_Date,"<"&$H6)+COUNTIFS($G$2:$G6,"Yes",$H$2:$H6,$H6)) -> 18
A7: =IF($B7="","",COUNTA($B$2:$B7)) -> 6 | B7: Edmond Goh | C7: edmondgoh@fapl.sg | D7: Financial Alliance | E7: Adviser | F7: Meeting List + ILP Data | G7: Yes | H7: 45918 | I7: 1 | J7: No | K7: 6000000 | N7: Attended | O7: Attended | P7: Not Invited | Q7: Not Invited | R7: Not Invited | T7: =IF($B7="","",COUNTA($N7:$R7)-COUNTIF($N7:$R7,"Not Invited")) -> 2 | U7: =IF($B7="","",COUNTIF($N7:$R7,"Attended")) -> 2 | V7: =IF($B7="","",_xlfn.TEXTJOIN(", ",TRUE(),IF($N7="Attended",Setup!$D$15,""),IF($O7="Attended",Setup!$D$16,""),IF($P7="Attended",Setup!$D$17,""),IF($Q7="Attended",Setup!$D$18,""),IF($R7="Attended",Setup!$D$19,""))) -> Oct-25 Symposium, May-26 Symposium | W7: =IF(OR($B7="",NOT(ISNUMBER($H7))),"",TODAY()-$H7) -> 323 | X7: =IF($B7="","",IF($U7>0,"Event attendee",IF($G7="Yes","Met (no event)",IF($T7>0,"Invited only",IF(OR($L7="Yes",$M7="Yes"),"Contacted only","Not yet contacted"))))) -> Event attendee | Y7: =IF($B7="","",COUNTIF(c_Firm,"<"&$D7)+COUNTIFS(c_Firm,$D7,c_Name,"<"&$B7)+COUNTIFS($D$2:$D7,$D7,$B$2:$B7,$B7)) -> 6 | Z7: =IF($B7="","",IF(AND(OR(Contacts!$C$3="(All)",$D7=Contacts!$C$3),OR(Contacts!$E$3="(All)",$G7=Contacts!$E$3),OR(Contacts!$G$3="(All)",ISNUMBER(SEARCH(Contacts!$G$3,$V7))),OR(Contacts!$I$3="(All)",$X7=Contacts!$I$3),OR(Contacts!$K$3="",ISNUMBER(SEARCH(Contacts!$K$3,$B7&" "&$C7&" "&$D7&" "&$S7)))),1,0)) -> 1 | AA7: =IF($Z7=1,COUNTIFS(c_Pass,1,c_Sort,"<="&$Y7),"") -> 6 | AB7: =IF(OR($G7<>"Yes",NOT(ISNUMBER($H7))),"",COUNTIFS(c_Met,"Yes",c_Date,"<"&$H7)+COUNTIFS($G$2:$G7,"Yes",$H$2:$H7,$H7)) -> 15
A8: =IF($B8="","",COUNTA($B$2:$B8)) -> 7 | B8: Edwin Tan | C8: edwintan@fapl.sg | D8: Financial Alliance | E8: Adviser | F8: Meeting List | G8: No | I8: 0 | J8: No | N8: Not Invited | O8: Attended | P8: Not Invited | Q8: Not Invited | R8: Not Invited | T8: =IF($B8="","",COUNTA($N8:$R8)-COUNTIF($N8:$R8,"Not Invited")) -> 1 | U8: =IF($B8="","",COUNTIF($N8:$R8,"Attended")) -> 1 | V8: =IF($B8="","",_xlfn.TEXTJOIN(", ",TRUE(),IF($N8="Attended",Setup!$D$15,""),IF($O8="Attended",Setup!$D$16,""),IF($P8="Attended",Setup!$D$17,""),IF($Q8="Attended",Setup!$D$18,""),IF($R8="Attended",Setup!$D$19,""))) -> May-26 Symposium | W8: =IF(OR($B8="",NOT(ISNUMBER($H8))),"",TODAY()-$H8) | X8: =IF($B8="","",IF($U8>0,"Event attendee",IF($G8="Yes","Met (no event)",IF($T8>0,"Invited only",IF(OR($L8="Yes",$M8="Yes"),"Contacted only","Not yet contacted"))))) -> Event attendee | Y8: =IF($B8="","",COUNTIF(c_Firm,"<"&$D8)+COUNTIFS(c_Firm,$D8,c_Name,"<"&$B8)+COUNTIFS($D$2:$D8,$D8,$B$2:$B8,$B8)) -> 7 | Z8: =IF($B8="","",IF(AND(OR(Contacts!$C$3="(All)",$D8=Contacts!$C$3),OR(Contacts!$E$3="(All)",$G8=Contacts!$E$3),OR(Contacts!$G$3="(All)",ISNUMBER(SEARCH(Contacts!$G$3,$V8))),OR(Contacts!$I$3="(All)",$X8=Contacts!$I$3),OR(Contacts!$K$3="",ISNUMBER(SEARCH(Contacts!$K$3,$B8&" "&$C8&" "&$D8&" "&$S8)))),1,0)) -> 1 | AA8: =IF($Z8=1,COUNTIFS(c_Pass,1,c_Sort,"<="&$Y8),"") -> 7 | AB8: =IF(OR($G8<>"Yes",NOT(ISNUMBER($H8))),"",COUNTIFS(c_Met,"Yes",c_Date,"<"&$H8)+COUNTIFS($G$2:$G8,"Yes",$H$2:$H8,$H8))
A9: =IF($B9="","",COUNTA($B$2:$B9)) -> 8 | B9: Francis Hoan | C9: francishoan@fapl.sg | D9: Financial Alliance | E9: Adviser | F9: Meeting List | G9: No | I9: 0 | J9: No | N9: Not Invited | O9: Declined | P9: Not Invited | Q9: Not Invited | R9: Not Invited | T9: =IF($B9="","",COUNTA($N9:$R9)-COUNTIF($N9:$R9,"Not Invited")) -> 1 | U9: =IF($B9="","",COUNTIF($N9:$R9,"Attended")) -> 0 | V9: =IF($B9="","",_xlfn.TEXTJOIN(", ",TRUE(),IF($N9="Attended",Setup!$D$15,""),IF($O9="Attended",Setup!$D$16,""),IF($P9="Attended",Setup!$D$17,""),IF($Q9="Attended",Setup!$D$18,""),IF($R9="Attended",Setup!$D$19,""))) | W9: =IF(OR($B9="",NOT(ISNUMBER($H9))),"",TODAY()-$H9) | X9: =IF($B9="","",IF($U9>0,"Event attendee",IF($G9="Yes","Met (no event)",IF($T9>0,"Invited only",IF(OR($L9="Yes",$M9="Yes"),"Contacted only","Not yet contacted"))))) -> Invited only | Y9: =IF($B9="","",COUNTIF(c_Firm,"<"&$D9)+COUNTIFS(c_Firm,$D9,c_Name,"<"&$B9)+COUNTIFS($D$2:$D9,$D9,$B$2:$B9,$B9)) -> 8 | Z9: =IF($B9="","",IF(AND(OR(Contacts!$C$3="(All)",$D9=Contacts!$C$3),OR(Contacts!$E$3="(All)",$G9=Contacts!$E$3),OR(Contacts!$G$3="(All)",ISNUMBER(SEARCH(Contacts!$G$3,$V9))),OR(Contacts!$I$3="(All)",$X9=Contacts!$I$3),OR(Contacts!$K$3="",ISNUMBER(SEARCH(Contacts!$K$3,$B9&" "&$C9&" "&$D9&" "&$S9)))),1,0)) -> 1 | AA9: =IF($Z9=1,COUNTIFS(c_Pass,1,c_Sort,"<="&$Y9),"") -> 8 | AB9: =IF(OR($G9<>"Yes",NOT(ISNUMBER($H9))),"",COUNTIFS(c_Met,"Yes",c_Date,"<"&$H9)+COUNTIFS($G$2:$G9,"Yes",$H$2:$H9,$H9))
A10: =IF($B10="","",COUNTA($B$2:$B10)) -> 9 | B10: Gary Lim | C10: garylim@fapl.sg | D10: Financial Alliance | E10: Adviser | F10: Meeting List + ILP Data | G10: No | I10: 0 | J10: No | K10: 10000000 | N10: Attended | O10: Declined | P10: Not Invited | Q10: Not Invited | R10: Not Invited | T10: =IF($B10="","",COUNTA($N10:$R10)-COUNTIF($N10:$R10,"Not Invited")) -> 2 | U10: =IF($B10="","",COUNTIF($N10:$R10,"Attended")) -> 1 | V10: =IF($B10="","",_xlfn.TEXTJOIN(", ",TRUE(),IF($N10="Attended",Setup!$D$15,""),IF($O10="Attended",Setup!$D$16,""),IF($P10="Attended",Setup!$D$17,""),IF($Q10="Attended",Setup!$D$18,""),IF($R10="Attended",Setup!$D$19,""))) -> Oct-25 Symposium | W10: =IF(OR($B10="",NOT(ISNUMBER($H10))),"",TODAY()-$H10) | X10: =IF($B10="","",IF($U10>0,"Event attendee",IF($G10="Yes","Met (no event)",IF($T10>0,"Invited only",IF(OR($L10="Yes",$M10="Yes"),"Contacted only","Not yet contacted"))))) -> Event attendee | Y10: =IF($B10="","",COUNTIF(c_Firm,"<"&$D10)+COUNTIFS(c_Firm,$D10,c_Name,"<"&$B10)+COUNTIFS($D$2:$D10,$D10,$B$2:$B10,$B10)) -> 9 | Z10: =IF($B10="","",IF(AND(OR(Contacts!$C$3="(All)",$D10=Contacts!$C$3),OR(Contacts!$E$3="(All)",$G10=Contacts!$E$3),OR(Contacts!$G$3="(All)",ISNUMBER(SEARCH(Contacts!$G$3,$V10))),OR(Contacts!$I$3="(All)",$X10=Contacts!$I$3),OR(Contacts!$K$3="",ISNUMBER(SEARCH(Contacts!$K$3,$B10&" "&$C10&" "&$D10&" "&$S10)))),1,0)) -> 1 | AA10: =IF($Z10=1,COUNTIFS(c_Pass,1,c_Sort,"<="&$Y10),"") -> 9 | AB10: =IF(OR($G10<>"Yes",NOT(ISNUMBER($H10))),"",COUNTIFS(c_Met,"Yes",c_Date,"<"&$H10)+COUNTIFS($G$2:$G10,"Yes",$H$2:$H10,$H10))
A11: =IF($B11="","",COUNTA($B$2:$B11)) -> 10 | B11: Guek Choo | C11: guekchoo@fapl.sg | D11: Financial Alliance | E11: Adviser | F11: Meeting List + ILP Data | G11: Yes | H11: 45923 | I11: 1 | J11: No | K11: 4000000 | N11: Declined | O11: Declined | P11: Not Invited | Q11: Not Invited | R11: Not Invited | S11: May-26: not available | T11: =IF($B11="","",COUNTA($N11:$R11)-COUNTIF($N11:$R11,"Not Invited")) -> 2 | U11: =IF($B11="","",COUNTIF($N11:$R11,"Attended")) -> 0 | V11: =IF($B11="","",_xlfn.TEXTJOIN(", ",TRUE(),IF($N11="Attended",Setup!$D$15,""),IF($O11="Attended",Setup!$D$16,""),IF($P11="Attended",Setup!$D$17,""),IF($Q11="Attended",Setup!$D$18,""),IF($R11="Attended",Setup!$D$19,""))) | W11: =IF(OR($B11="",NOT(ISNUMBER($H11))),"",TODAY()-$H11) -> 318 | X11: =IF($B11="","",IF($U11>0,"Event attendee",IF($G11="Yes","Met (no event)",IF($T11>0,"Invited only",IF(OR($L11="Yes",$M11="Yes"),"Contacted only","Not yet contacted"))))) -> Met (no event) | Y11: =IF($B11="","",COUNTIF(c_Firm,"<"&$D11)+COUNTIFS(c_Firm,$D11,c_Name,"<"&$B11)+COUNTIFS($D$2:$D11,$D11,$B$2:$B11,$B11)) -> 10 | Z11: =IF($B11="","",IF(AND(OR(Contacts!$C$3="(All)",$D11=Contacts!$C$3),OR(Contacts!$E$3="(All)",$G11=Contacts!$E$3),OR(Contacts!$G$3="(All)",ISNUMBER(SEARCH(Contacts!$G$3,$V11))),OR(Contacts!$I$3="(All)",$X11=Contacts!$I$3),OR(Contacts!$K$3="",ISNUMBER(SEARCH(Contacts!$K$3,$B11&" "&$C11&" "&$D11&" "&$S11)))),1,0)) -> 1 | AA11: =IF($Z11=1,COUNTIFS(c_Pass,1,c_Sort,"<="&$Y11),"") -> 10 | AB11: =IF(OR($G11<>"Yes",NOT(ISNUMBER($H11))),"",COUNTIFS(c_Met,"Yes",c_Date,"<"&$H11)+COUNTIFS($G$2:$G11,"Yes",$H$2:$H11,$H11)) -> 19
A12: =IF($B12="","",COUNTA($B$2:$B12)) -> 11 | B12: Hadi Wijaya | C12: hadiwijaya@fapl.sg | D12: Financial Alliance | E12: Adviser | F12: Meeting List | G12: No | I12: 0 | J12: No | N12: Not Invited | O12: No Reply | P12: Not Invited | Q12: Not Invited | R12: Not Invited | T12: =IF($B12="","",COUNTA($N12:$R12)-COUNTIF($N12:$R12,"Not Invited")) -> 1 | U12: =IF($B12="","",COUNTIF($N12:$R12,"Attended")) -> 0 | V12: =IF($B12="","",_xlfn.TEXTJOIN(", ",TRUE(),IF($N12="Attended",Setup!$D$15,""),IF($O12="Attended",Setup!$D$16,""),IF($P12="Attended",Setup!$D$17,""),IF($Q12="Attended",Setup!$D$18,""),IF($R12="Attended",Setup!$D$19,""))) | W12: =IF(OR($B12="",NOT(ISNUMBER($H12))),"",TODAY()-$H12) | X12: =IF($B12="","",IF($U12>0,"Event attendee",IF($G12="Yes","Met (no event)",IF($T12>0,"Invited only",IF(OR($L12="Yes",$M12="Yes"),"Contacted only","Not yet contacted"))))) -> Invited only | Y12: =IF($B12="","",COUNTIF(c_Firm,"<"&$D12)+COUNTIFS(c_Firm,$D12,c_Name,"<"&$B12)+COUNTIFS($D$2:$D12,$D12,$B$2:$B12,$B12)) -> 11 | Z12: =IF($B12="","",IF(AND(OR(Contacts!$C$3="(All)",$D12=Contacts!$C$3),OR(Contacts!$E$3="(All)",$G12=Contacts!$E$3),OR(Contacts!$G$3="(All)",ISNUMBER(SEARCH(Contacts!$G$3,$V12))),OR(Contacts!$I$3="(All)",$X12=Contacts!$I$3),OR(Contacts!$K$3="",ISNUMBER(SEARCH(Contacts!$K$3,$B12&" "&$C12&" "&$D12&" "&$S12)))),1,0)) -> 1 | AA12: =IF($Z12=1,COUNTIFS(c_Pass,1,c_Sort,"<="&$Y12),"") -> 11 | AB12: =IF(OR($G12<>"Yes",NOT(ISNUMBER($H12))),"",COUNTIFS(c_Met,"Yes",c_Date,"<"&$H12)+COUNTIFS($G$2:$G12,"Yes",$H$2:$H12,$H12))
A13: =IF($B13="","",COUNTA($B$2:$B13)) -> 12 | B13: Isaac Tang | C13: isaactang@fa.sg | D13: Financial Alliance | E13: Adviser | F13: Meeting List | G13: No | I13: 0 | J13: No | N13: Not Invited | O13: Attended | P13: Not Invited | Q13: Not Invited | R13: Not Invited | T13: =IF($B13="","",COUNTA($N13:$R13)-COUNTIF($N13:$R13,"Not Invited")) -> 1 | U13: =IF($B13="","",COUNTIF($N13:$R13,"Attended")) -> 1 | V13: =IF($B13="","",_xlfn.TEXTJOIN(", ",TRUE(),IF($N13="Attended",Setup!$D$15,""),IF($O13="Attended",Setup!$D$16,""),IF($P13="Attended",Setup!$D$17,""),IF($Q13="Attended",Setup!$D$18,""),IF($R13="Attended",Setup!$D$19,""))) -> May-26 Symposium | W13: =IF(OR($B13="",NOT(ISNUMBER($H13))),"",TODAY()-$H13) | X13: =IF($B13="","",IF($U13>0,"Event attendee",IF($G13="Yes","Met (no event)",IF($T13>0,"Invited only",IF(OR($L13="Yes",$M13="Yes"),"Contacted only","Not yet contacted"))))) -> Event attendee | Y13: =IF($B13="","",COUNTIF(c_Firm,"<"&$D13)+COUNTIFS(c_Firm,$D13,c_Name,"<"&$B13)+COUNTIFS($D$2:$D13,$D13,$B$2:$B13,$B13)) -> 12 | Z13: =IF($B13="","",IF(AND(OR(Contacts!$C$3="(All)",$D13=Contacts!$C$3),OR(Contacts!$E$3="(All)",$G13=Contacts!$E$3),OR(Contacts!$G$3="(All)",ISNUMBER(SEARCH(Contacts!$G$3,$V13))),OR(Contacts!$I$3="(All)",$X13=Contacts!$I$3),OR(Contacts!$K$3="",ISNUMBER(SEARCH(Contacts!$K$3,$B13&" "&$C13&" "&$D13&" "&$S13)))),1,0)) -> 1 | AA13: =IF($Z13=1,COUNTIFS(c_Pass,1,c_Sort,"<="&$Y13),"") -> 12 | AB13: =IF(OR($G13<>"Yes",NOT(ISNUMBER($H13))),"",COUNTIFS(c_Met,"Yes",c_Date,"<"&$H13)+COUNTIFS($G$2:$G13,"Yes",$H$2:$H13,$H13))
A14: =IF($B14="","",COUNTA($B$2:$B14)) -> 13 | B14: Kelvin Teng | C14: kelvinteng@fapl.sg | D14: Financial Alliance | E14: Adviser | F14: Meeting List | G14: No | I14: 0 | J14: No | N14: Not Invited | O14: Attended | P14: Not Invited | Q14: Not Invited | R14: Not Invited | T14: =IF($B14="","",COUNTA($N14:$R14)-COUNTIF($N14:$R14,"Not Invited")) -> 1 | U14: =IF($B14="","",COUNTIF($N14:$R14,"Attended")) -> 1 | V14: =IF($B14="","",_xlfn.TEXTJOIN(", ",TRUE(),IF($N14="Attended",Setup!$D$15,""),IF($O14="Attended",Setup!$D$16,""),IF($P14="Attended",Setup!$D$17,""),IF($Q14="Attended",Setup!$D$18,""),IF($R14="Attended",Setup!$D$19,""))) -> May-26 Symposium | W14: =IF(OR($B14="",NOT(ISNUMBER($H14))),"",TODAY()-$H14) | X14: =IF($B14="","",IF($U14>0,"Event attendee",IF($G14="Yes","Met (no event)",IF($T14>0,"Invited only",IF(OR($L14="Yes",$M14="Yes"),"Contacted only","Not yet contacted"))))) -> Event attendee | Y14: =IF($B14="","",COUNTIF(c_Firm,"<"&$D14)+COUNTIFS(c_Firm,$D14,c_Name,"<"&$B14)+COUNTIFS($D$2:$D14,$D14,$B$2:$B14,$B14)) -> 13 | Z14: =IF($B14="","",IF(AND(OR(Contacts!$C$3="(All)",$D14=Contacts!$C$3),OR(Contacts!$E$3="(All)",$G14=Contacts!$E$3),OR(Contacts!$G$3="(All)",ISNUMBER(SEARCH(Contacts!$G$3,$V14))),OR(Contacts!$I$3="(All)",$X14=Contacts!$I$3),OR(Contacts!$K$3="",ISNUMBER(SEARCH(Contacts!$K$3,$B14&" "&$C14&" "&$D14&" "&$S14)))),1,0)) -> 1 | AA14: =IF($Z14=1,COUNTIFS(c_Pass,1,c_Sort,"<="&$Y14),"") -> 13 | AB14: =IF(OR($G14<>"Yes",NOT(ISNUMBER($H14))),"",COUNTIFS(c_Met,"Yes",c_Date,"<"&$H14)+COUNTIFS($G$2:$G14,"Yes",$H$2:$H14,$H14))
A15: =IF($B15="","",COUNTA($B$2:$B15)) -> 14 | B15: Khairuddin Sukor | C15: khairuddin@fapl.sg | D15: Financial Alliance | E15: Adviser | F15: Meeting List + ILP Data | G15: Yes | H15: 45919 | I15: 1 | J15: No | K15: 5000000 | N15: Attended | O15: Declined | P15: Not Invited | Q15: Not Invited | R15: Not Invited | T15: =IF($B15="","",COUNTA($N15:$R15)-COUNTIF($N15:$R15,"Not Invited")) -> 2 | U15: =IF($B15="","",COUNTIF($N15:$R15,"Attended")) -> 1 | V15: =IF($B15="","",_xlfn.TEXTJOIN(", ",TRUE(),IF($N15="Attended",Setup!$D$15,""),IF($O15="Attended",Setup!$D$16,""),IF($P15="Attended",Setup!$D$17,""),IF($Q15="Attended",Setup!$D$18,""),IF($R15="Attended",Setup!$D$19,""))) -> Oct-25 Symposium | W15: =IF(OR($B15="",NOT(ISNUMBER($H15))),"",TODAY()-$H15) -> 322 | X15: =IF($B15="","",IF($U15>0,"Event attendee",IF($G15="Yes","Met (no event)",IF($T15>0,"Invited only",IF(OR($L15="Yes",$M15="Yes"),"Contacted only","Not yet contacted"))))) -> Event attendee | Y15: =IF($B15="","",COUNTIF(c_Firm,"<"&$D15)+COUNTIFS(c_Firm,$D15,c_Name,"<"&$B15)+COUNTIFS($D$2:$D15,$D15,$B$2:$B15,$B15)) -> 14 | Z15: =IF($B15="","",IF(AND(OR(Contacts!$C$3="(All)",$D15=Contacts!$C$3),OR(Contacts!$E$3="(All)",$G15=Contacts!$E$3),OR(Contacts!$G$3="(All)",ISNUMBER(SEARCH(Contacts!$G$3,$V15))),OR(Contacts!$I$3="(All)",$X15=Contacts!$I$3),OR(Contacts!$K$3="",ISNUMBER(SEARCH(Contacts!$K$3,$B15&" "&$C15&" "&$D15&" "&$S15)))),1,0)) -> 1 | AA15: =IF($Z15=1,COUNTIFS(c_Pass,1,c_Sort,"<="&$Y15),"") -> 14 | AB15: =IF(OR($G15<>"Yes",NOT(ISNUMBER($H15))),"",COUNTIFS(c_Met,"Yes",c_Date,"<"&$H15)+COUNTIFS($G$2:$G15,"Yes",$H$2:$H15,$H15)) -> 16
A16: =IF($B16="","",COUNTA($B$2:$B16)) -> 15 | B16: Mithun Malani | C16: mithunmalani@fapl.sg | D16: Financial Alliance | E16: Adviser | F16: Meeting List + ILP Data | G16: Yes | H16: 45965 | I16: 1 | J16: No | K16: 3000000 | N16: No Reply | O16: Attended | P16: Not Invited | Q16: Not Invited | R16: Not Invited | T16: =IF($B16="","",COUNTA($N16:$R16)-COUNTIF($N16:$R16,"Not Invited")) -> 2 | U16: =IF($B16="","",COUNTIF($N16:$R16,"Attended")) -> 1 | V16: =IF($B16="","",_xlfn.TEXTJOIN(", ",TRUE(),IF($N16="Attended",Setup!$D$15,""),IF($O16="Attended",Setup!$D$16,""),IF($P16="Attended",Setup!$D$17,""),IF($Q16="Attended",Setup!$D$18,""),IF($R16="Attended",Setup!$D$19,""))) -> May-26 Symposium | W16: =IF(OR($B16="",NOT(ISNUMBER($H16))),"",TODAY()-$H16) -> 276 | X16: =IF($B16="","",IF($U16>0,"Event attendee",IF($G16="Yes","Met (no event)",IF($T16>0,"Invited only",IF(OR($L16="Yes",$M16="Yes"),"Contacted only","Not yet contacted"))))) -> Event attendee | Y16: =IF($B16="","",COUNTIF(c_Firm,"<"&$D16)+COUNTIFS(c_Firm,$D16,c_Name,"<"&$B16)+COUNTIFS($D$2:$D16,$D16,$B$2:$B16,$B16)) -> 15 | Z16: =IF($B16="","",IF(AND(OR(Contacts!$C$3="(All)",$D16=Contacts!$C$3),OR(Contacts!$E$3="(All)",$G16=Contacts!$E$3),OR(Contacts!$G$3="(All)",ISNUMBER(SEARCH(Contacts!$G$3,$V16))),OR(Contacts!$I$3="(All)",$X16=Contacts!$I$3),OR(Contacts!$K$3="",ISNUMBER(SEARCH(Contacts!$K$3,$B16&" "&$C16&" "&$D16&" "&$S16)))),1,0)) -> 1 | AA16: =IF($Z16=1,COUNTIFS(c_Pass,1,c_Sort,"<="&$Y16),"") -> 15 | AB16: =IF(OR($G16<>"Yes",NOT(ISNUMBER($H16))),"",COUNTIFS(c_Met,"Yes",c_Date,"<"&$H16)+COUNTIFS($G$2:$G16,"Yes",$H$2:$H16,$H16)) -> 31
A17: =IF($B17="","",COUNTA($B$2:$B17)) -> 16 | B17: Nicholas Low | C17: lownicholas@fa.sg | D17: Financial Alliance | E17: Adviser | F17: Meeting List + ILP Data | G17: No | I17: 0 | J17: No | N17: Attended | O17: No Reply | P17: Not Invited | Q17: Not Invited | R17: Not Invited | S17: May-26: email bounced back; ILP: Investment | T17: =IF($B17="","",COUNTA($N17:$R17)-COUNTIF($N17:$R17,"Not Invited")) -> 2 | U17: =IF($B17="","",COUNTIF($N17:$R17,"Attended")) -> 1 | V17: =IF($B17="","",_xlfn.TEXTJOIN(", ",TRUE(),IF($N17="Attended",Setup!$D$15,""),IF($O17="Attended",Setup!$D$16,""),IF($P17="Attended",Setup!$D$17,""),IF($Q17="Attended",Setup!$D$18,""),IF($R17="Attended",Setup!$D$19,""))) -> Oct-25 Symposium | W17: =IF(OR($B17="",NOT(ISNUMBER($H17))),"",TODAY()-$H17) | X17: =IF($B17="","",IF($U17>0,"Event attendee",IF($G17="Yes","Met (no event)",IF($T17>0,"Invited only",IF(OR($L17="Yes",$M17="Yes"),"Contacted only","Not yet contacted"))))) -> Event attendee | Y17: =IF($B17="","",COUNTIF(c_Firm,"<"&$D17)+COUNTIFS(c_Firm,$D17,c_Name,"<"&$B17)+COUNTIFS($D$2:$D17,$D17,$B$2:$B17,$B17)) -> 16 | Z17: =IF($B17="","",IF(AND(OR(Contacts!$C$3="(All)",$D17=Contacts!$C$3),OR(Contacts!$E$3="(All)",$G17=Contacts!$E$3),OR(Contacts!$G$3="(All)",ISNUMBER(SEARCH(Contacts!$G$3,$V17))),OR(Contacts!$I$3="(All)",$X17=Contacts!$I$3),OR(Contacts!$K$3="",ISNUMBER(SEARCH(Contacts!$K$3,$B17&" "&$C17&" "&$D17&" "&$S17)))),1,0)) -> 1 | AA17: =IF($Z17=1,COUNTIFS(c_Pass,1,c_Sort,"<="&$Y17),"") -> 16 | AB17: =IF(OR($G17<>"Yes",NOT(ISNUMBER($H17))),"",COUNTIFS(c_Met,"Yes",c_Date,"<"&$H17)+COUNTIFS($G$2:$G17,"Yes",$H$2:$H17,$H17))
A18: =IF($B18="","",COUNTA($B$2:$B18)) -> 17 | B18: Norman Ngai | C18: normanngai@fapl.sg | D18: Financial Alliance | E18: Adviser | F18: Meeting List + ILP Data | G18: Yes | H18: 46043 | I18: 1 | J18: No | K18: 5000000 | N18: No Reply | O18: Declined | P18: Not Invited | Q18: Not Invited | R18: Not Invited | T18: =IF($B18="","",COUNTA($N18:$R18)-COUNTIF($N18:$R18,"Not Invited")) -> 2 | U18: =IF($B18="","",COUNTIF($N18:$R18,"Attended")) -> 0 | V18: =IF($B18="","",_xlfn.TEXTJOIN(", ",TRUE(),IF($N18="Attended",Setup!$D$15,""),IF($O18="Attended",Setup!$D$16,""),IF($P18="Attended",Setup!$D$17,""),IF($Q18="Attended",Setup!$D$18,""),IF($R18="Attended",Setup!$D$19,""))) | W18: =IF(OR($B18="",NOT(ISNUMBER($H18))),"",TODAY()-$H18) -> 198 | X18: =IF($B18="","",IF($U18>0,"Event attendee",IF($G18="Yes","Met (no event)",IF($T18>0,"Invited only",IF(OR($L18="Yes",$M18="Yes"),"Contacted only","Not yet contacted"))))) -> Met (no event) | Y18: =IF($B18="","",COUNTIF(c_Firm,"<"&$D18)+COUNTIFS(c_Firm,$D18,c_Name,"<"&$B18)+COUNTIFS($D$2:$D18,$D18,$B$2:$B18,$B18)) -> 17 | Z18: =IF($B18="","",IF(AND(OR(Contacts!$C$3="(All)",$D18=Contacts!$C$3),OR(Contacts!$E$3="(All)",$G18=Contacts!$E$3),OR(Contacts!$G$3="(All)",ISNUMBER(SEARCH(Contacts!$G$3,$V18))),OR(Contacts!$I$3="(All)",$X18=Contacts!$I$3),OR(Contacts!$K$3="",ISNUMBER(SEARCH(Contacts!$K$3,$B18&" "&$C18&" "&$D18&" "&$S18)))),1,0)) -> 1 | AA18: =IF($Z18=1,COUNTIFS(c_Pass,1,c_Sort,"<="&$Y18),"") -> 17 | AB18: =IF(OR($G18<>"Yes",NOT(ISNUMBER($H18))),"",COUNTIFS(c_Met,"Yes",c_Date,"<"&$H18)+COUNTIFS($G$2:$G18,"Yes",$H$2:$H18,$H18)) -> 41
A19: =IF($B19="","",COUNTA($B$2:$B19)) -> 18 | B19: Paul Chiam | C19: paulchiam@fapl.sg | D19: Financial Alliance | E19: Adviser | F19: Meeting List | G19: No | I19: 0 | J19: No | N19: Not Invited | O19: Attended | P19: Not Invited | Q19: Not Invited | R19: Not Invited | T19: =IF($B19="","",COUNTA($N19:$R19)-COUNTIF($N19:$R19,"Not Invited")) -> 1 | U19: =IF($B19="","",COUNTIF($N19:$R19,"Attended")) -> 1 | V19: =IF($B19="","",_xlfn.TEXTJOIN(", ",TRUE(),IF($N19="Attended",Setup!$D$15,""),IF($O19="Attended",Setup!$D$16,""),IF($P19="Attended",Setup!$D$17,""),IF($Q19="Attended",Setup!$D$18,""),IF($R19="Attended",Setup!$D$19,""))) -> May-26 Symposium | W19: =IF(OR($B19="",NOT(ISNUMBER($H19))),"",TODAY()-$H19) | X19: =IF($B19="","",IF($U19>0,"Event attendee",IF($G19="Yes","Met (no event)",IF($T19>0,"Invited only",IF(OR($L19="Yes",$M19="Yes"),"Contacted only","Not yet contacted"))))) -> Event attendee | Y19: =IF($B19="","",COUNTIF(c_Firm,"<"&$D19)+COUNTIFS(c_Firm,$D19,c_Name,"<"&$B19)+COUNTIFS($D$2:$D19,$D19,$B$2:$B19,$B19)) -> 18 | Z19: =IF($B19="","",IF(AND(OR(Contacts!$C$3="(All)",$D19=Contacts!$C$3),OR(Contacts!$E$3="(All)",$G19=Contacts!$E$3),OR(Contacts!$G$3="(All)",ISNUMBER(SEARCH(Contacts!$G$3,$V19))),OR(Contacts!$I$3="(All)",$X19=Contacts!$I$3),OR(Contacts!$K$3="",ISNUMBER(SEARCH(Contacts!$K$3,$B19&" "&$C19&" "&$D19&" "&$S19)))),1,0)) -> 1 | AA19: =IF($Z19=1,COUNTIFS(c_Pass,1,c_Sort,"<="&$Y19),"") -> 18 | AB19: =IF(OR($G19<>"Yes",NOT(ISNUMBER($H19))),"",COUNTIFS(c_Met,"Yes",c_Date,"<"&$H19)+COUNTIFS($G$2:$G19,"Yes",$H$2:$H19,$H19))
A20: =IF($B20="","",COUNTA($B$2:$B20)) -> 19 | B20: Raymund Ng | C20: raymundng@fapl.sg | D20: Financial Alliance | E20: Adviser | F20: Meeting List + ILP Data | G20: Yes | H20: 45829 | I20: 1 | J20: Yes | K20: 5000000 | N20: No Reply | O20: Declined | P20: Not Invited | Q20: Not Invited | R20: Not Invited | S20: May-26: not available | T20: =IF($B20="","",COUNTA($N20:$R20)-COUNTIF($N20:$R20,"Not Invited")) -> 2 | U20: =IF($B20="","",COUNTIF($N20:$R20,"Attended")) -> 0 | V20: =IF($B20="","",_xlfn.TEXTJOIN(", ",TRUE(),IF($N20="Attended",Setup!$D$15,""),IF($O20="Attended",Setup!$D$16,""),IF($P20="Attended",Setup!$D$17,""),IF($Q20="Attended",Setup!$D$18,""),IF($R20="Attended",Setup!$D$19,""))) | W20: =IF(OR($B20="",NOT(ISNUMBER($H20))),"",TODAY()-$H20) -> 412 | X20: =IF($B20="","",IF($U20>0,"Event attendee",IF($G20="Yes","Met (no event)",IF($T20>0,"Invited only",IF(OR($L20="Yes",$M20="Yes"),"Contacted only","Not yet contacted"))))) -> Met (no event) | Y20: =IF($B20="","",COUNTIF(c_Firm,"<"&$D20)+COUNTIFS(c_Firm,$D20,c_Name,"<"&$B20)+COUNTIFS($D$2:$D20,$D20,$B$2:$B20,$B20)) -> 19 | Z20: =IF($B20="","",IF(AND(OR(Contacts!$C$3="(All)",$D20=Contacts!$C$3),OR(Contacts!$E$3="(All)",$G20=Contacts!$E$3),OR(Contacts!$G$3="(All)",ISNUMBER(SEARCH(Contacts!$G$3,$V20))),OR(Contacts!$I$3="(All)",$X20=Contacts!$I$3),OR(Contacts!$K$3="",ISNUMBER(SEARCH(Contacts!$K$3,$B20&" "&$C20&" "&$D20&" "&$S20)))),1,0)) -> 1 | AA20: =IF($Z20=1,COUNTIFS(c_Pass,1,c_Sort,"<="&$Y20),"") -> 19 | AB20: =IF(OR($G20<>"Yes",NOT(ISNUMBER($H20))),"",COUNTIFS(c_Met,"Yes",c_Date,"<"&$H20)+COUNTIFS($G$2:$G20,"Yes",$H$2:$H20,$H20)) -> 8
A21: =IF($B21="","",COUNTA($B$2:$B21)) -> 20 | B21: Riyaz Tadjoudine | C21: riyazahmad@fa.sg | D21: Financial Alliance | E21: Adviser | F21: Meeting List + ILP Data | G21: No | I21: 0 | J21: No | N21: Attended | O21: Attended | P21: Not Invited | Q21: Not Invited | R21: Not Invited | S21: ILP: Investment | T21: =IF($B21="","",COUNTA($N21:$R21)-COUNTIF($N21:$R21,"Not Invited")) -> 2 | U21: =IF($B21="","",COUNTIF($N21:$R21,"Attended")) -> 2 | V21: =IF($B21="","",_xlfn.TEXTJOIN(", ",TRUE(),IF($N21="Attended",Setup!$D$15,""),IF($O21="Attended",Setup!$D$16,""),IF($P21="Attended",Setup!$D$17,""),IF($Q21="Attended",Setup!$D$18,""),IF($R21="Attended",Setup!$D$19,""))) -> Oct-25 Symposium, May-26 Symposium | W21: =IF(OR($B21="",NOT(ISNUMBER($H21))),"",TODAY()-$H21) | X21: =IF($B21="","",IF($U21>0,"Event attendee",IF($G21="Yes","Met (no event)",IF($T21>0,"Invited only",IF(OR($L21="Yes",$M21="Yes"),"Contacted only","Not yet contacted"))))) -> Event attendee | Y21: =IF($B21="","",COUNTIF(c_Firm,"<"&$D21)+COUNTIFS(c_Firm,$D21,c_Name,"<"&$B21)+COUNTIFS($D$2:$D21,$D21,$B$2:$B21,$B21)) -> 20 | Z21: =IF($B21="","",IF(AND(OR(Contacts!$C$3="(All)",$D21=Contacts!$C$3),OR(Contacts!$E$3="(All)",$G21=Contacts!$E$3),OR(Contacts!$G$3="(All)",ISNUMBER(SEARCH(Contacts!$G$3,$V21))),OR(Contacts!$I$3="(All)",$X21=Contacts!$I$3),OR(Contacts!$K$3="",ISNUMBER(SEARCH(Contacts!$K$3,$B21&" "&$C21&" "&$D21&" "&$S21)))),1,0)) -> 1 | AA21: =IF($Z21=1,COUNTIFS(c_Pass,1,c_Sort,"<="&$Y21),"") -> 20 | AB21: =IF(OR($G21<>"Yes",NOT(ISNUMBER($H21))),"",COUNTIFS(c_Met,"Yes",c_Date,"<"&$H21)+COUNTIFS($G$2:$G21,"Yes",$H$2:$H21,$H21))
A22: =IF($B22="","",COUNTA($B$2:$B22)) -> 21 | B22: Sani Amid | C22: sanihamid@fa.sg | D22: Financial Alliance | E22: Adviser | F22: Meeting List + ILP Data | G22: Yes | H22: 45819 | I22: 1 | J22: No | N22: Attended | O22: Declined | P22: Not Invited | Q22: Not Invited | R22: Not Invited | S22: May-26: not available; ILP: Investment | T22: =IF($B22="","",COUNTA($N22:$R22)-COUNTIF($N22:$R22,"Not Invited")) -> 2 | U22: =IF($B22="","",COUNTIF($N22:$R22,"Attended")) -> 1 | V22: =IF($B22="","",_xlfn.TEXTJOIN(", ",TRUE(),IF($N22="Attended",Setup!$D$15,""),IF($O22="Attended",Setup!$D$16,""),IF($P22="Attended",Setup!$D$17,""),IF($Q22="Attended",Setup!$D$18,""),IF($R22="Attended",Setup!$D$19,""))) -> Oct-25 Symposium | W22: =IF(OR($B22="",NOT(ISNUMBER($H22))),"",TODAY()-$H22) -> 422 | X22: =IF($B22="","",IF($U22>0,"Event attendee",IF($G22="Yes","Met (no event)",IF($T22>0,"Invited only",IF(OR($L22="Yes",$M22="Yes"),"Contacted only","Not yet contacted"))))) -> Event attendee | Y22: =IF($B22="","",COUNTIF(c_Firm,"<"&$D22)+COUNTIFS(c_Firm,$D22,c_Name,"<"&$B22)+COUNTIFS($D$2:$D22,$D22,$B$2:$B22,$B22)) -> 21 | Z22: =IF($B22="","",IF(AND(OR(Contacts!$C$3="(All)",$D22=Contacts!$C$3),OR(Contacts!$E$3="(All)",$G22=Contacts!$E$3),OR(Contacts!$G$3="(All)",ISNUMBER(SEARCH(Contacts!$G$3,$V22))),OR(Contacts!$I$3="(All)",$X22=Contacts!$I$3),OR(Contacts!$K$3="",ISNUMBER(SEARCH(Contacts!$K$3,$B22&" "&$C22&" "&$D22&" "&$S22)))),1,0)) -> 1 | AA22: =IF($Z22=1,COUNTIFS(c_Pass,1,c_Sort,"<="&$Y22),"") -> 21 | AB22: =IF(OR($G22<>"Yes",NOT(ISNUMBER($H22))),"",COUNTIFS(c_Met,"Yes",c_Date,"<"&$H22)+COUNTIFS($G$2:$G22,"Yes",$H$2:$H22,$H22)) -> 7
A23: =IF($B23="","",COUNTA($B$2:$B23)) -> 22 | B23: Sofan Tan | C23: sofantan@fapl.sg | D23: Financial Alliance | E23: Adviser | F23: Meeting List | G23: No | I23: 0 | J23: No | N23: Not Invited | O23: No Show | P23: Not Invited | Q23: Not Invited | R23: Not Invited | T23: =IF($B23="","",COUNTA($N23:$R23)-COUNTIF($N23:$R23,"Not Invited")) -> 1 | U23: =IF($B23="","",COUNTIF($N23:$R23,"Attended")) -> 0 | V23: =IF($B23="","",_xlfn.TEXTJOIN(", ",TRUE(),IF($N23="Attended",Setup!$D$15,""),IF($O23="Attended",Setup!$D$16,""),IF($P23="Attended",Setup!$D$17,""),IF($Q23="Attended",Setup!$D$18,""),IF($R23="Attended",Setup!$D$19,""))) | W23: =IF(OR($B23="",NOT(ISNUMBER($H23))),"",TODAY()-$H23) | X23: =IF($B23="","",IF($U23>0,"Event attendee",IF($G23="Yes","Met (no event)",IF($T23>0,"Invited only",IF(OR($L23="Yes",$M23="Yes"),"Contacted only","Not yet contacted"))))) -> Invited only | Y23: =IF($B23="","",COUNTIF(c_Firm,"<"&$D23)+COUNTIFS(c_Firm,$D23,c_Name,"<"&$B23)+COUNTIFS($D$2:$D23,$D23,$B$2:$B23,$B23)) -> 22 | Z23: =IF($B23="","",IF(AND(OR(Contacts!$C$3="(All)",$D23=Contacts!$C$3),OR(Contacts!$E$3="(All)",$G23=Contacts!$E$3),OR(Contacts!$G$3="(All)",ISNUMBER(SEARCH(Contacts!$G$3,$V23))),OR(Contacts!$I$3="(All)",$X23=Contacts!$I$3),OR(Contacts!$K$3="",ISNUMBER(SEARCH(Contacts!$K$3,$B23&" "&$C23&" "&$D23&" "&$S23)))),1,0)) -> 1 | AA23: =IF($Z23=1,COUNTIFS(c_Pass,1,c_Sort,"<="&$Y23),"") -> 22 | AB23: =IF(OR($G23<>"Yes",NOT(ISNUMBER($H23))),"",COUNTIFS(c_Met,"Yes",c_Date,"<"&$H23)+COUNTIFS($G$2:$G23,"Yes",$H$2:$H23,$H23))
A24: =IF($B24="","",COUNTA($B$2:$B24)) -> 23 | B24: Susan Au Yeong | C24: susanauyeong@fapl.sg | D24: Financial Alliance | E24: Adviser | F24: Meeting List | G24: No | I24: 0 | J24: No | N24: Not Invited | O24: Attended | P24: Not Invited | Q24: Not Invited | R24: Not Invited | T24: =IF($B24="","",COUNTA($N24:$R24)-COUNTIF($N24:$R24,"Not Invited")) -> 1 | U24: =IF($B24="","",COUNTIF($N24:$R24,"Attended")) -> 1 | V24: =IF($B24="","",_xlfn.TEXTJOIN(", ",TRUE(),IF($N24="Attended",Setup!$D$15,""),IF($O24="Attended",Setup!$D$16,""),IF($P24="Attended",Setup!$D$17,""),IF($Q24="Attended",Setup!$D$18,""),IF($R24="Attended",Setup!$D$19,""))) -> May-26 Symposium | W24: =IF(OR($B24="",NOT(ISNUMBER($H24))),"",TODAY()-$H24) | X24: =IF($B24="","",IF($U24>0,"Event attendee",IF($G24="Yes","Met (no event)",IF($T24>0,"Invited only",IF(OR($L24="Yes",$M24="Yes"),"Contacted only","Not yet contacted"))))) -> Event attendee | Y24: =IF($B24="","",COUNTIF(c_Firm,"<"&$D24)+COUNTIFS(c_Firm,$D24,c_Name,"<"&$B24)+COUNTIFS($D$2:$D24,$D24,$B$2:$B24,$B24)) -> 23 | Z24: =IF($B24="","",IF(AND(OR(Contacts!$C$3="(All)",$D24=Contacts!$C$3),OR(Contacts!$E$3="(All)",$G24=Contacts!$E$3),OR(Contacts!$G$3="(All)",ISNUMBER(SEARCH(Contacts!$G$3,$V24))),OR(Contacts!$I$3="(All)",$X24=Contacts!$I$3),OR(Contacts!$K$3="",ISNUMBER(SEARCH(Contacts!$K$3,$B24&" "&$C24&" "&$D24&" "&$S24)))),1,0)) -> 1 | AA24: =IF($Z24=1,COUNTIFS(c_Pass,1,c_Sort,"<="&$Y24),"") -> 23 | AB24: =IF(OR($G24<>"Yes",NOT(ISNUMBER($H24))),"",COUNTIFS(c_Met,"Yes",c_Date,"<"&$H24)+COUNTIFS($G$2:$G24,"Yes",$H$2:$H24,$H24))
A25: =IF($B25="","",COUNTA($B$2:$B25)) -> 24 | B25: Thomas Ong Cheow Siang | C25: thomasong@fapl.sg | D25: Financial Alliance | E25: Adviser | F25: Meeting List | G25: No | I25: 0 | J25: No | N25: Not Invited | O25: Attended | P25: Not Invited | Q25: Not Invited | R25: Not Invited | T25: =IF($B25="","",COUNTA($N25:$R25)-COUNTIF($N25:$R25,"Not Invited")) -> 1 | U25: =IF($B25="","",COUNTIF($N25:$R25,"Attended")) -> 1 | V25: =IF($B25="","",_xlfn.TEXTJOIN(", ",TRUE(),IF($N25="Attended",Setup!$D$15,""),IF($O25="Attended",Setup!$D$16,""),IF($P25="Attended",Setup!$D$17,""),IF($Q25="Attended",Setup!$D$18,""),IF($R25="Attended",Setup!$D$19,""))) -> May-26 Symposium | W25: =IF(OR($B25="",NOT(ISNUMBER($H25))),"",TODAY()-$H25) | X25: =IF($B25="","",IF($U25>0,"Event attendee",IF($G25="Yes","Met (no event)",IF($T25>0,"Invited only",IF(OR($L25="Yes",$M25="Yes"),"Contacted only","Not yet contacted"))))) -> Event attendee | Y25: =IF($B25="","",COUNTIF(c_Firm,"<"&$D25)+COUNTIFS(c_Firm,$D25,c_Name,"<"&$B25)+COUNTIFS($D$2:$D25,$D25,$B$2:$B25,$B25)) -> 24 | Z25: =IF($B25="","",IF(AND(OR(Contacts!$C$3="(All)",$D25=Contacts!$C$3),OR(Contacts!$E$3="(All)",$G25=Contacts!$E$3),OR(Contacts!$G$3="(All)",ISNUMBER(SEARCH(Contacts!$G$3,$V25))),OR(Contacts!$I$3="(All)",$X25=Contacts!$I$3),OR(Contacts!$K$3="",ISNUMBER(SEARCH(Contacts!$K$3,$B25&" "&$C25&" "&$D25&" "&$S25)))),1,0)) -> 1 | AA25: =IF($Z25=1,COUNTIFS(c_Pass,1,c_Sort,"<="&$Y25),"") -> 24 | AB25: =IF(OR($G25<>"Yes",NOT(ISNUMBER($H25))),"",COUNTIFS(c_Met,"Yes",c_Date,"<"&$H25)+COUNTIFS($G$2:$G25,"Yes",$H$2:$H25,$H25))
A26: =IF($B26="","",COUNTA($B$2:$B26)) -> 25 | B26: Toh Hung Jui | C26: tohhungjui@fapl.sg | D26: Financial Alliance | E26: Adviser | F26: Meeting List | G26: No | I26: 0 | J26: No | N26: Not Invited | O26: Attended | P26: Not Invited | Q26: Not Invited | R26: Not Invited | T26: =IF($B26="","",COUNTA($N26:$R26)-COUNTIF($N26:$R26,"Not Invited")) -> 1 | U26: =IF($B26="","",COUNTIF($N26:$R26,"Attended")) -> 1 | V26: =IF($B26="","",_xlfn.TEXTJOIN(", ",TRUE(),IF($N26="Attended",Setup!$D$15,""),IF($O26="Attended",Setup!$D$16,""),IF($P26="Attended",Setup!$D$17,""),IF($Q26="Attended",Setup!$D$18,""),IF($R26="Attended",Setup!$D$19,""))) -> May-26 Symposium | W26: =IF(OR($B26="",NOT(ISNUMBER($H26))),"",TODAY()-$H26) | X26: =IF($B26="","",IF($U26>0,"Event attendee",IF($G26="Yes","Met (no event)",IF($T26>0,"Invited only",IF(OR($L26="Yes",$M26="Yes"),"Contacted only","Not yet contacted"))))) -> Event attendee | Y26: =IF($B26="","",COUNTIF(c_Firm,"<"&$D26)+COUNTIFS(c_Firm,$D26,c_Name,"<"&$B26)+COUNTIFS($D$2:$D26,$D26,$B$2:$B26,$B26)) -> 25 | Z26: =IF($B26="","",IF(AND(OR(Contacts!$C$3="(All)",$D26=Contacts!$C$3),OR(Contacts!$E$3="(All)",$G26=Contacts!$E$3),OR(Contacts!$G$3="(All)",ISNUMBER(SEARCH(Contacts!$G$3,$V26))),OR(Contacts!$I$3="(All)",$X26=Contacts!$I$3),OR(Contacts!$K$3="",ISNUMBER(SEARCH(Contacts!$K$3,$B26&" "&$C26&" "&$D26&" "&$S26)))),1,0)) -> 1 | AA26: =IF($Z26=1,COUNTIFS(c_Pass,1,c_Sort,"<="&$Y26),"") -> 25 | AB26: =IF(OR($G26<>"Yes",NOT(ISNUMBER($H26))),"",COUNTIFS(c_Met,"Yes",c_Date,"<"&$H26)+COUNTIFS($G$2:$G26,"Yes",$H$2:$H26,$H26))
A27: =IF($B27="","",COUNTA($B$2:$B27)) -> 26 | B27: Winston Tyo | C27: winstontyo@fapl.sg | D27: Financial Alliance | E27: Adviser | F27: Meeting List | G27: No | I27: 0 | J27: No | N27: Not Invited | O27: Attended | P27: Not Invited | Q27: Not Invited | R27: Not Invited | T27: =IF($B27="","",COUNTA($N27:$R27)-COUNTIF($N27:$R27,"Not Invited")) -> 1 | U27: =IF($B27="","",COUNTIF($N27:$R27,"Attended")) -> 1 | V27: =IF($B27="","",_xlfn.TEXTJOIN(", ",TRUE(),IF($N27="Attended",Setup!$D$15,""),IF($O27="Attended",Setup!$D$16,""),IF($P27="Attended",Setup!$D$17,""),IF($Q27="Attended",Setup!$D$18,""),IF($R27="Attended",Setup!$D$19,""))) -> May-26 Symposium | W27: =IF(OR($B27="",NOT(ISNUMBER($H27))),"",TODAY()-$H27) | X27: =IF($B27="","",IF($U27>0,"Event attendee",IF($G27="Yes","Met (no event)",IF($T27>0,"Invited only",IF(OR($L27="Yes",$M27="Yes"),"Contacted only","Not yet contacted"))))) -> Event attendee | Y27: =IF($B27="","",COUNTIF(c_Firm,"<"&$D27)+COUNTIFS(c_Firm,$D27,c_Name,"<"&$B27)+COUNTIFS($D$2:$D27,$D27,$B$2:$B27,$B27)) -> 26 | Z27: =IF($B27="","",IF(AND(OR(Contacts!$C$3="(All)",$D27=Contacts!$C$3),OR(Contacts!$E$3="(All)",$G27=Contacts!$E$3),OR(Contacts!$G$3="(All)",ISNUMBER(SEARCH(Contacts!$G$3,$V27))),OR(Contacts!$I$3="(All)",$X27=Contacts!$I$3),OR(Contacts!$K$3="",ISNUMBER(SEARCH(Contacts!$K$3,$B27&" "&$C27&" "&$D27&" "&$S27)))),1,0)) -> 1 | AA27: =IF($Z27=1,COUNTIFS(c_Pass,1,c_Sort,"<="&$Y27),"") -> 26 | AB27: =IF(OR($G27<>"Yes",NOT(ISNUMBER($H27))),"",COUNTIFS(c_Met,"Yes",c_Date,"<"&$H27)+COUNTIFS($G$2:$G27,"Yes",$H$2:$H27,$H27))
A28: =IF($B28="","",COUNTA($B$2:$B28)) -> 27 | B28: Ada Huang | D28: Finexis Advisory | E28: Branch Director | F28: Branch Directors | G28: No | I28: 0 | J28: No | M28: Yes | N28: Not Invited | O28: Not Invited | P28: Not Invited | Q28: Not Invited | R28: Not Invited | S28: https://www.linkedin.com/in/tvivianhuang/ | T28: =IF($B28="","",COUNTA($N28:$R28)-COUNTIF($N28:$R28,"Not Invited")) -> 0 | U28: =IF($B28="","",COUNTIF($N28:$R28,"Attended")) -> 0 | V28: =IF($B28="","",_xlfn.TEXTJOIN(", ",TRUE(),IF($N28="Attended",Setup!$D$15,""),IF($O28="Attended",Setup!$D$16,""),IF($P28="Attended",Setup!$D$17,""),IF($Q28="Attended",Setup!$D$18,""),IF($R28="Attended",Setup!$D$19,""))) | W28: =IF(OR($B28="",NOT(ISNUMBER($H28))),"",TODAY()-$H28) | X28: =IF($B28="","",IF($U28>0,"Event attendee",IF($G28="Yes","Met (no event)",IF($T28>0,"Invited only",IF(OR($L28="Yes",$M28="Yes"),"Contacted only","Not yet contacted"))))) -> Contacted only | Y28: =IF($B28="","",COUNTIF(c_Firm,"<"&$D28)+COUNTIFS(c_Firm,$D28,c_Name,"<"&$B28)+COUNTIFS($D$2:$D28,$D28,$B$2:$B28,$B28)) -> 27 | Z28: =IF($B28="","",IF(AND(OR(Contacts!$C$3="(All)",$D28=Contacts!$C$3),OR(Contacts!$E$3="(All)",$G28=Contacts!$E$3),OR(Contacts!$G$3="(All)",ISNUMBER(SEARCH(Contacts!$G$3,$V28))),OR(Contacts!$I$3="(All)",$X28=Contacts!$I$3),OR(Contacts!$K$3="",ISNUMBER(SEARCH(Contacts!$K$3,$B28&" "&$C28&" "&$D28&" "&$S28)))),1,0)) -> 1 | AA28: =IF($Z28=1,COUNTIFS(c_Pass,1,c_Sort,"<="&$Y28),"") -> 27 | AB28: =IF(OR($G28<>"Yes",NOT(ISNUMBER($H28))),"",COUNTIFS(c_Met,"Yes",c_Date,"<"&$H28)+COUNTIFS($G$2:$G28,"Yes",$H$2:$H28,$H28))
A29: =IF($B29="","",COUNTA($B$2:$B29)) -> 28 | B29: Amanda Tan | D29: Finexis Advisory | E29: Branch Director | F29: Branch Directors | G29: No | I29: 0 | J29: No | M29: Yes | N29: Not Invited | O29: Not Invited | P29: Not Invited | Q29: Not Invited | R29: Not Invited | S29: https://www.linkedin.com/in/amanda-tan-36799498/ | T29: =IF($B29="","",COUNTA($N29:$R29)-COUNTIF($N29:$R29,"Not Invited")) -> 0 | U29: =IF($B29="","",COUNTIF($N29:$R29,"Attended")) -> 0 | V29: =IF($B29="","",_xlfn.TEXTJOIN(", ",TRUE(),IF($N29="Attended",Setup!$D$15,""),IF($O29="Attended",Setup!$D$16,""),IF($P29="Attended",Setup!$D$17,""),IF($Q29="Attended",Setup!$D$18,""),IF($R29="Attended",Setup!$D$19,""))) | W29: =IF(OR($B29="",NOT(ISNUMBER($H29))),"",TODAY()-$H29) | X29: =IF($B29="","",IF($U29>0,"Event attendee",IF($G29="Yes","Met (no event)",IF($T29>0,"Invited only",IF(OR($L29="Yes",$M29="Yes"),"Contacted only","Not yet contacted"))))) -> Contacted only | Y29: =IF($B29="","",COUNTIF(c_Firm,"<"&$D29)+COUNTIFS(c_Firm,$D29,c_Name,"<"&$B29)+COUNTIFS($D$2:$D29,$D29,$B$2:$B29,$B29)) -> 28 | Z29: =IF($B29="","",IF(AND(OR(Contacts!$C$3="(All)",$D29=Contacts!$C$3),OR(Contacts!$E$3="(All)",$G29=Contacts!$E$3),OR(Contacts!$G$3="(All)",ISNUMBER(SEARCH(Contacts!$G$3,$V29))),OR(Contacts!$I$3="(All)",$X29=Contacts!$I$3),OR(Contacts!$K$3="",ISNUMBER(SEARCH(Contacts!$K$3,$B29&" "&$C29&" "&$D29&" "&$S29)))),1,0)) -> 1 | AA29: =IF($Z29=1,COUNTIFS(c_Pass,1,c_Sort,"<="&$Y29),"") -> 28 | AB29: =IF(OR($G29<>"Yes",NOT(ISNUMBER($H29))),"",COUNTIFS(c_Met,"Yes",c_Date,"<"&$H29)+COUNTIFS($G$2:$G29,"Yes",$H$2:$H29,$H29))
A30: =IF($B30="","",COUNTA($B$2:$B30)) -> 29 | B30: Amanda Yeo | C30: amanda.yeo@finexis.com.sg | D30: Finexis Advisory | E30: Adviser | F30: Meeting List + ILP Data | G30: Yes | H30: 45992 | I30: 1 | J30: No | K30: 40000000 | N30: Attended | O30: Attended | P30: Not Invited | Q30: Not Invited | R30: Not Invited | T30: =IF($B30="","",COUNTA($N30:$R30)-COUNTIF($N30:$R30,"Not Invited")) -> 2 | U30: =IF($B30="","",COUNTIF($N30:$R30,"Attended")) -> 2 | V30: =IF($B30="","",_xlfn.TEXTJOIN(", ",TRUE(),IF($N30="Attended",Setup!$D$15,""),IF($O30="Attended",Setup!$D$16,""),IF($P30="Attended",Setup!$D$17,""),IF($Q30="Attended",Setup!$D$18,""),IF($R30="Attended",Setup!$D$19,""))) -> Oct-25 Symposium, May-26 Symposium | W30: =IF(OR($B30="",NOT(ISNUMBER($H30))),"",TODAY()-$H30) -> 249 | X30: =IF($B30="","",IF($U30>0,"Event attendee",IF($G30="Yes","Met (no event)",IF($T30>0,"Invited only",IF(OR($L30="Yes",$M30="Yes"),"Contacted only","Not yet contacted"))))) -> Event attendee | Y30: =IF($B30="","",COUNTIF(c_Firm,"<"&$D30)+COUNTIFS(c_Firm,$D30,c_Name,"<"&$B30)+COUNTIFS($D$2:$D30,$D30,$B$2:$B30,$B30)) -> 29 | Z30: =IF($B30="","",IF(AND(OR(Contacts!$C$3="(All)",$D30=Contacts!$C$3),OR(Contacts!$E$3="(All)",$G30=Contacts!$E$3),OR(Contacts!$G$3="(All)",ISNUMBER(SEARCH(Contacts!$G$3,$V30))),OR(Contacts!$I$3="(All)",$X30=Contacts!$I$3),OR(Contacts!$K$3="",ISNUMBER(SEARCH(Contacts!$K$3,$B30&" "&$C30&" "&$D30&" "&$S30)))),1,0)) -> 1 | AA30: =IF($Z30=1,COUNTIFS(c_Pass,1,c_Sort,"<="&$Y30),"") -> 29 | AB30: =IF(OR($G30<>"Yes",NOT(ISNUMBER($H30))),"",COUNTIFS(c_Met,"Yes",c_Date,"<"&$H30)+COUNTIFS($G$2:$G30,"Yes",$H$2:$H30,$H30)) -> 36
A31: =IF($B31="","",COUNTA($B$2:$B31)) -> 30 | B31: Anton Chua | D31: Finexis Advisory | E31: Branch Director | F31: Branch Directors | G31: No | I31: 0 | J31: No | M31: Yes | N31: Not Invited | O31: Not Invited | P31: Not Invited | Q31: Not Invited | R31: Not Invited | S31: Branch: Acorn Wealth | T31: =IF($B31="","",COUNTA($N31:$R31)-COUNTIF($N31:$R31,"Not Invited")) -> 0 | U31: =IF($B31="","",COUNTIF($N31:$R31,"Attended")) -> 0 | V31: =IF($B31="","",_xlfn.TEXTJOIN(", ",TRUE(),IF($N31="Attended",Setup!$D$15,""),IF($O31="Attended",Setup!$D$16,""),IF($P31="Attended",Setup!$D$17,""),IF($Q31="Attended",Setup!$D$18,""),IF($R31="Attended",Setup!$D$19,""))) | W31: =IF(OR($B31="",NOT(ISNUMBER($H31))),"",TODAY()-$H31) | X31: =IF($B31="","",IF($U31>0,"Event attendee",IF($G31="Yes","Met (no event)",IF($T31>0,"Invited only",IF(OR($L31="Yes",$M31="Yes"),"Contacted only","Not yet contacted"))))) -> Contacted only | Y31: =IF($B31="","",COUNTIF(c_Firm,"<"&$D31)+COUNTIFS(c_Firm,$D31,c_Name,"<"&$B31)+COUNTIFS($D$2:$D31,$D31,$B$2:$B31,$B31)) -> 30 | Z31: =IF($B31="","",IF(AND(OR(Contacts!$C$3="(All)",$D31=Contacts!$C$3),OR(Contacts!$E$3="(All)",$G31=Contacts!$E$3),OR(Contacts!$G$3="(All)",ISNUMBER(SEARCH(Contacts!$G$3,$V31))),OR(Contacts!$I$3="(All)",$X31=Contacts!$I$3),OR(Contacts!$K$3="",ISNUMBER(SEARCH(Contacts!$K$3,$B31&" "&$C31&" "&$D31&" "&$S31)))),1,0)) -> 1 | AA31: =IF($Z31=1,COUNTIFS(c_Pass,1,c_Sort,"<="&$Y31),"") -> 30 | AB31: =IF(OR($G31<>"Yes",NOT(ISNUMBER($H31))),"",COUNTIFS(c_Met,"Yes",c_Date,"<"&$H31)+COUNTIFS($G$2:$G31,"Yes",$H$2:$H31,$H31))
A32: =IF($B32="","",COUNTA($B$2:$B32)) -> 31 | B32: Ben Pua | C32: ben.pua@finexis.com.sg | D32: Finexis Advisory | E32: Adviser | F32: Meeting List | G32: No | I32: 0 | J32: No | N32: Not Invited | O32: Attended | P32: Not Invited | Q32: Not Invited | R32: Not Invited | T32: =IF($B32="","",COUNTA($N32:$R32)-COUNTIF($N32:$R32,"Not Invited")) -> 1 | U32: =IF($B32="","",COUNTIF($N32:$R32,"Attended")) -> 1 | V32: =IF($B32="","",_xlfn.TEXTJOIN(", ",TRUE(),IF($N32="Attended",Setup!$D$15,""),IF($O32="Attended",Setup!$D$16,""),IF($P32="Attended",Setup!$D$17,""),IF($Q32="Attended",Setup!$D$18,""),IF($R32="Attended",Setup!$D$19,""))) -> May-26 Symposium | W32: =IF(OR($B32="",NOT(ISNUMBER($H32))),"",TODAY()-$H32) | X32: =IF($B32="","",IF($U32>0,"Event attendee",IF($G32="Yes","Met (no event)",IF($T32>0,"Invited only",IF(OR($L32="Yes",$M32="Yes"),"Contacted only","Not yet contacted"))))) -> Event attendee | Y32: =IF($B32="","",COUNTIF(c_Firm,"<"&$D32)+COUNTIFS(c_Firm,$D32,c_Name,"<"&$B32)+COUNTIFS($D$2:$D32,$D32,$B$2:$B32,$B32)) -> 31 | Z32: =IF($B32="","",IF(AND(OR(Contacts!$C$3="(All)",$D32=Contacts!$C$3),OR(Contacts!$E$3="(All)",$G32=Contacts!$E$3),OR(Contacts!$G$3="(All)",ISNUMBER(SEARCH(Contacts!$G$3,$V32))),OR(Contacts!$I$3="(All)",$X32=Contacts!$I$3),OR(Contacts!$K$3="",ISNUMBER(SEARCH(Contacts!$K$3,$B32&" "&$C32&" "&$D32&" "&$S32)))),1,0)) -> 1 | AA32: =IF($Z32=1,COUNTIFS(c_Pass,1,c_Sort,"<="&$Y32),"") -> 31 | AB32: =IF(OR($G32<>"Yes",NOT(ISNUMBER($H32))),"",COUNTIFS(c_Met,"Yes",c_Date,"<"&$H32)+COUNTIFS($G$2:$G32,"Yes",$H$2:$H32,$H32))
A33: =IF($B33="","",COUNTA($B$2:$B33)) -> 32 | B33: Benedict Chua | C33: benedict.chua@finexis.com.sg | D33: Finexis Advisory | E33: Adviser | F33: Meeting List + ILP Data | G33: Yes | H33: 46007 | I33: 1 | J33: Yes | K33: 60000000 | N33: Declined | O33: Attended | P33: Not Invited | Q33: Not Invited | R33: Not Invited | T33: =IF($B33="","",COUNTA($N33:$R33)-COUNTIF($N33:$R33,"Not Invited")) -> 2 | U33: =IF($B33="","",COUNTIF($N33:$R33,"Attended")) -> 1 | V33: =IF($B33="","",_xlfn.TEXTJOIN(", ",TRUE(),IF($N33="Attended",Setup!$D$15,""),IF($O33="Attended",Setup!$D$16,""),IF($P33="Attended",Setup!$D$17,""),IF($Q33="Attended",Setup!$D$18,""),IF($R33="Attended",Setup!$D$19,""))) -> May-26 Symposium | W33: =IF(OR($B33="",NOT(ISNUMBER($H33))),"",TODAY()-$H33) -> 234 | X33: =IF($B33="","",IF($U33>0,"Event attendee",IF($G33="Yes","Met (no event)",IF($T33>0,"Invited only",IF(OR($L33="Yes",$M33="Yes"),"Contacted only","Not yet contacted"))))) -> Event attendee | Y33: =IF($B33="","",COUNTIF(c_Firm,"<"&$D33)+COUNTIFS(c_Firm,$D33,c_Name,"<"&$B33)+COUNTIFS($D$2:$D33,$D33,$B$2:$B33,$B33)) -> 32 | Z33: =IF($B33="","",IF(AND(OR(Contacts!$C$3="(All)",$D33=Contacts!$C$3),OR(Contacts!$E$3="(All)",$G33=Contacts!$E$3),OR(Contacts!$G$3="(All)",ISNUMBER(SEARCH(Contacts!$G$3,$V33))),OR(Contacts!$I$3="(All)",$X33=Contacts!$I$3),OR(Contacts!$K$3="",ISNUMBER(SEARCH(Contacts!$K$3,$B33&" "&$C33&" "&$D33&" "&$S33)))),1,0)) -> 1 | AA33: =IF($Z33=1,COUNTIFS(c_Pass,1,c_Sort,"<="&$Y33),"") -> 32 | AB33: =IF(OR($G33<>"Yes",NOT(ISNUMBER($H33))),"",COUNTIFS(c_Met,"Yes",c_Date,"<"&$H33)+COUNTIFS($G$2:$G33,"Yes",$H$2:$H33,$H33)) -> 39
A34: =IF($B34="","",COUNTA($B$2:$B34)) -> 33 | B34: Beverly Poon | C34: beverly.poon@finexis.com.sg | D34: Finexis Advisory | E34: Adviser | F34: Meeting List + ILP Data + Branch Directors | G34: Yes | H34: 45954 | I34: 1 | J34: No | K34: 60000000 | M34: No | N34: Declined | O34: Declined | P34: Not Invited | Q34: Not Invited | R34: Not Invited | S34: May-26: not available | T34: =IF($B34="","",COUNTA($N34:$R34)-COUNTIF($N34:$R34,"Not Invited")) -> 2 | U34: =IF($B34="","",COUNTIF($N34:$R34,"Attended")) -> 0 | V34: =IF($B34="","",_xlfn.TEXTJOIN(", ",TRUE(),IF($N34="Attended",Setup!$D$15,""),IF($O34="Attended",Setup!$D$16,""),IF($P34="Attended",Setup!$D$17,""),IF($Q34="Attended",Setup!$D$18,""),IF($R34="Attended",Setup!$D$19,""))) | W34: =IF(OR($B34="",NOT(ISNUMBER($H34))),"",TODAY()-$H34) -> 287 | X34: =IF($B34="","",IF($U34>0,"Event attendee",IF($G34="Yes","Met (no event)",IF($T34>0,"Invited only",IF(OR($L34="Yes",$M34="Yes"),"Contacted only","Not yet contacted"))))) -> Met (no event) | Y34: =IF($B34="","",COUNTIF(c_Firm,"<"&$D34)+COUNTIFS(c_Firm,$D34,c_Name,"<"&$B34)+COUNTIFS($D$2:$D34,$D34,$B$2:$B34,$B34)) -> 33 | Z34: =IF($B34="","",IF(AND(OR(Contacts!$C$3="(All)",$D34=Contacts!$C$3),OR(Contacts!$E$3="(All)",$G34=Contacts!$E$3),OR(Contacts!$G$3="(All)",ISNUMBER(SEARCH(Contacts!$G$3,$V34))),OR(Contacts!$I$3="(All)",$X34=Contacts!$I$3),OR(Contacts!$K$3="",ISNUMBER(SEARCH(Contacts!$K$3,$B34&" "&$C34&" "&$D34&" "&$S34)))),1,0)) -> 1 | AA34: =IF($Z34=1,COUNTIFS(c_Pass,1,c_Sort,"<="&$Y34),"") -> 33 | AB34: =IF(OR($G34<>"Yes",NOT(ISNUMBER($H34))),"",COUNTIFS(c_Met,"Yes",c_Date,"<"&$H34)+COUNTIFS($G$2:$G34,"Yes",$H$2:$H34,$H34)) -> 29
A35: =IF($B35="","",COUNTA($B$2:$B35)) -> 34 | B35: Bo Han Ng | D35: Finexis Advisory | E35: Branch Director | F35: Branch Directors | G35: No | I35: 0 | J35: No | M35: Yes | N35: Not Invited | O35: Not Invited | P35: Not Invited | Q35: Not Invited | R35: Not Invited | S35: Branch: Azure Dragon Partners | https://www.linkedin.com/in/bohan-ng/ | T35: =IF($B35="","",COUNTA($N35:$R35)-COUNTIF($N35:$R35,"Not Invited")) -> 0 | U35: =IF($B35="","",COUNTIF($N35:$R35,"Attended")) -> 0 | V35: =IF($B35="","",_xlfn.TEXTJOIN(", ",TRUE(),IF($N35="Attended",Setup!$D$15,""),IF($O35="Attended",Setup!$D$16,""),IF($P35="Attended",Setup!$D$17,""),IF($Q35="Attended",Setup!$D$18,""),IF($R35="Attended",Setup!$D$19,""))) | W35: =IF(OR($B35="",NOT(ISNUMBER($H35))),"",TODAY()-$H35) | X35: =IF($B35="","",IF($U35>0,"Event attendee",IF($G35="Yes","Met (no event)",IF($T35>0,"Invited only",IF(OR($L35="Yes",$M35="Yes"),"Contacted only","Not yet contacted"))))) -> Contacted only | Y35: =IF($B35="","",COUNTIF(c_Firm,"<"&$D35)+COUNTIFS(c_Firm,$D35,c_Name,"<"&$B35)+COUNTIFS($D$2:$D35,$D35,$B$2:$B35,$B35)) -> 34 | Z35: =IF($B35="","",IF(AND(OR(Contacts!$C$3="(All)",$D35=Contacts!$C$3),OR(Contacts!$E$3="(All)",$G35=Contacts!$E$3),OR(Contacts!$G$3="(All)",ISNUMBER(SEARCH(Contacts!$G$3,$V35))),OR(Contacts!$I$3="(All)",$X35=Contacts!$I$3),OR(Contacts!$K$3="",ISNUMBER(SEARCH(Contacts!$K$3,$B35&" "&$C35&" "&$D35&" "&$S35)))),1,0)) -> 1 | AA35: =IF($Z35=1,COUNTIFS(c_Pass,1,c_Sort,"<="&$Y35),"") -> 34 | AB35: =IF(OR($G35<>"Yes",NOT(ISNUMBER($H35))),"",COUNTIFS(c_Met,"Yes",c_Date,"<"&$H35)+COUNTIFS($G$2:$G35,"Yes",$H$2:$H35,$H35))
A36: =IF($B36="","",COUNTA($B$2:$B36)) -> 35 | B36: Caden Chia | D36: Finexis Advisory | E36: Branch Director | F36: Branch Directors | G36: No | I36: 0 | J36: No | M36: Yes | N36: Not Invited | O36: Not Invited | P36: Not Invited | Q36: Not Invited | R36: Not Invited | T36: =IF($B36="","",COUNTA($N36:$R36)-COUNTIF($N36:$R36,"Not Invited")) -> 0 | U36: =IF($B36="","",COUNTIF($N36:$R36,"Attended")) -> 0 | V36: =IF($B36="","",_xlfn.TEXTJOIN(", ",TRUE(),IF($N36="Attended",Setup!$D$15,""),IF($O36="Attended",Setup!$D$16,""),IF($P36="Attended",Setup!$D$17,""),IF($Q36="Attended",Setup!$D$18,""),IF($R36="Attended",Setup!$D$19,""))) | W36: =IF(OR($B36="",NOT(ISNUMBER($H36))),"",TODAY()-$H36) | X36: =IF($B36="","",IF($U36>0,"Event attendee",IF($G36="Yes","Met (no event)",IF($T36>0,"Invited only",IF(OR($L36="Yes",$M36="Yes"),"Contacted only","Not yet contacted"))))) -> Contacted only | Y36: =IF($B36="","",COUNTIF(c_Firm,"<"&$D36)+COUNTIFS(c_Firm,$D36,c_Name,"<"&$B36)+COUNTIFS($D$2:$D36,$D36,$B$2:$B36,$B36)) -> 35 | Z36: =IF($B36="","",IF(AND(OR(Contacts!$C$3="(All)",$D36=Contacts!$C$3),OR(Contacts!$E$3="(All)",$G36=Contacts!$E$3),OR(Contacts!$G$3="(All)",ISNUMBER(SEARCH(Contacts!$G$3,$V36))),OR(Contacts!$I$3="(All)",$X36=Contacts!$I$3),OR(Contacts!$K$3="",ISNUMBER(SEARCH(Contacts!$K$3,$B36&" "&$C36&" "&$D36&" "&$S36)))),1,0)) -> 1 | AA36: =IF($Z36=1,COUNTIFS(c_Pass,1,c_Sort,"<="&$Y36),"") -> 35 | AB36: =IF(OR($G36<>"Yes",NOT(ISNUMBER($H36))),"",COUNTIFS(c_Met,"Yes",c_Date,"<"&$H36)+COUNTIFS($G$2:$G36,"Yes",$H$2:$H36,$H36))
A37: =IF($B37="","",COUNTA($B$2:$B37)) -> 36 | B37: Chee Koon Seah | D37: Finexis Advisory | E37: Branch Director | F37: Branch Directors | G37: No | I37: 0 | J37: No | M37: Yes | N37: Not Invited | O37: Not Invited | P37: Not Invited | Q37: Not Invited | R37: Not Invited | S37: https://www.linkedin.com/in/ck-seah/ | T37: =IF($B37="","",COUNTA($N37:$R37)-COUNTIF($N37:$R37,"Not Invited")) -> 0 | U37: =IF($B37="","",COUNTIF($N37:$R37,"Attended")) -> 0 | V37: =IF($B37="","",_xlfn.TEXTJOIN(", ",TRUE(),IF($N37="Attended",Setup!$D$15,""),IF($O37="Attended",Setup!$D$16,""),IF($P37="Attended",Setup!$D$17,""),IF($Q37="Attended",Setup!$D$18,""),IF($R37="Attended",Setup!$D$19,""))) | W37: =IF(OR($B37="",NOT(ISNUMBER($H37))),"",TODAY()-$H37) | X37: =IF($B37="","",IF($U37>0,"Event attendee",IF($G37="Yes","Met (no event)",IF($T37>0,"Invited only",IF(OR($L37="Yes",$M37="Yes"),"Contacted only","Not yet contacted"))))) -> Contacted only | Y37: =IF($B37="","",COUNTIF(c_Firm,"<"&$D37)+COUNTIFS(c_Firm,$D37,c_Name,"<"&$B37)+COUNTIFS($D$2:$D37,$D37,$B$2:$B37,$B37)) -> 36 | Z37: =IF($B37="","",IF(AND(OR(Contacts!$C$3="(All)",$D37=Contacts!$C$3),OR(Contacts!$E$3="(All)",$G37=Contacts!$E$3),OR(Contacts!$G$3="(All)",ISNUMBER(SEARCH(Contacts!$G$3,$V37))),OR(Contacts!$I$3="(All)",$X37=Contacts!$I$3),OR(Contacts!$K$3="",ISNUMBER(SEARCH(Contacts!$K$3,$B37&" "&$C37&" "&$D37&" "&$S37)))),1,0)) -> 1 | AA37: =IF($Z37=1,COUNTIFS(c_Pass,1,c_Sort,"<="&$Y37),"") -> 36 | AB37: =IF(OR($G37<>"Yes",NOT(ISNUMBER($H37))),"",COUNTIFS(c_Met,"Yes",c_Date,"<"&$H37)+COUNTIFS($G$2:$G37,"Yes",$H$2:$H37,$H37))
A38: =IF($B38="","",COUNTA($B$2:$B38)) -> 37 | B38: ChinSiong Yee | D38: Finexis Advisory | E38: Branch Director | F38: Branch Directors | G38: No | I38: 0 | J38: No | M38: Yes | N38: Not Invited | O38: Not Invited | P38: Not Invited | Q38: Not Invited | R38: Not Invited | S38: https://www.linkedin.com/in/chinsiong-y-4149405b/ | T38: =IF($B38="","",COUNTA($N38:$R38)-COUNTIF($N38:$R38,"Not Invited")) -> 0 | U38: =IF($B38="","",COUNTIF($N38:$R38,"Attended")) -> 0 | V38: =IF($B38="","",_xlfn.TEXTJOIN(", ",TRUE(),IF($N38="Attended",Setup!$D$15,""),IF($O38="Attended",Setup!$D$16,""),IF($P38="Attended",Setup!$D$17,""),IF($Q38="Attended",Setup!$D$18,""),IF($R38="Attended",Setup!$D$19,""))) | W38: =IF(OR($B38="",NOT(ISNUMBER($H38))),"",TODAY()-$H38) | X38: =IF($B38="","",IF($U38>0,"Event attendee",IF($G38="Yes","Met (no event)",IF($T38>0,"Invited only",IF(OR($L38="Yes",$M38="Yes"),"Contacted only","Not yet contacted"))))) -> Contacted only | Y38: =IF($B38="","",COUNTIF(c_Firm,"<"&$D38)+COUNTIFS(c_Firm,$D38,c_Name,"<"&$B38)+COUNTIFS($D$2:$D38,$D38,$B$2:$B38,$B38)) -> 37 | Z38: =IF($B38="","",IF(AND(OR(Contacts!$C$3="(All)",$D38=Contacts!$C$3),OR(Contacts!$E$3="(All)",$G38=Contacts!$E$3),OR(Contacts!$G$3="(All)",ISNUMBER(SEARCH(Contacts!$G$3,$V38))),OR(Contacts!$I$3="(All)",$X38=Contacts!$I$3),OR(Contacts!$K$3="",ISNUMBER(SEARCH(Contacts!$K$3,$B38&" "&$C38&" "&$D38&" "&$S38)))),1,0)) -> 1 | AA38: =IF($Z38=1,COUNTIFS(c_Pass,1,c_Sort,"<="&$Y38),"") -> 37 | AB38: =IF(OR($G38<>"Yes",NOT(ISNUMBER($H38))),"",COUNTIFS(c_Met,"Yes",c_Date,"<"&$H38)+COUNTIFS($G$2:$G38,"Yes",$H$2:$H38,$H38))
A39: =IF($B39="","",COUNTA($B$2:$B39)) -> 38 | B39: Danny Neo | D39: Finexis Advisory | E39: Branch Director | F39: Branch Directors | G39: No | I39: 0 | J39: No | M39: Yes | N39: Not Invited | O39: Not Invited | P39: Not Invited | Q39: Not Invited | R39: Not Invited | S39: https://www.linkedin.com/in/danny-neo-16497a85/ | T39: =IF($B39="","",COUNTA($N39:$R39)-COUNTIF($N39:$R39,"Not Invited")) -> 0 | U39: =IF($B39="","",COUNTIF($N39:$R39,"Attended")) -> 0 | V39: =IF($B39="","",_xlfn.TEXTJOIN(", ",TRUE(),IF($N39="Attended",Setup!$D$15,""),IF($O39="Attended",Setup!$D$16,""),IF($P39="Attended",Setup!$D$17,""),IF($Q39="Attended",Setup!$D$18,""),IF($R39="Attended",Setup!$D$19,""))) | W39: =IF(OR($B39="",NOT(ISNUMBER($H39))),"",TODAY()-$H39) | X39: =IF($B39="","",IF($U39>0,"Event attendee",IF($G39="Yes","Met (no event)",IF($T39>0,"Invited only",IF(OR($L39="Yes",$M39="Yes"),"Contacted only","Not yet contacted"))))) -> Contacted only | Y39: =IF($B39="","",COUNTIF(c_Firm,"<"&$D39)+COUNTIFS(c_Firm,$D39,c_Name,"<"&$B39)+COUNTIFS($D$2:$D39,$D39,$B$2:$B39,$B39)) -> 38 | Z39: =IF($B39="","",IF(AND(OR(Contacts!$C$3="(All)",$D39=Contacts!$C$3),OR(Contacts!$E$3="(All)",$G39=Contacts!$E$3),OR(Contacts!$G$3="(All)",ISNUMBER(SEARCH(Contacts!$G$3,$V39))),OR(Contacts!$I$3="(All)",$X39=Contacts!$I$3),OR(Contacts!$K$3="",ISNUMBER(SEARCH(Contacts!$K$3,$B39&" "&$C39&" "&$D39&" "&$S39)))),1,0)) -> 1 | AA39: =IF($Z39=1,COUNTIFS(c_Pass,1,c_Sort,"<="&$Y39),"") -> 38 | AB39: =IF(OR($G39<>"Yes",NOT(ISNUMBER($H39))),"",COUNTIFS(c_Met,"Yes",c_Date,"<"&$H39)+COUNTIFS($G$2:$G39,"Yes",$H$2:$H39,$H39))
A40: =IF($B40="","",COUNTA($B$2:$B40)) -> 39 | B40: Darryl Low | D40: Finexis Advisory | E40: Branch Director | F40: Branch Directors | G40: No | I40: 0 | J40: No | M40: Yes | N40: Not Invited | O40: Not Invited | P40: Not Invited | Q40: Not Invited | R40: Not Invited | S40: https://www.linkedin.com/in/darryllowkh/ | T40: =IF($B40="","",COUNTA($N40:$R40)-COUNTIF($N40:$R40,"Not Invited")) -> 0 | U40: =IF($B40="","",COUNTIF($N40:$R40,"Attended")) -> 0 | V40: =IF($B40="","",_xlfn.TEXTJOIN(", ",TRUE(),IF($N40="Attended",Setup!$D$15,""),IF($O40="Attended",Setup!$D$16,""),IF($P40="Attended",Setup!$D$17,""),IF($Q40="Attended",Setup!$D$18,""),IF($R40="Attended",Setup!$D$19,""))) | W40: =IF(OR($B40="",NOT(ISNUMBER($H40))),"",TODAY()-$H40) | X40: =IF($B40="","",IF($U40>0,"Event attendee",IF($G40="Yes","Met (no event)",IF($T40>0,"Invited only",IF(OR($L40="Yes",$M40="Yes"),"Contacted only","Not yet contacted"))))) -> Contacted only | Y40: =IF($B40="","",COUNTIF(c_Firm,"<"&$D40)+COUNTIFS(c_Firm,$D40,c_Name,"<"&$B40)+COUNTIFS($D$2:$D40,$D40,$B$2:$B40,$B40)) -> 39 | Z40: =IF($B40="","",IF(AND(OR(Contacts!$C$3="(All)",$D40=Contacts!$C$3),OR(Contacts!$E$3="(All)",$G40=Contacts!$E$3),OR(Contacts!$G$3="(All)",ISNUMBER(SEARCH(Contacts!$G$3,$V40))),OR(Contacts!$I$3="(All)",$X40=Contacts!$I$3),OR(Contacts!$K$3="",ISNUMBER(SEARCH(Contacts!$K$3,$B40&" "&$C40&" "&$D40&" "&$S40)))),1,0)) -> 1 | AA40: =IF($Z40=1,COUNTIFS(c_Pass,1,c_Sort,"<="&$Y40),"") -> 39 | AB40: =IF(OR($G40<>"Yes",NOT(ISNUMBER($H40))),"",COUNTIFS(c_Met,"Yes",c_Date,"<"&$H40)+COUNTIFS($G$2:$G40,"Yes",$H$2:$H40,$H40))
A41: =IF($B41="","",COUNTA($B$2:$B41)) -> 40 | B41: Daryl Peck | D41: Finexis Advisory | E41: Branch Director | F41: Branch Directors | G41: No | I41: 0 | J41: No | M41: No | N41: Not Invited | O41: Not Invited | P41: Not Invited | Q41: Not Invited | R41: Not Invited | T41: =IF($B41="","",COUNTA($N41:$R41)-COUNTIF($N41:$R41,"Not Invited")) -> 0 | U41: =IF($B41="","",COUNTIF($N41:$R41,"Attended")) -> 0 | V41: =IF($B41="","",_xlfn.TEXTJOIN(", ",TRUE(),IF($N41="Attended",Setup!$D$15,""),IF($O41="Attended",Setup!$D$16,""),IF($P41="Attended",Setup!$D$17,""),IF($Q41="Attended",Setup!$D$18,""),IF($R41="Attended",Setup!$D$19,""))) | W41: =IF(OR($B41="",NOT(ISNUMBER($H41))),"",TODAY()-$H41) | X41: =IF($B41="","",IF($U41>0,"Event attendee",IF($G41="Yes","Met (no event)",IF($T41>0,"Invited only",IF(OR($L41="Yes",$M41="Yes"),"Contacted only","Not yet contacted"))))) -> Not yet contacted | Y41: =IF($B41="","",COUNTIF(c_Firm,"<"&$D41)+COUNTIFS(c_Firm,$D41,c_Name,"<"&$B41)+COUNTIFS($D$2:$D41,$D41,$B$2:$B41,$B41)) -> 40 | Z41: =IF($B41="","",IF(AND(OR(Contacts!$C$3="(All)",$D41=Contacts!$C$3),OR(Contacts!$E$3="(All)",$G41=Contacts!$E$3),OR(Contacts!$G$3="(All)",ISNUMBER(SEARCH(Contacts!$G$3,$V41))),OR(Contacts!$I$3="(All)",$X41=Contacts!$I$3),OR(Contacts!$K$3="",ISNUMBER(SEARCH(Contacts!$K$3,$B41&" "&$C41&" "&$D41&" "&$S41)))),1,0)) -> 1 | AA41: =IF($Z41=1,COUNTIFS(c_Pass,1,c_Sort,"<="&$Y41),"") -> 40 | AB41: =IF(OR($G41<>"Yes",NOT(ISNUMBER($H41))),"",COUNTIFS(c_Met,"Yes",c_Date,"<"&$H41)+COUNTIFS($G$2:$G41,"Yes",$H$2:$H41,$H41))
A42: =IF($B42="","",COUNTA($B$2:$B42)) -> 41 | B42: Desmund Chin | D42: Finexis Advisory | E42: Branch Director | F42: Branch Directors | G42: No | I42: 0 | J42: No | M42: Yes | N42: Not Invited | O42: Not Invited | P42: Not Invited | Q42: Not Invited | R42: Not Invited | S42: https://www.linkedin.com/in/desmund-chin-aa81436/ | T42: =IF($B42="","",COUNTA($N42:$R42)-COUNTIF($N42:$R42,"Not Invited")) -> 0 | U42: =IF($B42="","",COUNTIF($N42:$R42,"Attended")) -> 0 | V42: =IF($B42="","",_xlfn.TEXTJOIN(", ",TRUE(),IF($N42="Attended",Setup!$D$15,""),IF($O42="Attended",Setup!$D$16,""),IF($P42="Attended",Setup!$D$17,""),IF($Q42="Attended",Setup!$D$18,""),IF($R42="Attended",Setup!$D$19,""))) | W42: =IF(OR($B42="",NOT(ISNUMBER($H42))),"",TODAY()-$H42) | X42: =IF($B42="","",IF($U42>0,"Event attendee",IF($G42="Yes","Met (no event)",IF($T42>0,"Invited only",IF(OR($L42="Yes",$M42="Yes"),"Contacted only","Not yet contacted"))))) -> Contacted only | Y42: =IF($B42="","",COUNTIF(c_Firm,"<"&$D42)+COUNTIFS(c_Firm,$D42,c_Name,"<"&$B42)+COUNTIFS($D$2:$D42,$D42,$B$2:$B42,$B42)) -> 41 | Z42: =IF($B42="","",IF(AND(OR(Contacts!$C$3="(All)",$D42=Contacts!$C$3),OR(Contacts!$E$3="(All)",$G42=Contacts!$E$3),OR(Contacts!$G$3="(All)",ISNUMBER(SEARCH(Contacts!$G$3,$V42))),OR(Contacts!$I$3="(All)",$X42=Contacts!$I$3),OR(Contacts!$K$3="",ISNUMBER(SEARCH(Contacts!$K$3,$B42&" "&$C42&" "&$D42&" "&$S42)))),1,0)) -> 1 | AA42: =IF($Z42=1,COUNTIFS(c_Pass,1,c_Sort,"<="&$Y42),"") -> 41 | AB42: =IF(OR($G42<>"Yes",NOT(ISNUMBER($H42))),"",COUNTIFS(c_Met,"Yes",c_Date,"<"&$H42)+COUNTIFS($G$2:$G42,"Yes",$H$2:$H42,$H42))
A43: =IF($B43="","",COUNTA($B$2:$B43)) -> 42 | B43: En Hao Hee | D43: Finexis Advisory | E43: Branch Director | F43: Branch Directors | G43: No | I43: 0 | J43: No | M43: Yes | N43: Not Invited | O43: Not Invited | P43: Not Invited | Q43: Not Invited | R43: Not Invited | S43: https://www.linkedin.com/in/enhaohee/ | T43: =IF($B43="","",COUNTA($N43:$R43)-COUNTIF($N43:$R43,"Not Invited")) -> 0 | U43: =IF($B43="","",COUNTIF($N43:$R43,"Attended")) -> 0 | V43: =IF($B43="","",_xlfn.TEXTJOIN(", ",TRUE(),IF($N43="Attended",Setup!$D$15,""),IF($O43="Attended",Setup!$D$16,""),IF($P43="Attended",Setup!$D$17,""),IF($Q43="Attended",Setup!$D$18,""),IF($R43="Attended",Setup!$D$19,""))) | W43: =IF(OR($B43="",NOT(ISNUMBER($H43))),"",TODAY()-$H43) | X43: =IF($B43="","",IF($U43>0,"Event attendee",IF($G43="Yes","Met (no event)",IF($T43>0,"Invited only",IF(OR($L43="Yes",$M43="Yes"),"Contacted only","Not yet contacted"))))) -> Contacted only | Y43: =IF($B43="","",COUNTIF(c_Firm,"<"&$D43)+COUNTIFS(c_Firm,$D43,c_Name,"<"&$B43)+COUNTIFS($D$2:$D43,$D43,$B$2:$B43,$B43)) -> 42 | Z43: =IF($B43="","",IF(AND(OR(Contacts!$C$3="(All)",$D43=Contacts!$C$3),OR(Contacts!$E$3="(All)",$G43=Contacts!$E$3),OR(Contacts!$G$3="(All)",ISNUMBER(SEARCH(Contacts!$G$3,$V43))),OR(Contacts!$I$3="(All)",$X43=Contacts!$I$3),OR(Contacts!$K$3="",ISNUMBER(SEARCH(Contacts!$K$3,$B43&" "&$C43&" "&$D43&" "&$S43)))),1,0)) -> 1 | AA43: =IF($Z43=1,COUNTIFS(c_Pass,1,c_Sort,"<="&$Y43),"") -> 42 | AB43: =IF(OR($G43<>"Yes",NOT(ISNUMBER($H43))),"",COUNTIFS(c_Met,"Yes",c_Date,"<"&$H43)+COUNTIFS($G$2:$G43,"Yes",$H$2:$H43,$H43))
A44: =IF($B44="","",COUNTA($B$2:$B44)) -> 43 | B44: Eric Lau | D44: Finexis Advisory | E44: Branch Director | F44: Branch Directors | G44: No | I44: 0 | J44: No | M44: Yes | N44: Not Invited | O44: Not Invited | P44: Not Invited | Q44: Not Invited | R44: Not Invited | T44: =IF($B44="","",COUNTA($N44:$R44)-COUNTIF($N44:$R44,"Not Invited")) -> 0 | U44: =IF($B44="","",COUNTIF($N44:$R44,"Attended")) -> 0 | V44: =IF($B44="","",_xlfn.TEXTJOIN(", ",TRUE(),IF($N44="Attended",Setup!$D$15,""),IF($O44="Attended",Setup!$D$16,""),IF($P44="Attended",Setup!$D$17,""),IF($Q44="Attended",Setup!$D$18,""),IF($R44="Attended",Setup!$D$19,""))) | W44: =IF(OR($B44="",NOT(ISNUMBER($H44))),"",TODAY()-$H44) | X44: =IF($B44="","",IF($U44>0,"Event attendee",IF($G44="Yes","Met (no event)",IF($T44>0,"Invited only",IF(OR($L44="Yes",$M44="Yes"),"Contacted only","Not yet contacted"))))) -> Contacted only | Y44: =IF($B44="","",COUNTIF(c_Firm,"<"&$D44)+COUNTIFS(c_Firm,$D44,c_Name,"<"&$B44)+COUNTIFS($D$2:$D44,$D44,$B$2:$B44,$B44)) -> 43 | Z44: =IF($B44="","",IF(AND(OR(Contacts!$C$3="(All)",$D44=Contacts!$C$3),OR(Contacts!$E$3="(All)",$G44=Contacts!$E$3),OR(Contacts!$G$3="(All)",ISNUMBER(SEARCH(Contacts!$G$3,$V44))),OR(Contacts!$I$3="(All)",$X44=Contacts!$I$3),OR(Contacts!$K$3="",ISNUMBER(SEARCH(Contacts!$K$3,$B44&" "&$C44&" "&$D44&" "&$S44)))),1,0)) -> 1 | AA44: =IF($Z44=1,COUNTIFS(c_Pass,1,c_Sort,"<="&$Y44),"") -> 43 | AB44: =IF(OR($G44<>"Yes",NOT(ISNUMBER($H44))),"",COUNTIFS(c_Met,"Yes",c_Date,"<"&$H44)+COUNTIFS($G$2:$G44,"Yes",$H$2:$H44,$H44))
A45: =IF($B45="","",COUNTA($B$2:$B45)) -> 44 | B45: Felicia Pan | D45: Finexis Advisory | E45: Branch Director | F45: Branch Directors | G45: No | I45: 0 | J45: No | M45: Yes | N45: Not Invited | O45: Not Invited | P45: Not Invited | Q45: Not Invited | R45: Not Invited | S45: https://www.linkedin.com/in/felicia-pan-88a19781/ | T45: =IF($B45="","",COUNTA($N45:$R45)-COUNTIF($N45:$R45,"Not Invited")) -> 0 | U45: =IF($B45="","",COUNTIF($N45:$R45,"Attended")) -> 0 | V45: =IF($B45="","",_xlfn.TEXTJOIN(", ",TRUE(),IF($N45="Attended",Setup!$D$15,""),IF($O45="Attended",Setup!$D$16,""),IF($P45="Attended",Setup!$D$17,""),IF($Q45="Attended",Setup!$D$18,""),IF($R45="Attended",Setup!$D$19,""))) | W45: =IF(OR($B45="",NOT(ISNUMBER($H45))),"",TODAY()-$H45) | X45: =IF($B45="","",IF($U45>0,"Event attendee",IF($G45="Yes","Met (no event)",IF($T45>0,"Invited only",IF(OR($L45="Yes",$M45="Yes"),"Contacted only","Not yet contacted"))))) -> Contacted only | Y45: =IF($B45="","",COUNTIF(c_Firm,"<"&$D45)+COUNTIFS(c_Firm,$D45,c_Name,"<"&$B45)+COUNTIFS($D$2:$D45,$D45,$B$2:$B45,$B45)) -> 44 | Z45: =IF($B45="","",IF(AND(OR(Contacts!$C$3="(All)",$D45=Contacts!$C$3),OR(Contacts!$E$3="(All)",$G45=Contacts!$E$3),OR(Contacts!$G$3="(All)",ISNUMBER(SEARCH(Contacts!$G$3,$V45))),OR(Contacts!$I$3="(All)",$X45=Contacts!$I$3),OR(Contacts!$K$3="",ISNUMBER(SEARCH(Contacts!$K$3,$B45&" "&$C45&" "&$D45&" "&$S45)))),1,0)) -> 1 | AA45: =IF($Z45=1,COUNTIFS(c_Pass,1,c_Sort,"<="&$Y45),"") -> 44 | AB45: =IF(OR($G45<>"Yes",NOT(ISNUMBER($H45))),"",COUNTIFS(c_Met,"Yes",c_Date,"<"&$H45)+COUNTIFS($G$2:$G45,"Yes",$H$2:$H45,$H45))
A46: =IF($B46="","",COUNTA($B$2:$B46)) -> 45 | B46: Foong Kin Peng | D46: Finexis Advisory | E46: Branch Director | F46: Branch Directors | G46: No | I46: 0 | J46: No | M46: Yes | N46: Not Invited | O46: Not Invited | P46: Not Invited | Q46: Not Invited | R46: Not Invited | S46: https://www.linkedin.com/in/foongkinpeng/ | T46: =IF($B46="","",COUNTA($N46:$R46)-COUNTIF($N46:$R46,"Not Invited")) -> 0 | U46: =IF($B46="","",COUNTIF($N46:$R46,"Attended")) -> 0 | V46: =IF($B46="","",_xlfn.TEXTJOIN(", ",TRUE(),IF($N46="Attended",Setup!$D$15,""),IF($O46="Attended",Setup!$D$16,""),IF($P46="Attended",Setup!$D$17,""),IF($Q46="Attended",Setup!$D$18,""),IF($R46="Attended",Setup!$D$19,""))) | W46: =IF(OR($B46="",NOT(ISNUMBER($H46))),"",TODAY()-$H46) | X46: =IF($B46="","",IF($U46>0,"Event attendee",IF($G46="Yes","Met (no event)",IF($T46>0,"Invited only",IF(OR($L46="Yes",$M46="Yes"),"Contacted only","Not yet contacted"))))) -> Contacted only | Y46: =IF($B46="","",COUNTIF(c_Firm,"<"&$D46)+COUNTIFS(c_Firm,$D46,c_Name,"<"&$B46)+COUNTIFS($D$2:$D46,$D46,$B$2:$B46,$B46)) -> 45 | Z46: =IF($B46="","",IF(AND(OR(Contacts!$C$3="(All)",$D46=Contacts!$C$3),OR(Contacts!$E$3="(All)",$G46=Contacts!$E$3),OR(Contacts!$G$3="(All)",ISNUMBER(SEARCH(Contacts!$G$3,$V46))),OR(Contacts!$I$3="(All)",$X46=Contacts!$I$3),OR(Contacts!$K$3="",ISNUMBER(SEARCH(Contacts!$K$3,$B46&" "&$C46&" "&$D46&" "&$S46)))),1,0)) -> 1 | AA46: =IF($Z46=1,COUNTIFS(c_Pass,1,c_Sort,"<="&$Y46),"") -> 45 | AB46: =IF(OR($G46<>"Yes",NOT(ISNUMBER($H46))),"",COUNTIFS(c_Met,"Yes",c_Date,"<"&$H46)+COUNTIFS($G$2:$G46,"Yes",$H$2:$H46,$H46))
A47: =IF($B47="","",COUNTA($B$2:$B47)) -> 46 | B47: Garry Goh | D47: Finexis Advisory | E47: Branch Director | F47: Branch Directors | G47: No | I47: 0 | J47: No | M47: Yes | N47: Not Invited | O47: Not Invited | P47: Not Invited | Q47: Not Invited | R47: Not Invited | S47: Branch: Team GGO | https://www.linkedin.com/in/garry-goh-82b41740/ | T47: =IF($B47="","",COUNTA($N47:$R47)-COUNTIF($N47:$R47,"Not Invited")) -> 0 | U47: =IF($B47="","",COUNTIF($N47:$R47,"Attended")) -> 0 | V47: =IF($B47="","",_xlfn.TEXTJOIN(", ",TRUE(),IF($N47="Attended",Setup!$D$15,""),IF($O47="Attended",Setup!$D$16,""),IF($P47="Attended",Setup!$D$17,""),IF($Q47="Attended",Setup!$D$18,""),IF($R47="Attended",Setup!$D$19,""))) | W47: =IF(OR($B47="",NOT(ISNUMBER($H47))),"",TODAY()-$H47) | X47: =IF($B47="","",IF($U47>0,"Event attendee",IF($G47="Yes","Met (no event)",IF($T47>0,"Invited only",IF(OR($L47="Yes",$M47="Yes"),"Contacted only","Not yet contacted"))))) -> Contacted only | Y47: =IF($B47="","",COUNTIF(c_Firm,"<"&$D47)+COUNTIFS(c_Firm,$D47,c_Name,"<"&$B47)+COUNTIFS($D$2:$D47,$D47,$B$2:$B47,$B47)) -> 46 | Z47: =IF($B47="","",IF(AND(OR(Contacts!$C$3="(All)",$D47=Contacts!$C$3),OR(Contacts!$E$3="(All)",$G47=Contacts!$E$3),OR(Contacts!$G$3="(All)",ISNUMBER(SEARCH(Contacts!$G$3,$V47))),OR(Contacts!$I$3="(All)",$X47=Contacts!$I$3),OR(Contacts!$K$3="",ISNUMBER(SEARCH(Contacts!$K$3,$B47&" "&$C47&" "&$D47&" "&$S47)))),1,0)) -> 1 | AA47: =IF($Z47=1,COUNTIFS(c_Pass,1,c_Sort,"<="&$Y47),"") -> 46 | AB47: =IF(OR($G47<>"Yes",NOT(ISNUMBER($H47))),"",COUNTIFS(c_Met,"Yes",c_Date,"<"&$H47)+COUNTIFS($G$2:$G47,"Yes",$H$2:$H47,$H47))
A48: =IF($B48="","",COUNTA($B$2:$B48)) -> 47 | B48: Gary Yong | D48: Finexis Advisory | E48: Branch Director | F48: Branch Directors | G48: No | I48: 0 | J48: No | M48: Yes | N48: Not Invited | O48: Not Invited | P48: Not Invited | Q48: Not Invited | R48: Not Invited | S48: https://www.linkedin.com/in/garyyongwk/ | T48: =IF($B48="","",COUNTA($N48:$R48)-COUNTIF($N48:$R48,"Not Invited")) -> 0 | U48: =IF($B48="","",COUNTIF($N48:$R48,"Attended")) -> 0 | V48: =IF($B48="","",_xlfn.TEXTJOIN(", ",TRUE(),IF($N48="Attended",Setup!$D$15,""),IF($O48="Attended",Setup!$D$16,""),IF($P48="Attended",Setup!$D$17,""),IF($Q48="Attended",Setup!$D$18,""),IF($R48="Attended",Setup!$D$19,""))) | W48: =IF(OR($B48="",NOT(ISNUMBER($H48))),"",TODAY()-$H48) | X48: =IF($B48="","",IF($U48>0,"Event attendee",IF($G48="Yes","Met (no event)",IF($T48>0,"Invited only",IF(OR($L48="Yes",$M48="Yes"),"Contacted only","Not yet contacted"))))) -> Contacted only | Y48: =IF($B48="","",COUNTIF(c_Firm,"<"&$D48)+COUNTIFS(c_Firm,$D48,c_Name,"<"&$B48)+COUNTIFS($D$2:$D48,$D48,$B$2:$B48,$B48)) -> 47 | Z48: =IF($B48="","",IF(AND(OR(Contacts!$C$3="(All)",$D48=Contacts!$C$3),OR(Contacts!$E$3="(All)",$G48=Contacts!$E$3),OR(Contacts!$G$3="(All)",ISNUMBER(SEARCH(Contacts!$G$3,$V48))),OR(Contacts!$I$3="(All)",$X48=Contacts!$I$3),OR(Contacts!$K$3="",ISNUMBER(SEARCH(Contacts!$K$3,$B48&" "&$C48&" "&$D48&" "&$S48)))),1,0)) -> 1 | AA48: =IF($Z48=1,COUNTIFS(c_Pass,1,c_Sort,"<="&$Y48),"") -> 47 | AB48: =IF(OR($G48<>"Yes",NOT(ISNUMBER($H48))),"",COUNTIFS(c_Met,"Yes",c_Date,"<"&$H48)+COUNTIFS($G$2:$G48,"Yes",$H$2:$H48,$H48))
A49: =IF($B49="","",COUNTA($B$2:$B49)) -> 48 | B49: Gregory Ong | D49: Finexis Advisory | E49: Branch Director | F49: Branch Directors | G49: No | I49: 0 | J49: No | M49: Yes | N49: Not Invited | O49: Not Invited | P49: Not Invited | Q49: Not Invited | R49: Not Invited | S49: https://www.linkedin.com/in/gregory-ong-7009679a/ | T49: =IF($B49="","",COUNTA($N49:$R49)-COUNTIF($N49:$R49,"Not Invited")) -> 0 | U49: =IF($B49="","",COUNTIF($N49:$R49,"Attended")) -> 0 | V49: =IF($B49="","",_xlfn.TEXTJOIN(", ",TRUE(),IF($N49="Attended",Setup!$D$15,""),IF($O49="Attended",Setup!$D$16,""),IF($P49="Attended",Setup!$D$17,""),IF($Q49="Attended",Setup!$D$18,""),IF($R49="Attended",Setup!$D$19,""))) | W49: =IF(OR($B49="",NOT(ISNUMBER($H49))),"",TODAY()-$H49) | X49: =IF($B49="","",IF($U49>0,"Event attendee",IF($G49="Yes","Met (no event)",IF($T49>0,"Invited only",IF(OR($L49="Yes",$M49="Yes"),"Contacted only","Not yet contacted"))))) -> Contacted only | Y49: =IF($B49="","",COUNTIF(c_Firm,"<"&$D49)+COUNTIFS(c_Firm,$D49,c_Name,"<"&$B49)+COUNTIFS($D$2:$D49,$D49,$B$2:$B49,$B49)) -> 48 | Z49: =IF($B49="","",IF(AND(OR(Contacts!$C$3="(All)",$D49=Contacts!$C$3),OR(Contacts!$E$3="(All)",$G49=Contacts!$E$3),OR(Contacts!$G$3="(All)",ISNUMBER(SEARCH(Contacts!$G$3,$V49))),OR(Contacts!$I$3="(All)",$X49=Contacts!$I$3),OR(Contacts!$K$3="",ISNUMBER(SEARCH(Contacts!$K$3,$B49&" "&$C49&" "&$D49&" "&$S49)))),1,0)) -> 1 | AA49: =IF($Z49=1,COUNTIFS(c_Pass,1,c_Sort,"<="&$Y49),"") -> 48 | AB49: =IF(OR($G49<>"Yes",NOT(ISNUMBER($H49))),"",COUNTIFS(c_Met,"Yes",c_Date,"<"&$H49)+COUNTIFS($G$2:$G49,"Yes",$H$2:$H49,$H49))
A50: =IF($B50="","",COUNTA($B$2:$B50)) -> 49 | B50: Ivan Teo | D50: Finexis Advisory | E50: Branch Director | F50: Branch Directors | G50: No | I50: 0 | J50: No | M50: Yes | N50: Not Invited | O50: Not Invited | P50: Not Invited | Q50: Not Invited | R50: Not Invited | S50: Branch: Impact Wealth Advisory | T50: =IF($B50="","",COUNTA($N50:$R50)-COUNTIF($N50:$R50,"Not Invited")) -> 0 | U50: =IF($B50="","",COUNTIF($N50:$R50,"Attended")) -> 0 | V50: =IF($B50="","",_xlfn.TEXTJOIN(", ",TRUE(),IF($N50="Attended",Setup!$D$15,""),IF($O50="Attended",Setup!$D$16,""),IF($P50="Attended",Setup!$D$17,""),IF($Q50="Attended",Setup!$D$18,""),IF($R50="Attended",Setup!$D$19,""))) | W50: =IF(OR($B50="",NOT(ISNUMBER($H50))),"",TODAY()-$H50) | X50: =IF($B50="","",IF($U50>0,"Event attendee",IF($G50="Yes","Met (no event)",IF($T50>0,"Invited only",IF(OR($L50="Yes",$M50="Yes"),"Contacted only","Not yet contacted"))))) -> Contacted only | Y50: =IF($B50="","",COUNTIF(c_Firm,"<"&$D50)+COUNTIFS(c_Firm,$D50,c_Name,"<"&$B50)+COUNTIFS($D$2:$D50,$D50,$B$2:$B50,$B50)) -> 49 | Z50: =IF($B50="","",IF(AND(OR(Contacts!$C$3="(All)",$D50=Contacts!$C$3),OR(Contacts!$E$3="(All)",$G50=Contacts!$E$3),OR(Contacts!$G$3="(All)",ISNUMBER(SEARCH(Contacts!$G$3,$V50))),OR(Contacts!$I$3="(All)",$X50=Contacts!$I$3),OR(Contacts!$K$3="",ISNUMBER(SEARCH(Contacts!$K$3,$B50&" "&$C50&" "&$D50&" "&$S50)))),1,0)) -> 1 | AA50: =IF($Z50=1,COUNTIFS(c_Pass,1,c_Sort,"<="&$Y50),"") -> 49 | AB50: =IF(OR($G50<>"Yes",NOT(ISNUMBER($H50))),"",COUNTIFS(c_Met,"Yes",c_Date,"<"&$H50)+COUNTIFS($G$2:$G50,"Yes",$H$2:$H50,$H50))
A51: =IF($B51="","",COUNTA($B$2:$B51)) -> 50 | B51: Jason Ang | C51: Jason.ang@finexis.com.sg | D51: Finexis Advisory | E51: Adviser | F51: Meeting List | G51: No | I51: 0 | J51: No | N51: Not Invited | O51: Attended | P51: Not Invited | Q51: Not Invited | R51: Not Invited | T51: =IF($B51="","",COUNTA($N51:$R51)-COUNTIF($N51:$R51,"Not Invited")) -> 1 | U51: =IF($B51="","",COUNTIF($N51:$R51,"Attended")) -> 1 | V51: =IF($B51="","",_xlfn.TEXTJOIN(", ",TRUE(),IF($N51="Attended",Setup!$D$15,""),IF($O51="Attended",Setup!$D$16,""),IF($P51="Attended",Setup!$D$17,""),IF($Q51="Attended",Setup!$D$18,""),IF($R51="Attended",Setup!$D$19,""))) -> May-26 Symposium | W51: =IF(OR($B51="",NOT(ISNUMBER($H51))),"",TODAY()-$H51) | X51: =IF($B51="","",IF($U51>0,"Event attendee",IF($G51="Yes","Met (no event)",IF($T51>0,"Invited only",IF(OR($L51="Yes",$M51="Yes"),"Contacted only","Not yet contacted"))))) -> Event attendee | Y51: =IF($B51="","",COUNTIF(c_Firm,"<"&$D51)+COUNTIFS(c_Firm,$D51,c_Name,"<"&$B51)+COUNTIFS($D$2:$D51,$D51,$B$2:$B51,$B51)) -> 50 | Z51: =IF($B51="","",IF(AND(OR(Contacts!$C$3="(All)",$D51=Contacts!$C$3),OR(Contacts!$E$3="(All)",$G51=Contacts!$E$3),OR(Contacts!$G$3="(All)",ISNUMBER(SEARCH(Contacts!$G$3,$V51))),OR(Contacts!$I$3="(All)",$X51=Contacts!$I$3),OR(Contacts!$K$3="",ISNUMBER(SEARCH(Contacts!$K$3,$B51&" "&$C51&" "&$D51&" "&$S51)))),1,0)) -> 1 | AA51: =IF($Z51=1,COUNTIFS(c_Pass,1,c_Sort,"<="&$Y51),"") -> 50 | AB51: =IF(OR($G51<>"Yes",NOT(ISNUMBER($H51))),"",COUNTIFS(c_Met,"Yes",c_Date,"<"&$H51)+COUNTIFS($G$2:$G51,"Yes",$H$2:$H51,$H51))
A52: =IF($B52="","",COUNTA($B$2:$B52)) -> 51 | B52: Jessica Peh | C52: jessica.peh@finexis.com.sg | D52: Finexis Advisory | E52: Adviser | F52: Meeting List + ILP Data | G52: Yes | H52: 45994 | I52: 1 | J52: Yes | K52: 3000000 | N52: Attended | O52: Attended | P52: Not Invited | Q52: Not Invited | R52: Not Invited | T52: =IF($B52="","",COUNTA($N52:$R52)-COUNTIF($N52:$R52,"Not Invited")) -> 2 | U52: =IF($B52="","",COUNTIF($N52:$R52,"Attended")) -> 2 | V52: =IF($B52="","",_xlfn.TEXTJOIN(", ",TRUE(),IF($N52="Attended",Setup!$D$15,""),IF($O52="Attended",Setup!$D$16,""),IF($P52="Attended",Setup!$D$17,""),IF($Q52="Attended",Setup!$D$18,""),IF($R52="Attended",Setup!$D$19,""))) -> Oct-25 Symposium, May-26 Symposium | W52: =IF(OR($B52="",NOT(ISNUMBER($H52))),"",TODAY()-$H52) -> 247 | X52: =IF($B52="","",IF($U52>0,"Event attendee",IF($G52="Yes","Met (no event)",IF($T52>0,"Invited only",IF(OR($L52="Yes",$M52="Yes"),"Contacted only","Not yet contacted"))))) -> Event attendee | Y52: =IF($B52="","",COUNTIF(c_Firm,"<"&$D52)+COUNTIFS(c_Firm,$D52,c_Name,"<"&$B52)+COUNTIFS($D$2:$D52,$D52,$B$2:$B52,$B52)) -> 51 | Z52: =IF($B52="","",IF(AND(OR(Contacts!$C$3="(All)",$D52=Contacts!$C$3),OR(Contacts!$E$3="(All)",$G52=Contacts!$E$3),OR(Contacts!$G$3="(All)",ISNUMBER(SEARCH(Contacts!$G$3,$V52))),OR(Contacts!$I$3="(All)",$X52=Contacts!$I$3),OR(Contacts!$K$3="",ISNUMBER(SEARCH(Contacts!$K$3,$B52&" "&$C52&" "&$D52&" "&$S52)))),1,0)) -> 1 | AA52: =IF($Z52=1,COUNTIFS(c_Pass,1,c_Sort,"<="&$Y52),"") -> 51 | AB52: =IF(OR($G52<>"Yes",NOT(ISNUMBER($H52))),"",COUNTIFS(c_Met,"Yes",c_Date,"<"&$H52)+COUNTIFS($G$2:$G52,"Yes",$H$2:$H52,$H52)) -> 37
A53: =IF($B53="","",COUNTA($B$2:$B53)) -> 52 | B53: Jiateng Lin | C53: lin.jiateng@finexis.com.sg | D53: Finexis Advisory | E53: Adviser | F53: Meeting List | G53: No | I53: 0 | J53: No | N53: Not Invited | O53: Attended | P53: Not Invited | Q53: Not Invited | R53: Not Invited | T53: =IF($B53="","",COUNTA($N53:$R53)-COUNTIF($N53:$R53,"Not Invited")) -> 1 | U53: =IF($B53="","",COUNTIF($N53:$R53,"Attended")) -> 1 | V53: =IF($B53="","",_xlfn.TEXTJOIN(", ",TRUE(),IF($N53="Attended",Setup!$D$15,""),IF($O53="Attended",Setup!$D$16,""),IF($P53="Attended",Setup!$D$17,""),IF($Q53="Attended",Setup!$D$18,""),IF($R53="Attended",Setup!$D$19,""))) -> May-26 Symposium | W53: =IF(OR($B53="",NOT(ISNUMBER($H53))),"",TODAY()-$H53) | X53: =IF($B53="","",IF($U53>0,"Event attendee",IF($G53="Yes","Met (no event)",IF($T53>0,"Invited only",IF(OR($L53="Yes",$M53="Yes"),"Contacted only","Not yet contacted"))))) -> Event attendee | Y53: =IF($B53="","",COUNTIF(c_Firm,"<"&$D53)+COUNTIFS(c_Firm,$D53,c_Name,"<"&$B53)+COUNTIFS($D$2:$D53,$D53,$B$2:$B53,$B53)) -> 52 | Z53: =IF($B53="","",IF(AND(OR(Contacts!$C$3="(All)",$D53=Contacts!$C$3),OR(Contacts!$E$3="(All)",$G53=Contacts!$E$3),OR(Contacts!$G$3="(All)",ISNUMBER(SEARCH(Contacts!$G$3,$V53))),OR(Contacts!$I$3="(All)",$X53=Contacts!$I$3),OR(Contacts!$K$3="",ISNUMBER(SEARCH(Contacts!$K$3,$B53&" "&$C53&" "&$D53&" "&$S53)))),1,0)) -> 1 | AA53: =IF($Z53=1,COUNTIFS(c_Pass,1,c_Sort,"<="&$Y53),"") -> 52 | AB53: =IF(OR($G53<>"Yes",NOT(ISNUMBER($H53))),"",COUNTIFS(c_Met,"Yes",c_Date,"<"&$H53)+COUNTIFS($G$2:$G53,"Yes",$H$2:$H53,$H53))
A54: =IF($B54="","",COUNTA($B$2:$B54)) -> 53 | B54: Joel Chia | D54: Finexis Advisory | E54: Branch Director | F54: Branch Directors | G54: No | I54: 0 | J54: No | M54: Yes | N54: Not Invited | O54: Not Invited | P54: Not Invited | Q54: Not Invited | R54: Not Invited | S54: https://www.linkedin.com/in/joel-chia-b84a8039/ | T54: =IF($B54="","",COUNTA($N54:$R54)-COUNTIF($N54:$R54,"Not Invited")) -> 0 | U54: =IF($B54="","",COUNTIF($N54:$R54,"Attended")) -> 0 | V54: =IF($B54="","",_xlfn.TEXTJOIN(", ",TRUE(),IF($N54="Attended",Setup!$D$15,""),IF($O54="Attended",Setup!$D$16,""),IF($P54="Attended",Setup!$D$17,""),IF($Q54="Attended",Setup!$D$18,""),IF($R54="Attended",Setup!$D$19,""))) | W54: =IF(OR($B54="",NOT(ISNUMBER($H54))),"",TODAY()-$H54) | X54: =IF($B54="","",IF($U54>0,"Event attendee",IF($G54="Yes","Met (no event)",IF($T54>0,"Invited only",IF(OR($L54="Yes",$M54="Yes"),"Contacted only","Not yet contacted"))))) -> Contacted only | Y54: =IF($B54="","",COUNTIF(c_Firm,"<"&$D54)+COUNTIFS(c_Firm,$D54,c_Name,"<"&$B54)+COUNTIFS($D$2:$D54,$D54,$B$2:$B54,$B54)) -> 53 | Z54: =IF($B54="","",IF(AND(OR(Contacts!$C$3="(All)",$D54=Contacts!$C$3),OR(Contacts!$E$3="(All)",$G54=Contacts!$E$3),OR(Contacts!$G$3="(All)",ISNUMBER(SEARCH(Contacts!$G$3,$V54))),OR(Contacts!$I$3="(All)",$X54=Contacts!$I$3),OR(Contacts!$K$3="",ISNUMBER(SEARCH(Contacts!$K$3,$B54&" "&$C54&" "&$D54&" "&$S54)))),1,0)) -> 1 | AA54: =IF($Z54=1,COUNTIFS(c_Pass,1,c_Sort,"<="&$Y54),"") -> 53 | AB54: =IF(OR($G54<>"Yes",NOT(ISNUMBER($H54))),"",COUNTIFS(c_Met,"Yes",c_Date,"<"&$H54)+COUNTIFS($G$2:$G54,"Yes",$H$2:$H54,$H54))
A55: =IF($B55="","",COUNTA($B$2:$B55)) -> 54 | B55: Johnny Nimrod Chan | D55: Finexis Advisory | E55: Branch Director | F55: Branch Directors | G55: No | I55: 0 | J55: No | M55: Yes | N55: Not Invited | O55: Not Invited | P55: Not Invited | Q55: Not Invited | R55: Not Invited | S55: Branch: Faith Advisory | T55: =IF($B55="","",COUNTA($N55:$R55)-COUNTIF($N55:$R55,"Not Invited")) -> 0 | U55: =IF($B55="","",COUNTIF($N55:$R55,"Attended")) -> 0 | V55: =IF($B55="","",_xlfn.TEXTJOIN(", ",TRUE(),IF($N55="Attended",Setup!$D$15,""),IF($O55="Attended",Setup!$D$16,""),IF($P55="Attended",Setup!$D$17,""),IF($Q55="Attended",Setup!$D$18,""),IF($R55="Attended",Setup!$D$19,""))) | W55: =IF(OR($B55="",NOT(ISNUMBER($H55))),"",TODAY()-$H55) | X55: =IF($B55="","",IF($U55>0,"Event attendee",IF($G55="Yes","Met (no event)",IF($T55>0,"Invited only",IF(OR($L55="Yes",$M55="Yes"),"Contacted only","Not yet contacted"))))) -> Contacted only | Y55: =IF($B55="","",COUNTIF(c_Firm,"<"&$D55)+COUNTIFS(c_Firm,$D55,c_Name,"<"&$B55)+COUNTIFS($D$2:$D55,$D55,$B$2:$B55,$B55)) -> 54 | Z55: =IF($B55="","",IF(AND(OR(Contacts!$C$3="(All)",$D55=Contacts!$C$3),OR(Contacts!$E$3="(All)",$G55=Contacts!$E$3),OR(Contacts!$G$3="(All)",ISNUMBER(SEARCH(Contacts!$G$3,$V55))),OR(Contacts!$I$3="(All)",$X55=Contacts!$I$3),OR(Contacts!$K$3="",ISNUMBER(SEARCH(Contacts!$K$3,$B55&" "&$C55&" "&$D55&" "&$S55)))),1,0)) -> 1 | AA55: =IF($Z55=1,COUNTIFS(c_Pass,1,c_Sort,"<="&$Y55),"") -> 54 | AB55: =IF(OR($G55<>"Yes",NOT(ISNUMBER($H55))),"",COUNTIFS(c_Met,"Yes",c_Date,"<"&$H55)+COUNTIFS($G$2:$G55,"Yes",$H$2:$H55,$H55))
A56: =IF($B56="","",COUNTA($B$2:$B56)) -> 55 | B56: Julian Tan | D56: Finexis Advisory | E56: Branch Director | F56: Branch Directors | G56: No | I56: 0 | J56: No | M56: Yes | N56: Not Invited | O56: Not Invited | P56: Not Invited | Q56: Not Invited | R56: Not Invited | S56: Branch: Omega Financial Advisory Group | https://www.linkedin.com/in/juliantan-finexis/ | T56: =IF($B56="","",COUNTA($N56:$R56)-COUNTIF($N56:$R56,"Not Invited")) -> 0 | U56: =IF($B56="","",COUNTIF($N56:$R56,"Attended")) -> 0 | V56: =IF($B56="","",_xlfn.TEXTJOIN(", ",TRUE(),IF($N56="Attended",Setup!$D$15,""),IF($O56="Attended",Setup!$D$16,""),IF($P56="Attended",Setup!$D$17,""),IF($Q56="Attended",Setup!$D$18,""),IF($R56="Attended",Setup!$D$19,""))) | W56: =IF(OR($B56="",NOT(ISNUMBER($H56))),"",TODAY()-$H56) | X56: =IF($B56="","",IF($U56>0,"Event attendee",IF($G56="Yes","Met (no event)",IF($T56>0,"Invited only",IF(OR($L56="Yes",$M56="Yes"),"Contacted only","Not yet contacted"))))) -> Contacted only | Y56: =IF($B56="","",COUNTIF(c_Firm,"<"&$D56)+COUNTIFS(c_Firm,$D56,c_Name,"<"&$B56)+COUNTIFS($D$2:$D56,$D56,$B$2:$B56,$B56)) -> 55 | Z56: =IF($B56="","",IF(AND(OR(Contacts!$C$3="(All)",$D56=Contacts!$C$3),OR(Contacts!$E$3="(All)",$G56=Contacts!$E$3),OR(Contacts!$G$3="(All)",ISNUMBER(SEARCH(Contacts!$G$3,$V56))),OR(Contacts!$I$3="(All)",$X56=Contacts!$I$3),OR(Contacts!$K$3="",ISNUMBER(SEARCH(Contacts!$K$3,$B56&" "&$C56&" "&$D56&" "&$S56)))),1,0)) -> 1 | AA56: =IF($Z56=1,COUNTIFS(c_Pass,1,c_Sort,"<="&$Y56),"") -> 55 | AB56: =IF(OR($G56<>"Yes",NOT(ISNUMBER($H56))),"",COUNTIFS(c_Met,"Yes",c_Date,"<"&$H56)+COUNTIFS($G$2:$G56,"Yes",$H$2:$H56,$H56))
A57: =IF($B57="","",COUNTA($B$2:$B57)) -> 56 | B57: Keziah Choy Yau Wong | D57: Finexis Advisory | E57: Branch Director | F57: Branch Directors | G57: No | I57: 0 | J57: No | M57: Yes | N57: Not Invited | O57: Not Invited | P57: Not Invited | Q57: Not Invited | R57: Not Invited | S57: Branch: Keziah & Associates Wealth Arkiteks | Already in CRM | T57: =IF($B57="","",COUNTA($N57:$R57)-COUNTIF($N57:$R57,"Not Invited")) -> 0 | U57: =IF($B57="","",COUNTIF($N57:$R57,"Attended")) -> 0 | V57: =IF($B57="","",_xlfn.TEXTJOIN(", ",TRUE(),IF($N57="Attended",Setup!$D$15,""),IF($O57="Attended",Setup!$D$16,""),IF($P57="Attended",Setup!$D$17,""),IF($Q57="Attended",Setup!$D$18,""),IF($R57="Attended",Setup!$D$19,""))) | W57: =IF(OR($B57="",NOT(ISNUMBER($H57))),"",TODAY()-$H57) | X57: =IF($B57="","",IF($U57>0,"Event attendee",IF($G57="Yes","Met (no event)",IF($T57>0,"Invited only",IF(OR($L57="Yes",$M57="Yes"),"Contacted only","Not yet contacted"))))) -> Contacted only | Y57: =IF($B57="","",COUNTIF(c_Firm,"<"&$D57)+COUNTIFS(c_Firm,$D57,c_Name,"<"&$B57)+COUNTIFS($D$2:$D57,$D57,$B$2:$B57,$B57)) -> 56 | Z57: =IF($B57="","",IF(AND(OR(Contacts!$C$3="(All)",$D57=Contacts!$C$3),OR(Contacts!$E$3="(All)",$G57=Contacts!$E$3),OR(Contacts!$G$3="(All)",ISNUMBER(SEARCH(Contacts!$G$3,$V57))),OR(Contacts!$I$3="(All)",$X57=Contacts!$I$3),OR(Contacts!$K$3="",ISNUMBER(SEARCH(Contacts!$K$3,$B57&" "&$C57&" "&$D57&" "&$S57)))),1,0)) -> 1 | AA57: =IF($Z57=1,COUNTIFS(c_Pass,1,c_Sort,"<="&$Y57),"") -> 56 | AB57: =IF(OR($G57<>"Yes",NOT(ISNUMBER($H57))),"",COUNTIFS(c_Met,"Yes",c_Date,"<"&$H57)+COUNTIFS($G$2:$G57,"Yes",$H$2:$H57,$H57))
A58: =IF($B58="","",COUNTA($B$2:$B58)) -> 57 | B58: Kiat Hwee Sim | D58: Finexis Advisory | E58: Branch Director | F58: Branch Directors | G58: No | I58: 0 | J58: No | M58: Yes | N58: Not Invited | O58: Not Invited | P58: Not Invited | Q58: Not Invited | R58: Not Invited | S58: https://www.linkedin.com/in/kiat-hwee-sim-429b05bb/ | T58: =IF($B58="","",COUNTA($N58:$R58)-COUNTIF($N58:$R58,"Not Invited")) -> 0 | U58: =IF($B58="","",COUNTIF($N58:$R58,"Attended")) -> 0 | V58: =IF($B58="","",_xlfn.TEXTJOIN(", ",TRUE(),IF($N58="Attended",Setup!$D$15,""),IF($O58="Attended",Setup!$D$16,""),IF($P58="Attended",Setup!$D$17,""),IF($Q58="Attended",Setup!$D$18,""),IF($R58="Attended",Setup!$D$19,""))) | W58: =IF(OR($B58="",NOT(ISNUMBER($H58))),"",TODAY()-$H58) | X58: =IF($B58="","",IF($U58>0,"Event attendee",IF($G58="Yes","Met (no event)",IF($T58>0,"Invited only",IF(OR($L58="Yes",$M58="Yes"),"Contacted only","Not yet contacted"))))) -> Contacted only | Y58: =IF($B58="","",COUNTIF(c_Firm,"<"&$D58)+COUNTIFS(c_Firm,$D58,c_Name,"<"&$B58)+COUNTIFS($D$2:$D58,$D58,$B$2:$B58,$B58)) -> 57 | Z58: =IF($B58="","",IF(AND(OR(Contacts!$C$3="(All)",$D58=Contacts!$C$3),OR(Contacts!$E$3="(All)",$G58=Contacts!$E$3),OR(Contacts!$G$3="(All)",ISNUMBER(SEARCH(Contacts!$G$3,$V58))),OR(Contacts!$I$3="(All)",$X58=Contacts!$I$3),OR(Contacts!$K$3="",ISNUMBER(SEARCH(Contacts!$K$3,$B58&" "&$C58&" "&$D58&" "&$S58)))),1,0)) -> 1 | AA58: =IF($Z58=1,COUNTIFS(c_Pass,1,c_Sort,"<="&$Y58),"") -> 57 | AB58: =IF(OR($G58<>"Yes",NOT(ISNUMBER($H58))),"",COUNTIFS(c_Met,"Yes",c_Date,"<"&$H58)+COUNTIFS($G$2:$G58,"Yes",$H$2:$H58,$H58))
A59: =IF($B59="","",COUNTA($B$2:$B59)) -> 58 | B59: Li Qingning Ruby | D59: Finexis Advisory | E59: Branch Director | F59: Branch Directors | G59: No | I59: 0 | J59: No | M59: Yes | N59: Not Invited | O59: Not Invited | P59: Not Invited | Q59: Not Invited | R59: Not Invited | S59: https://www.linkedin.com/in/li-qingning-ruby-25616a37a/ | T59: =IF($B59="","",COUNTA($N59:$R59)-COUNTIF($N59:$R59,"Not Invited")) -> 0 | U59: =IF($B59="","",COUNTIF($N59:$R59,"Attended")) -> 0 | V59: =IF($B59="","",_xlfn.TEXTJOIN(", ",TRUE(),IF($N59="Attended",Setup!$D$15,""),IF($O59="Attended",Setup!$D$16,""),IF($P59="Attended",Setup!$D$17,""),IF($Q59="Attended",Setup!$D$18,""),IF($R59="Attended",Setup!$D$19,""))) | W59: =IF(OR($B59="",NOT(ISNUMBER($H59))),"",TODAY()-$H59) | X59: =IF($B59="","",IF($U59>0,"Event attendee",IF($G59="Yes","Met (no event)",IF($T59>0,"Invited only",IF(OR($L59="Yes",$M59="Yes"),"Contacted only","Not yet contacted"))))) -> Contacted only | Y59: =IF($B59="","",COUNTIF(c_Firm,"<"&$D59)+COUNTIFS(c_Firm,$D59,c_Name,"<"&$B59)+COUNTIFS($D$2:$D59,$D59,$B$2:$B59,$B59)) -> 58 | Z59: =IF($B59="","",IF(AND(OR(Contacts!$C$3="(All)",$D59=Contacts!$C$3),OR(Contacts!$E$3="(All)",$G59=Contacts!$E$3),OR(Contacts!$G$3="(All)",ISNUMBER(SEARCH(Contacts!$G$3,$V59))),OR(Contacts!$I$3="(All)",$X59=Contacts!$I$3),OR(Contacts!$K$3="",ISNUMBER(SEARCH(Contacts!$K$3,$B59&" "&$C59&" "&$D59&" "&$S59)))),1,0)) -> 1 | AA59: =IF($Z59=1,COUNTIFS(c_Pass,1,c_Sort,"<="&$Y59),"") -> 58 | AB59: =IF(OR($G59<>"Yes",NOT(ISNUMBER($H59))),"",COUNTIFS(c_Met,"Yes",c_Date,"<"&$H59)+COUNTIFS($G$2:$G59,"Yes",$H$2:$H59,$H59))
A60: =IF($B60="","",COUNTA($B$2:$B60)) -> 59 | B60: Lim Jason | D60: Finexis Advisory | E60: Branch Director | F60: Branch Directors | G60: No | I60: 0 | J60: No | M60: Yes | N60: Not Invited | O60: Not Invited | P60: Not Invited | Q60: Not Invited | R60: Not Invited | S60: Already in CRM | https://www.linkedin.com/in/lim-jason-3ba424181/ | T60: =IF($B60="","",COUNTA($N60:$R60)-COUNTIF($N60:$R60,"Not Invited")) -> 0 | U60: =IF($B60="","",COUNTIF($N60:$R60,"Attended")) -> 0 | V60: =IF($B60="","",_xlfn.TEXTJOIN(", ",TRUE(),IF($N60="Attended",Setup!$D$15,""),IF($O60="Attended",Setup!$D$16,""),IF($P60="Attended",Setup!$D$17,""),IF($Q60="Attended",Setup!$D$18,""),IF($R60="Attended",Setup!$D$19,""))) | W60: =IF(OR($B60="",NOT(ISNUMBER($H60))),"",TODAY()-$H60) | X60: =IF($B60="","",IF($U60>0,"Event attendee",IF($G60="Yes","Met (no event)",IF($T60>0,"Invited only",IF(OR($L60="Yes",$M60="Yes"),"Contacted only","Not yet contacted"))))) -> Contacted only | Y60: =IF($B60="","",COUNTIF(c_Firm,"<"&$D60)+COUNTIFS(c_Firm,$D60,c_Name,"<"&$B60)+COUNTIFS($D$2:$D60,$D60,$B$2:$B60,$B60)) -> 59 | Z60: =IF($B60="","",IF(AND(OR(Contacts!$C$3="(All)",$D60=Contacts!$C$3),OR(Contacts!$E$3="(All)",$G60=Contacts!$E$3),OR(Contacts!$G$3="(All)",ISNUMBER(SEARCH(Contacts!$G$3,$V60))),OR(Contacts!$I$3="(All)",$X60=Contacts!$I$3),OR(Contacts!$K$3="",ISNUMBER(SEARCH(Contacts!$K$3,$B60&" "&$C60&" "&$D60&" "&$S60)))),1,0)) -> 1 | AA60: =IF($Z60=1,COUNTIFS(c_Pass,1,c_Sort,"<="&$Y60),"") -> 59 | AB60: =IF(OR($G60<>"Yes",NOT(ISNUMBER($H60))),"",COUNTIFS(c_Met,"Yes",c_Date,"<"&$H60)+COUNTIFS($G$2:$G60,"Yes",$H$2:$H60,$H60))
A61: =IF($B61="","",COUNTA($B$2:$B61)) -> 60 | B61: Lionel Ling | C61: lionel.ling@finexis.com.sg | D61: Finexis Advisory | E61: Adviser | F61: Meeting List + ILP Data | G61: Yes | H61: 45936 | I61: 1 | J61: No | K61: 4000000 | N61: Declined | O61: No Reply | P61: Not Invited | Q61: Not Invited | R61: Not Invited | T61: =IF($B61="","",COUNTA($N61:$R61)-COUNTIF($N61:$R61,"Not Invited")) -> 2 | U61: =IF($B61="","",COUNTIF($N61:$R61,"Attended")) -> 0 | V61: =IF($B61="","",_xlfn.TEXTJOIN(", ",TRUE(),IF($N61="Attended",Setup!$D$15,""),IF($O61="Attended",Setup!$D$16,""),IF($P61="Attended",Setup!$D$17,""),IF($Q61="Attended",Setup!$D$18,""),IF($R61="Attended",Setup!$D$19,""))) | W61: =IF(OR($B61="",NOT(ISNUMBER($H61))),"",TODAY()-$H61) -> 305 | X61: =IF($B61="","",IF($U61>0,"Event attendee",IF($G61="Yes","Met (no event)",IF($T61>0,"Invited only",IF(OR($L61="Yes",$M61="Yes"),"Contacted only","Not yet contacted"))))) -> Met (no event) | Y61: =IF($B61="","",COUNTIF(c_Firm,"<"&$D61)+COUNTIFS(c_Firm,$D61,c_Name,"<"&$B61)+COUNTIFS($D$2:$D61,$D61,$B$2:$B61,$B61)) -> 60 | Z61: =IF($B61="","",IF(AND(OR(Contacts!$C$3="(All)",$D61=Contacts!$C$3),OR(Contacts!$E$3="(All)",$G61=Contacts!$E$3),OR(Contacts!$G$3="(All)",ISNUMBER(SEARCH(Contacts!$G$3,$V61))),OR(Contacts!$I$3="(All)",$X61=Contacts!$I$3),OR(Contacts!$K$3="",ISNUMBER(SEARCH(Contacts!$K$3,$B61&" "&$C61&" "&$D61&" "&$S61)))),1,0)) -> 1 | AA61: =IF($Z61=1,COUNTIFS(c_Pass,1,c_Sort,"<="&$Y61),"") -> 60 | AB61: =IF(OR($G61<>"Yes",NOT(ISNUMBER($H61))),"",COUNTIFS(c_Met,"Yes",c_Date,"<"&$H61)+COUNTIFS($G$2:$G61,"Yes",$H$2:$H61,$H61)) -> 27
A62: =IF($B62="","",COUNTA($B$2:$B62)) -> 61 | B62: Lomency Ng | C62: lomency.ng@finexis.com.sg | D62: Finexis Advisory | E62: Adviser | F62: Meeting List + ILP Data + Branch Directors | G62: Yes | H62: 45933 | I62: 1 | J62: No | K62: 40000000 | M62: No | N62: Declined | O62: Attended | P62: Not Invited | Q62: Not Invited | R62: Not Invited | S62: Branch: faVe Advisory Practice | T62: =IF($B62="","",COUNTA($N62:$R62)-COUNTIF($N62:$R62,"Not Invited")) -> 2 | U62: =IF($B62="","",COUNTIF($N62:$R62,"Attended")) -> 1 | V62: =IF($B62="","",_xlfn.TEXTJOIN(", ",TRUE(),IF($N62="Attended",Setup!$D$15,""),IF($O62="Attended",Setup!$D$16,""),IF($P62="Attended",Setup!$D$17,""),IF($Q62="Attended",Setup!$D$18,""),IF($R62="Attended",Setup!$D$19,""))) -> May-26 Symposium | W62: =IF(OR($B62="",NOT(ISNUMBER($H62))),"",TODAY()-$H62) -> 308 | X62: =IF($B62="","",IF($U62>0,"Event attendee",IF($G62="Yes","Met (no event)",IF($T62>0,"Invited only",IF(OR($L62="Yes",$M62="Yes"),"Contacted only","Not yet contacted"))))) -> Event attendee | Y62: =IF($B62="","",COUNTIF(c_Firm,"<"&$D62)+COUNTIFS(c_Firm,$D62,c_Name,"<"&$B62)+COUNTIFS($D$2:$D62,$D62,$B$2:$B62,$B62)) -> 61 | Z62: =IF($B62="","",IF(AND(OR(Contacts!$C$3="(All)",$D62=Contacts!$C$3),OR(Contacts!$E$3="(All)",$G62=Contacts!$E$3),OR(Contacts!$G$3="(All)",ISNUMBER(SEARCH(Contacts!$G$3,$V62))),OR(Contacts!$I$3="(All)",$X62=Contacts!$I$3),OR(Contacts!$K$3="",ISNUMBER(SEARCH(Contacts!$K$3,$B62&" "&$C62&" "&$D62&" "&$S62)))),1,0)) -> 1 | AA62: =IF($Z62=1,COUNTIFS(c_Pass,1,c_Sort,"<="&$Y62),"") -> 61 | AB62: =IF(OR($G62<>"Yes",NOT(ISNUMBER($H62))),"",COUNTIFS(c_Met,"Yes",c_Date,"<"&$H62)+COUNTIFS($G$2:$G62,"Yes",$H$2:$H62,$H62)) -> 24
A63: =IF($B63="","",COUNTA($B$2:$B63)) -> 62 | B63: Mingshan Goh | D63: Finexis Advisory | E63: Branch Director | F63: Branch Directors | G63: No | I63: 0 | J63: No | M63: Yes | N63: Not Invited | O63: Not Invited | P63: Not Invited | Q63: Not Invited | R63: Not Invited | S63: https://www.linkedin.com/in/mingshangoh/ | T63: =IF($B63="","",COUNTA($N63:$R63)-COUNTIF($N63:$R63,"Not Invited")) -> 0 | U63: =IF($B63="","",COUNTIF($N63:$R63,"Attended")) -> 0 | V63: =IF($B63="","",_xlfn.TEXTJOIN(", ",TRUE(),IF($N63="Attended",Setup!$D$15,""),IF($O63="Attended",Setup!$D$16,""),IF($P63="Attended",Setup!$D$17,""),IF($Q63="Attended",Setup!$D$18,""),IF($R63="Attended",Setup!$D$19,""))) | W63: =IF(OR($B63="",NOT(ISNUMBER($H63))),"",TODAY()-$H63) | X63: =IF($B63="","",IF($U63>0,"Event attendee",IF($G63="Yes","Met (no event)",IF($T63>0,"Invited only",IF(OR($L63="Yes",$M63="Yes"),"Contacted only","Not yet contacted"))))) -> Contacted only | Y63: =IF($B63="","",COUNTIF(c_Firm,"<"&$D63)+COUNTIFS(c_Firm,$D63,c_Name,"<"&$B63)+COUNTIFS($D$2:$D63,$D63,$B$2:$B63,$B63)) -> 62 | Z63: =IF($B63="","",IF(AND(OR(Contacts!$C$3="(All)",$D63=Contacts!$C$3),OR(Contacts!$E$3="(All)",$G63=Contacts!$E$3),OR(Contacts!$G$3="(All)",ISNUMBER(SEARCH(Contacts!$G$3,$V63))),OR(Contacts!$I$3="(All)",$X63=Contacts!$I$3),OR(Contacts!$K$3="",ISNUMBER(SEARCH(Contacts!$K$3,$B63&" "&$C63&" "&$D63&" "&$S63)))),1,0)) -> 1 | AA63: =IF($Z63=1,COUNTIFS(c_Pass,1,c_Sort,"<="&$Y63),"") -> 62 | AB63: =IF(OR($G63<>"Yes",NOT(ISNUMBER($H63))),"",COUNTIFS(c_Met,"Yes",c_Date,"<"&$H63)+COUNTIFS($G$2:$G63,"Yes",$H$2:$H63,$H63))
A64: =IF($B64="","",COUNTA($B$2:$B64)) -> 63 | B64: Neo Poh Lin Ben | D64: Finexis Advisory | E64: Branch Director | F64: Branch Directors | G64: No | I64: 0 | J64: No | M64: Yes | N64: Not Invited | O64: Not Invited | P64: Not Invited | Q64: Not Invited | R64: Not Invited | S64: Branch: NPLO Advisory Group | https://www.linkedin.com/in/neo-poh-lin-ben-69801b37/ | T64: =IF($B64="","",COUNTA($N64:$R64)-COUNTIF($N64:$R64,"Not Invited")) -> 0 | U64: =IF($B64="","",COUNTIF($N64:$R64,"Attended")) -> 0 | V64: =IF($B64="","",_xlfn.TEXTJOIN(", ",TRUE(),IF($N64="Attended",Setup!$D$15,""),IF($O64="Attended",Setup!$D$16,""),IF($P64="Attended",Setup!$D$17,""),IF($Q64="Attended",Setup!$D$18,""),IF($R64="Attended",Setup!$D$19,""))) | W64: =IF(OR($B64="",NOT(ISNUMBER($H64))),"",TODAY()-$H64) | X64: =IF($B64="","",IF($U64>0,"Event attendee",IF($G64="Yes","Met (no event)",IF($T64>0,"Invited only",IF(OR($L64="Yes",$M64="Yes"),"Contacted only","Not yet contacted"))))) -> Contacted only | Y64: =IF($B64="","",COUNTIF(c_Firm,"<"&$D64)+COUNTIFS(c_Firm,$D64,c_Name,"<"&$B64)+COUNTIFS($D$2:$D64,$D64,$B$2:$B64,$B64)) -> 63 | Z64: =IF($B64="","",IF(AND(OR(Contacts!$C$3="(All)",$D64=Contacts!$C$3),OR(Contacts!$E$3="(All)",$G64=Contacts!$E$3),OR(Contacts!$G$3="(All)",ISNUMBER(SEARCH(Contacts!$G$3,$V64))),OR(Contacts!$I$3="(All)",$X64=Contacts!$I$3),OR(Contacts!$K$3="",ISNUMBER(SEARCH(Contacts!$K$3,$B64&" "&$C64&" "&$D64&" "&$S64)))),1,0)) -> 1 | AA64: =IF($Z64=1,COUNTIFS(c_Pass,1,c_Sort,"<="&$Y64),"") -> 63 | AB64: =IF(OR($G64<>"Yes",NOT(ISNUMBER($H64))),"",COUNTIFS(c_Met,"Yes",c_Date,"<"&$H64)+COUNTIFS($G$2:$G64,"Yes",$H$2:$H64,$H64))
A65: =IF($B65="","",COUNTA($B$2:$B65)) -> 64 | B65: Nur Fitria Rozlan | D65: Finexis Advisory | E65: Branch Director | F65: Branch Directors | G65: No | I65: 0 | J65: No | M65: Yes | N65: Not Invited | O65: Not Invited | P65: Not Invited | Q65: Not Invited | R65: Not Invited | S65: https://www.linkedin.com/in/nurfitriarozlan/ | T65: =IF($B65="","",COUNTA($N65:$R65)-COUNTIF($N65:$R65,"Not Invited")) -> 0 | U65: =IF($B65="","",COUNTIF($N65:$R65,"Attended")) -> 0 | V65: =IF($B65="","",_xlfn.TEXTJOIN(", ",TRUE(),IF($N65="Attended",Setup!$D$15,""),IF($O65="Attended",Setup!$D$16,""),IF($P65="Attended",Setup!$D$17,""),IF($Q65="Attended",Setup!$D$18,""),IF($R65="Attended",Setup!$D$19,""))) | W65: =IF(OR($B65="",NOT(ISNUMBER($H65))),"",TODAY()-$H65) | X65: =IF($B65="","",IF($U65>0,"Event attendee",IF($G65="Yes","Met (no event)",IF($T65>0,"Invited only",IF(OR($L65="Yes",$M65="Yes"),"Contacted only","Not yet contacted"))))) -> Contacted only | Y65: =IF($B65="","",COUNTIF(c_Firm,"<"&$D65)+COUNTIFS(c_Firm,$D65,c_Name,"<"&$B65)+COUNTIFS($D$2:$D65,$D65,$B$2:$B65,$B65)) -> 64 | Z65: =IF($B65="","",IF(AND(OR(Contacts!$C$3="(All)",$D65=Contacts!$C$3),OR(Contacts!$E$3="(All)",$G65=Contacts!$E$3),OR(Contacts!$G$3="(All)",ISNUMBER(SEARCH(Contacts!$G$3,$V65))),OR(Contacts!$I$3="(All)",$X65=Contacts!$I$3),OR(Contacts!$K$3="",ISNUMBER(SEARCH(Contacts!$K$3,$B65&" "&$C65&" "&$D65&" "&$S65)))),1,0)) -> 1 | AA65: =IF($Z65=1,COUNTIFS(c_Pass,1,c_Sort,"<="&$Y65),"") -> 64 | AB65: =IF(OR($G65<>"Yes",NOT(ISNUMBER($H65))),"",COUNTIFS(c_Met,"Yes",c_Date,"<"&$H65)+COUNTIFS($G$2:$G65,"Yes",$H$2:$H65,$H65))
A66: =IF($B66="","",COUNTA($B$2:$B66)) -> 65 | B66: Oliver Mak | D66: Finexis Advisory | E66: Branch Director | F66: Branch Directors | G66: No | I66: 0 | J66: No | M66: Yes | N66: Not Invited | O66: Not Invited | P66: Not Invited | Q66: Not Invited | R66: Not Invited | S66: Already in CRM | https://www.linkedin.com/in/oliver-mak-2b935524/ | T66: =IF($B66="","",COUNTA($N66:$R66)-COUNTIF($N66:$R66,"Not Invited")) -> 0 | U66: =IF($B66="","",COUNTIF($N66:$R66,"Attended")) -> 0 | V66: =IF($B66="","",_xlfn.TEXTJOIN(", ",TRUE(),IF($N66="Attended",Setup!$D$15,""),IF($O66="Attended",Setup!$D$16,""),IF($P66="Attended",Setup!$D$17,""),IF($Q66="Attended",Setup!$D$18,""),IF($R66="Attended",Setup!$D$19,""))) | W66: =IF(OR($B66="",NOT(ISNUMBER($H66))),"",TODAY()-$H66) | X66: =IF($B66="","",IF($U66>0,"Event attendee",IF($G66="Yes","Met (no event)",IF($T66>0,"Invited only",IF(OR($L66="Yes",$M66="Yes"),"Contacted only","Not yet contacted"))))) -> Contacted only | Y66: =IF($B66="","",COUNTIF(c_Firm,"<"&$D66)+COUNTIFS(c_Firm,$D66,c_Name,"<"&$B66)+COUNTIFS($D$2:$D66,$D66,$B$2:$B66,$B66)) -> 65 | Z66: =IF($B66="","",IF(AND(OR(Contacts!$C$3="(All)",$D66=Contacts!$C$3),OR(Contacts!$E$3="(All)",$G66=Contacts!$E$3),OR(Contacts!$G$3="(All)",ISNUMBER(SEARCH(Contacts!$G$3,$V66))),OR(Contacts!$I$3="(All)",$X66=Contacts!$I$3),OR(Contacts!$K$3="",ISNUMBER(SEARCH(Contacts!$K$3,$B66&" "&$C66&" "&$D66&" "&$S66)))),1,0)) -> 1 | AA66: =IF($Z66=1,COUNTIFS(c_Pass,1,c_Sort,"<="&$Y66),"") -> 65 | AB66: =IF(OR($G66<>"Yes",NOT(ISNUMBER($H66))),"",COUNTIFS(c_Met,"Yes",c_Date,"<"&$H66)+COUNTIFS($G$2:$G66,"Yes",$H$2:$H66,$H66))
A67: =IF($B67="","",COUNTA($B$2:$B67)) -> 66 | B67: Perry Lau Wei Han | D67: Finexis Advisory | E67: Branch Director | F67: Branch Directors | G67: No | I67: 0 | J67: No | M67: Yes | N67: Not Invited | O67: Not Invited | P67: Not Invited | Q67: Not Invited | R67: Not Invited | S67: https://www.linkedin.com/in/perry-lau-wei-han-976901186/ | T67: =IF($B67="","",COUNTA($N67:$R67)-COUNTIF($N67:$R67,"Not Invited")) -> 0 | U67: =IF($B67="","",COUNTIF($N67:$R67,"Attended")) -> 0 | V67: =IF($B67="","",_xlfn.TEXTJOIN(", ",TRUE(),IF($N67="Attended",Setup!$D$15,""),IF($O67="Attended",Setup!$D$16,""),IF($P67="Attended",Setup!$D$17,""),IF($Q67="Attended",Setup!$D$18,""),IF($R67="Attended",Setup!$D$19,""))) | W67: =IF(OR($B67="",NOT(ISNUMBER($H67))),"",TODAY()-$H67) | X67: =IF($B67="","",IF($U67>0,"Event attendee",IF($G67="Yes","Met (no event)",IF($T67>0,"Invited only",IF(OR($L67="Yes",$M67="Yes"),"Contacted only","Not yet contacted"))))) -> Contacted only | Y67: =IF($B67="","",COUNTIF(c_Firm,"<"&$D67)+COUNTIFS(c_Firm,$D67,c_Name,"<"&$B67)+COUNTIFS($D$2:$D67,$D67,$B$2:$B67,$B67)) -> 66 | Z67: =IF($B67="","",IF(AND(OR(Contacts!$C$3="(All)",$D67=Contacts!$C$3),OR(Contacts!$E$3="(All)",$G67=Contacts!$E$3),OR(Contacts!$G$3="(All)",ISNUMBER(SEARCH(Contacts!$G$3,$V67))),OR(Contacts!$I$3="(All)",$X67=Contacts!$I$3),OR(Contacts!$K$3="",ISNUMBER(SEARCH(Contacts!$K$3,$B67&" "&$C67&" "&$D67&" "&$S67)))),1,0)) -> 1 | AA67: =IF($Z67=1,COUNTIFS(c_Pass,1,c_Sort,"<="&$Y67),"") -> 66 | AB67: =IF(OR($G67<>"Yes",NOT(ISNUMBER($H67))),"",COUNTIFS(c_Met,"Yes",c_Date,"<"&$H67)+COUNTIFS($G$2:$G67,"Yes",$H$2:$H67,$H67))
A68: =IF($B68="","",COUNTA($B$2:$B68)) -> 67 | B68: Philip Tan | C68: philip.tan@finexis.com.sg | D68: Finexis Advisory | E68: Adviser | F68: Meeting List + ILP Data | G68: Yes | H68: 45933 | I68: 1 | J68: No | K68: 40000000 | N68: Declined | O68: Attended | P68: Not Invited | Q68: Not Invited | R68: Not Invited | T68: =IF($B68="","",COUNTA($N68:$R68)-COUNTIF($N68:$R68,"Not Invited")) -> 2 | U68: =IF($B68="","",COUNTIF($N68:$R68,"Attended")) -> 1 | V68: =IF($B68="","",_xlfn.TEXTJOIN(", ",TRUE(),IF($N68="Attended",Setup!$D$15,""),IF($O68="Attended",Setup!$D$16,""),IF($P68="Attended",Setup!$D$17,""),IF($Q68="Attended",Setup!$D$18,""),IF($R68="Attended",Setup!$D$19,""))) -> May-26 Symposium | W68: =IF(OR($B68="",NOT(ISNUMBER($H68))),"",TODAY()-$H68) -> 308 | X68: =IF($B68="","",IF($U68>0,"Event attendee",IF($G68="Yes","Met (no event)",IF($T68>0,"Invited only",IF(OR($L68="Yes",$M68="Yes"),"Contacted only","Not yet contacted"))))) -> Event attendee | Y68: =IF($B68="","",COUNTIF(c_Firm,"<"&$D68)+COUNTIFS(c_Firm,$D68,c_Name,"<"&$B68)+COUNTIFS($D$2:$D68,$D68,$B$2:$B68,$B68)) -> 67 | Z68: =IF($B68="","",IF(AND(OR(Contacts!$C$3="(All)",$D68=Contacts!$C$3),OR(Contacts!$E$3="(All)",$G68=Contacts!$E$3),OR(Contacts!$G$3="(All)",ISNUMBER(SEARCH(Contacts!$G$3,$V68))),OR(Contacts!$I$3="(All)",$X68=Contacts!$I$3),OR(Contacts!$K$3="",ISNUMBER(SEARCH(Contacts!$K$3,$B68&" "&$C68&" "&$D68&" "&$S68)))),1,0)) -> 1 | AA68: =IF($Z68=1,COUNTIFS(c_Pass,1,c_Sort,"<="&$Y68),"") -> 67 | AB68: =IF(OR($G68<>"Yes",NOT(ISNUMBER($H68))),"",COUNTIFS(c_Met,"Yes",c_Date,"<"&$H68)+COUNTIFS($G$2:$G68,"Yes",$H$2:$H68,$H68)) -> 25
A69: =IF($B69="","",COUNTA($B$2:$B69)) -> 68 | B69: Shimin Chong | D69: Finexis Advisory | E69: Branch Director | F69: Branch Directors | G69: No | I69: 0 | J69: No | M69: Yes | N69: Not Invited | O69: Not Invited | P69: Not Invited | Q69: Not Invited | R69: Not Invited | S69: https://www.linkedin.com/in/chongshimin/ | T69: =IF($B69="","",COUNTA($N69:$R69)-COUNTIF($N69:$R69,"Not Invited")) -> 0 | U69: =IF($B69="","",COUNTIF($N69:$R69,"Attended")) -> 0 | V69: =IF($B69="","",_xlfn.TEXTJOIN(", ",TRUE(),IF($N69="Attended",Setup!$D$15,""),IF($O69="Attended",Setup!$D$16,""),IF($P69="Attended",Setup!$D$17,""),IF($Q69="Attended",Setup!$D$18,""),IF($R69="Attended",Setup!$D$19,""))) | W69: =IF(OR($B69="",NOT(ISNUMBER($H69))),"",TODAY()-$H69) | X69: =IF($B69="","",IF($U69>0,"Event attendee",IF($G69="Yes","Met (no event)",IF($T69>0,"Invited only",IF(OR($L69="Yes",$M69="Yes"),"Contacted only","Not yet contacted"))))) -> Contacted only | Y69: =IF($B69="","",COUNTIF(c_Firm,"<"&$D69)+COUNTIFS(c_Firm,$D69,c_Name,"<"&$B69)+COUNTIFS($D$2:$D69,$D69,$B$2:$B69,$B69)) -> 68 | Z69: =IF($B69="","",IF(AND(OR(Contacts!$C$3="(All)",$D69=Contacts!$C$3),OR(Contacts!$E$3="(All)",$G69=Contacts!$E$3),OR(Contacts!$G$3="(All)",ISNUMBER(SEARCH(Contacts!$G$3,$V69))),OR(Contacts!$I$3="(All)",$X69=Contacts!$I$3),OR(Contacts!$K$3="",ISNUMBER(SEARCH(Contacts!$K$3,$B69&" "&$C69&" "&$D69&" "&$S69)))),1,0)) -> 1 | AA69: =IF($Z69=1,COUNTIFS(c_Pass,1,c_Sort,"<="&$Y69),"") -> 68 | AB69: =IF(OR($G69<>"Yes",NOT(ISNUMBER($H69))),"",COUNTIFS(c_Met,"Yes",c_Date,"<"&$H69)+COUNTIFS($G$2:$G69,"Yes",$H$2:$H69,$H69))
A70: =IF($B70="","",COUNTA($B$2:$B70)) -> 69 | B70: Shinni Hong | D70: Finexis Advisory | E70: Branch Director | F70: Branch Directors | G70: No | I70: 0 | J70: No | M70: Yes | N70: Not Invited | O70: Not Invited | P70: Not Invited | Q70: Not Invited | R70: Not Invited | S70: https://www.linkedin.com/in/shinni-hong-a9b0b2166/ | T70: =IF($B70="","",COUNTA($N70:$R70)-COUNTIF($N70:$R70,"Not Invited")) -> 0 | U70: =IF($B70="","",COUNTIF($N70:$R70,"Attended")) -> 0 | V70: =IF($B70="","",_xlfn.TEXTJOIN(", ",TRUE(),IF($N70="Attended",Setup!$D$15,""),IF($O70="Attended",Setup!$D$16,""),IF($P70="Attended",Setup!$D$17,""),IF($Q70="Attended",Setup!$D$18,""),IF($R70="Attended",Setup!$D$19,""))) | W70: =IF(OR($B70="",NOT(ISNUMBER($H70))),"",TODAY()-$H70) | X70: =IF($B70="","",IF($U70>0,"Event attendee",IF($G70="Yes","Met (no event)",IF($T70>0,"Invited only",IF(OR($L70="Yes",$M70="Yes"),"Contacted only","Not yet contacted"))))) -> Contacted only | Y70: =IF($B70="","",COUNTIF(c_Firm,"<"&$D70)+COUNTIFS(c_Firm,$D70,c_Name,"<"&$B70)+COUNTIFS($D$2:$D70,$D70,$B$2:$B70,$B70)) -> 69 | Z70: =IF($B70="","",IF(AND(OR(Contacts!$C$3="(All)",$D70=Contacts!$C$3),OR(Contacts!$E$3="(All)",$G70=Contacts!$E$3),OR(Contacts!$G$3="(All)",ISNUMBER(SEARCH(Contacts!$G$3,$V70))),OR(Contacts!$I$3="(All)",$X70=Contacts!$I$3),OR(Contacts!$K$3="",ISNUMBER(SEARCH(Contacts!$K$3,$B70&" "&$C70&" "&$D70&" "&$S70)))),1,0)) -> 1 | AA70: =IF($Z70=1,COUNTIFS(c_Pass,1,c_Sort,"<="&$Y70),"") -> 69 | AB70: =IF(OR($G70<>"Yes",NOT(ISNUMBER($H70))),"",COUNTIFS(c_Met,"Yes",c_Date,"<"&$H70)+COUNTIFS($G$2:$G70,"Yes",$H$2:$H70,$H70))
A71: =IF($B71="","",COUNTA($B$2:$B71)) -> 70 | B71: Siew Yin Tan | D71: Finexis Advisory | E71: Branch Director | F71: Branch Directors | G71: No | I71: 0 | J71: No | M71: Yes | N71: Not Invited | O71: Not Invited | P71: Not Invited | Q71: Not Invited | R71: Not Invited | S71: https://www.linkedin.com/in/siew-yin-tan-aepp%C2%AE-cfp%C2%AE-tot-18859373/ | T71: =IF($B71="","",COUNTA($N71:$R71)-COUNTIF($N71:$R71,"Not Invited")) -> 0 | U71: =IF($B71="","",COUNTIF($N71:$R71,"Attended")) -> 0 | V71: =IF($B71="","",_xlfn.TEXTJOIN(", ",TRUE(),IF($N71="Attended",Setup!$D$15,""),IF($O71="Attended",Setup!$D$16,""),IF($P71="Attended",Setup!$D$17,""),IF($Q71="Attended",Setup!$D$18,""),IF($R71="Attended",Setup!$D$19,""))) | W71: =IF(OR($B71="",NOT(ISNUMBER($H71))),"",TODAY()-$H71) | X71: =IF($B71="","",IF($U71>0,"Event attendee",IF($G71="Yes","Met (no event)",IF($T71>0,"Invited only",IF(OR($L71="Yes",$M71="Yes"),"Contacted only","Not yet contacted"))))) -> Contacted only | Y71: =IF($B71="","",COUNTIF(c_Firm,"<"&$D71)+COUNTIFS(c_Firm,$D71,c_Name,"<"&$B71)+COUNTIFS($D$2:$D71,$D71,$B$2:$B71,$B71)) -> 70 | Z71: =IF($B71="","",IF(AND(OR(Contacts!$C$3="(All)",$D71=Contacts!$C$3),OR(Contacts!$E$3="(All)",$G71=Contacts!$E$3),OR(Contacts!$G$3="(All)",ISNUMBER(SEARCH(Contacts!$G$3,$V71))),OR(Contacts!$I$3="(All)",$X71=Contacts!$I$3),OR(Contacts!$K$3="",ISNUMBER(SEARCH(Contacts!$K$3,$B71&" "&$C71&" "&$D71&" "&$S71)))),1,0)) -> 1 | AA71: =IF($Z71=1,COUNTIFS(c_Pass,1,c_Sort,"<="&$Y71),"") -> 70 | AB71: =IF(OR($G71<>"Yes",NOT(ISNUMBER($H71))),"",COUNTIFS(c_Met,"Yes",c_Date,"<"&$H71)+COUNTIFS($G$2:$G71,"Yes",$H$2:$H71,$H71))
A72: =IF($B72="","",COUNTA($B$2:$B72)) -> 71 | B72: Stacey Lwin | D72: Finexis Advisory | E72: Branch Director | F72: Branch Directors | G72: No | I72: 0 | J72: No | M72: Yes | N72: Not Invited | O72: Not Invited | P72: Not Invited | Q72: Not Invited | R72: Not Invited | S72: https://www.linkedin.com/in/staceylwin/ | T72: =IF($B72="","",COUNTA($N72:$R72)-COUNTIF($N72:$R72,"Not Invited")) -> 0 | U72: =IF($B72="","",COUNTIF($N72:$R72,"Attended")) -> 0 | V72: =IF($B72="","",_xlfn.TEXTJOIN(", ",TRUE(),IF($N72="Attended",Setup!$D$15,""),IF($O72="Attended",Setup!$D$16,""),IF($P72="Attended",Setup!$D$17,""),IF($Q72="Attended",Setup!$D$18,""),IF($R72="Attended",Setup!$D$19,""))) | W72: =IF(OR($B72="",NOT(ISNUMBER($H72))),"",TODAY()-$H72) | X72: =IF($B72="","",IF($U72>0,"Event attendee",IF($G72="Yes","Met (no event)",IF($T72>0,"Invited only",IF(OR($L72="Yes",$M72="Yes"),"Contacted only","Not yet contacted"))))) -> Contacted only | Y72: =IF($B72="","",COUNTIF(c_Firm,"<"&$D72)+COUNTIFS(c_Firm,$D72,c_Name,"<"&$B72)+COUNTIFS($D$2:$D72,$D72,$B$2:$B72,$B72)) -> 71 | Z72: =IF($B72="","",IF(AND(OR(Contacts!$C$3="(All)",$D72=Contacts!$C$3),OR(Contacts!$E$3="(All)",$G72=Contacts!$E$3),OR(Contacts!$G$3="(All)",ISNUMBER(SEARCH(Contacts!$G$3,$V72))),OR(Contacts!$I$3="(All)",$X72=Contacts!$I$3),OR(Contacts!$K$3="",ISNUMBER(SEARCH(Contacts!$K$3,$B72&" "&$C72&" "&$D72&" "&$S72)))),1,0)) -> 1 | AA72: =IF($Z72=1,COUNTIFS(c_Pass,1,c_Sort,"<="&$Y72),"") -> 71 | AB72: =IF(OR($G72<>"Yes",NOT(ISNUMBER($H72))),"",COUNTIFS(c_Met,"Yes",c_Date,"<"&$H72)+COUNTIFS($G$2:$G72,"Yes",$H$2:$H72,$H72))
A73: =IF($B73="","",COUNTA($B$2:$B73)) -> 72 | B73: Tan Kwang Sheng | D73: Finexis Advisory | E73: Branch Director | F73: Branch Directors | G73: No | I73: 0 | J73: No | M73: Yes | N73: Not Invited | O73: Not Invited | P73: Not Invited | Q73: Not Invited | R73: Not Invited | S73: https://www.linkedin.com/in/tan-kwang-sheng-4a8923172/ | T73: =IF($B73="","",COUNTA($N73:$R73)-COUNTIF($N73:$R73,"Not Invited")) -> 0 | U73: =IF($B73="","",COUNTIF($N73:$R73,"Attended")) -> 0 | V73: =IF($B73="","",_xlfn.TEXTJOIN(", ",TRUE(),IF($N73="Attended",Setup!$D$15,""),IF($O73="Attended",Setup!$D$16,""),IF($P73="Attended",Setup!$D$17,""),IF($Q73="Attended",Setup!$D$18,""),IF($R73="Attended",Setup!$D$19,""))) | W73: =IF(OR($B73="",NOT(ISNUMBER($H73))),"",TODAY()-$H73) | X73: =IF($B73="","",IF($U73>0,"Event attendee",IF($G73="Yes","Met (no event)",IF($T73>0,"Invited only",IF(OR($L73="Yes",$M73="Yes"),"Contacted only","Not yet contacted"))))) -> Contacted only | Y73: =IF($B73="","",COUNTIF(c_Firm,"<"&$D73)+COUNTIFS(c_Firm,$D73,c_Name,"<"&$B73)+COUNTIFS($D$2:$D73,$D73,$B$2:$B73,$B73)) -> 72 | Z73: =IF($B73="","",IF(AND(OR(Contacts!$C$3="(All)",$D73=Contacts!$C$3),OR(Contacts!$E$3="(All)",$G73=Contacts!$E$3),OR(Contacts!$G$3="(All)",ISNUMBER(SEARCH(Contacts!$G$3,$V73))),OR(Contacts!$I$3="(All)",$X73=Contacts!$I$3),OR(Contacts!$K$3="",ISNUMBER(SEARCH(Contacts!$K$3,$B73&" "&$C73&" "&$D73&" "&$S73)))),1,0)) -> 1 | AA73: =IF($Z73=1,COUNTIFS(c_Pass,1,c_Sort,"<="&$Y73),"") -> 72 | AB73: =IF(OR($G73<>"Yes",NOT(ISNUMBER($H73))),"",COUNTIFS(c_Met,"Yes",c_Date,"<"&$H73)+COUNTIFS($G$2:$G73,"Yes",$H$2:$H73,$H73))
A74: =IF($B74="","",COUNTA($B$2:$B74)) -> 73 | B74: Tang Charles | D74: Finexis Advisory | E74: Branch Director | F74: Branch Directors | G74: No | I74: 0 | J74: No | M74: Yes | N74: Not Invited | O74: Not Invited | P74: Not Invited | Q74: Not Invited | R74: Not Invited | S74: https://www.linkedin.com/in/tang-charles-2b311651/ | T74: =IF($B74="","",COUNTA($N74:$R74)-COUNTIF($N74:$R74,"Not Invited")) -> 0 | U74: =IF($B74="","",COUNTIF($N74:$R74,"Attended")) -> 0 | V74: =IF($B74="","",_xlfn.TEXTJOIN(", ",TRUE(),IF($N74="Attended",Setup!$D$15,""),IF($O74="Attended",Setup!$D$16,""),IF($P74="Attended",Setup!$D$17,""),IF($Q74="Attended",Setup!$D$18,""),IF($R74="Attended",Setup!$D$19,""))) | W74: =IF(OR($B74="",NOT(ISNUMBER($H74))),"",TODAY()-$H74) | X74: =IF($B74="","",IF($U74>0,"Event attendee",IF($G74="Yes","Met (no event)",IF($T74>0,"Invited only",IF(OR($L74="Yes",$M74="Yes"),"Contacted only","Not yet contacted"))))) -> Contacted only | Y74: =IF($B74="","",COUNTIF(c_Firm,"<"&$D74)+COUNTIFS(c_Firm,$D74,c_Name,"<"&$B74)+COUNTIFS($D$2:$D74,$D74,$B$2:$B74,$B74)) -> 73 | Z74: =IF($B74="","",IF(AND(OR(Contacts!$C$3="(All)",$D74=Contacts!$C$3),OR(Contacts!$E$3="(All)",$G74=Contacts!$E$3),OR(Contacts!$G$3="(All)",ISNUMBER(SEARCH(Contacts!$G$3,$V74))),OR(Contacts!$I$3="(All)",$X74=Contacts!$I$3),OR(Contacts!$K$3="",ISNUMBER(SEARCH(Contacts!$K$3,$B74&" "&$C74&" "&$D74&" "&$S74)))),1,0)) -> 1 | AA74: =IF($Z74=1,COUNTIFS(c_Pass,1,c_Sort,"<="&$Y74),"") -> 73 | AB74: =IF(OR($G74<>"Yes",NOT(ISNUMBER($H74))),"",COUNTIFS(c_Met,"Yes",c_Date,"<"&$H74)+COUNTIFS($G$2:$G74,"Yes",$H$2:$H74,$H74))
A75: =IF($B75="","",COUNTA($B$2:$B75)) -> 74 | B75: Theresa Groyon | D75: Finexis Advisory | E75: Branch Director | F75: Branch Directors | G75: No | I75: 0 | J75: No | M75: Yes | N75: Not Invited | O75: Not Invited | P75: Not Invited | Q75: Not Invited | R75: Not Invited | T75: =IF($B75="","",COUNTA($N75:$R75)-COUNTIF($N75:$R75,"Not Invited")) -> 0 | U75: =IF($B75="","",COUNTIF($N75:$R75,"Attended")) -> 0 | V75: =IF($B75="","",_xlfn.TEXTJOIN(", ",TRUE(),IF($N75="Attended",Setup!$D$15,""),IF($O75="Attended",Setup!$D$16,""),IF($P75="Attended",Setup!$D$17,""),IF($Q75="Attended",Setup!$D$18,""),IF($R75="Attended",Setup!$D$19,""))) | W75: =IF(OR($B75="",NOT(ISNUMBER($H75))),"",TODAY()-$H75) | X75: =IF($B75="","",IF($U75>0,"Event attendee",IF($G75="Yes","Met (no event)",IF($T75>0,"Invited only",IF(OR($L75="Yes",$M75="Yes"),"Contacted only","Not yet contacted"))))) -> Contacted only | Y75: =IF($B75="","",COUNTIF(c_Firm,"<"&$D75)+COUNTIFS(c_Firm,$D75,c_Name,"<"&$B75)+COUNTIFS($D$2:$D75,$D75,$B$2:$B75,$B75)) -> 74 | Z75: =IF($B75="","",IF(AND(OR(Contacts!$C$3="(All)",$D75=Contacts!$C$3),OR(Contacts!$E$3="(All)",$G75=Contacts!$E$3),OR(Contacts!$G$3="(All)",ISNUMBER(SEARCH(Contacts!$G$3,$V75))),OR(Contacts!$I$3="(All)",$X75=Contacts!$I$3),OR(Contacts!$K$3="",ISNUMBER(SEARCH(Contacts!$K$3,$B75&" "&$C75&" "&$D75&" "&$S75)))),1,0)) -> 1 | AA75: =IF($Z75=1,COUNTIFS(c_Pass,1,c_Sort,"<="&$Y75),"") -> 74 | AB75: =IF(OR($G75<>"Yes",NOT(ISNUMBER($H75))),"",COUNTIFS(c_Met,"Yes",c_Date,"<"&$H75)+COUNTIFS($G$2:$G75,"Yes",$H$2:$H75,$H75))
A76: =IF($B76="","",COUNTA($B$2:$B76)) -> 75 | B76: Yeo Chinwei | C76: yeo.chinwei@finexis.com.sg | D76: Finexis Advisory | E76: Adviser | F76: Meeting List + Branch Directors | G76: No | I76: 0 | J76: No | M76: No | N76: Not Invited | O76: Attended | P76: Not Invited | Q76: Not Invited | R76: Not Invited | T76: =IF($B76="","",COUNTA($N76:$R76)-COUNTIF($N76:$R76,"Not Invited")) -> 1 | U76: =IF($B76="","",COUNTIF($N76:$R76,"Attended")) -> 1 | V76: =IF($B76="","",_xlfn.TEXTJOIN(", ",TRUE(),IF($N76="Attended",Setup!$D$15,""),IF($O76="Attended",Setup!$D$16,""),IF($P76="Attended",Setup!$D$17,""),IF($Q76="Attended",Setup!$D$18,""),IF($R76="Attended",Setup!$D$19,""))) -> May-26 Symposium | W76: =IF(OR($B76="",NOT(ISNUMBER($H76))),"",TODAY()-$H76) | X76: =IF($B76="","",IF($U76>0,"Event attendee",IF($G76="Yes","Met (no event)",IF($T76>0,"Invited only",IF(OR($L76="Yes",$M76="Yes"),"Contacted only","Not yet contacted"))))) -> Event attendee | Y76: =IF($B76="","",COUNTIF(c_Firm,"<"&$D76)+COUNTIFS(c_Firm,$D76,c_Name,"<"&$B76)+COUNTIFS($D$2:$D76,$D76,$B$2:$B76,$B76)) -> 75 | Z76: =IF($B76="","",IF(AND(OR(Contacts!$C$3="(All)",$D76=Contacts!$C$3),OR(Contacts!$E$3="(All)",$G76=Contacts!$E$3),OR(Contacts!$G$3="(All)",ISNUMBER(SEARCH(Contacts!$G$3,$V76))),OR(Contacts!$I$3="(All)",$X76=Contacts!$I$3),OR(Contacts!$K$3="",ISNUMBER(SEARCH(Contacts!$K$3,$B76&" "&$C76&" "&$D76&" "&$S76)))),1,0)) -> 1 | AA76: =IF($Z76=1,COUNTIFS(c_Pass,1,c_Sort,"<="&$Y76),"") -> 75 | AB76: =IF(OR($G76<>"Yes",NOT(ISNUMBER($H76))),"",COUNTIFS(c_Met,"Yes",c_Date,"<"&$H76)+COUNTIFS($G$2:$G76,"Yes",$H$2:$H76,$H76))
A77: =IF($B77="","",COUNTA($B$2:$B77)) -> 76 | B77: Zach Zhang | D77: Finexis Advisory | E77: Branch Director | F77: Branch Directors | G77: No | I77: 0 | J77: No | M77: Yes | N77: Not Invited | O77: Not Invited | P77: Not Invited | Q77: Not Invited | R77: Not Invited | S77: https://www.linkedin.com/in/zach-zhang-a313b0139/ | T77: =IF($B77="","",COUNTA($N77:$R77)-COUNTIF($N77:$R77,"Not Invited")) -> 0 | U77: =IF($B77="","",COUNTIF($N77:$R77,"Attended")) -> 0 | V77: =IF($B77="","",_xlfn.TEXTJOIN(", ",TRUE(),IF($N77="Attended",Setup!$D$15,""),IF($O77="Attended",Setup!$D$16,""),IF($P77="Attended",Setup!$D$17,""),IF($Q77="Attended",Setup!$D$18,""),IF($R77="Attended",Setup!$D$19,""))) | W77: =IF(OR($B77="",NOT(ISNUMBER($H77))),"",TODAY()-$H77) | X77: =IF($B77="","",IF($U77>0,"Event attendee",IF($G77="Yes","Met (no event)",IF($T77>0,"Invited only",IF(OR($L77="Yes",$M77="Yes"),"Contacted only","Not yet contacted"))))) -> Contacted only | Y77: =IF($B77="","",COUNTIF(c_Firm,"<"&$D77)+COUNTIFS(c_Firm,$D77,c_Name,"<"&$B77)+COUNTIFS($D$2:$D77,$D77,$B$2:$B77,$B77)) -> 76 | Z77: =IF($B77="","",IF(AND(OR(Contacts!$C$3="(All)",$D77=Contacts!$C$3),OR(Contacts!$E$3="(All)",$G77=Contacts!$E$3),OR(Contacts!$G$3="(All)",ISNUMBER(SEARCH(Contacts!$G$3,$V77))),OR(Contacts!$I$3="(All)",$X77=Contacts!$I$3),OR(Contacts!$K$3="",ISNUMBER(SEARCH(Contacts!$K$3,$B77&" "&$C77&" "&$D77&" "&$S77)))),1,0)) -> 1 | AA77: =IF($Z77=1,COUNTIFS(c_Pass,1,c_Sort,"<="&$Y77),"") -> 76 | AB77: =IF(OR($G77<>"Yes",NOT(ISNUMBER($H77))),"",COUNTIFS(c_Met,"Yes",c_Date,"<"&$H77)+COUNTIFS($G$2:$G77,"Yes",$H$2:$H77,$H77))
A78: =IF($B78="","",COUNTA($B$2:$B78)) -> 77 | B78: Martha Yu | D78: Franklin Templeton | E78: Adviser | F78: ILP Data | G78: No | I78: 0 | J78: No | N78: Not Invited | O78: Not Invited | P78: Not Invited | Q78: Not Invited | R78: Not Invited | S78: ILP: Unrelated | T78: =IF($B78="","",COUNTA($N78:$R78)-COUNTIF($N78:$R78,"Not Invited")) -> 0 | U78: =IF($B78="","",COUNTIF($N78:$R78,"Attended")) -> 0 | V78: =IF($B78="","",_xlfn.TEXTJOIN(", ",TRUE(),IF($N78="Attended",Setup!$D$15,""),IF($O78="Attended",Setup!$D$16,""),IF($P78="Attended",Setup!$D$17,""),IF($Q78="Attended",Setup!$D$18,""),IF($R78="Attended",Setup!$D$19,""))) | W78: =IF(OR($B78="",NOT(ISNUMBER($H78))),"",TODAY()-$H78) | X78: =IF($B78="","",IF($U78>0,"Event attendee",IF($G78="Yes","Met (no event)",IF($T78>0,"Invited only",IF(OR($L78="Yes",$M78="Yes"),"Contacted only","Not yet contacted"))))) -> Not yet contacted | Y78: =IF($B78="","",COUNTIF(c_Firm,"<"&$D78)+COUNTIFS(c_Firm,$D78,c_Name,"<"&$B78)+COUNTIFS($D$2:$D78,$D78,$B$2:$B78,$B78)) -> 77 | Z78: =IF($B78="","",IF(AND(OR(Contacts!$C$3="(All)",$D78=Contacts!$C$3),OR(Contacts!$E$3="(All)",$G78=Contacts!$E$3),OR(Contacts!$G$3="(All)",ISNUMBER(SEARCH(Contacts!$G$3,$V78))),OR(Contacts!$I$3="(All)",$X78=Contacts!$I$3),OR(Contacts!$K$3="",ISNUMBER(SEARCH(Contacts!$K$3,$B78&" "&$C78&" "&$D78&" "&$S78)))),1,0)) -> 1 | AA78: =IF($Z78=1,COUNTIFS(c_Pass,1,c_Sort,"<="&$Y78),"") -> 77 | AB78: =IF(OR($G78<>"Yes",NOT(ISNUMBER($H78))),"",COUNTIFS(c_Met,"Yes",c_Date,"<"&$H78)+COUNTIFS($G$2:$G78,"Yes",$H$2:$H78,$H78))
A79: =IF($B79="","",COUNTA($B$2:$B79)) -> 78 | B79: Daniel Sng Boon | C79: danielsngbt@greateasternlife.com | D79: Great Eastern Life | E79: Adviser | F79: Meeting List + ILP Data | G79: Yes | H79: 45989 | I79: 1 | J79: No | N79: Attended | O79: Declined | P79: Not Invited | Q79: Not Invited | R79: Not Invited | S79: May-26: not available; ILP: Product | T79: =IF($B79="","",COUNTA($N79:$R79)-COUNTIF($N79:$R79,"Not Invited")) -> 2 | U79: =IF($B79="","",COUNTIF($N79:$R79,"Attended")) -> 1 | V79: =IF($B79="","",_xlfn.TEXTJOIN(", ",TRUE(),IF($N79="Attended",Setup!$D$15,""),IF($O79="Attended",Setup!$D$16,""),IF($P79="Attended",Setup!$D$17,""),IF($Q79="Attended",Setup!$D$18,""),IF($R79="Attended",Setup!$D$19,""))) -> Oct-25 Symposium | W79: =IF(OR($B79="",NOT(ISNUMBER($H79))),"",TODAY()-$H79) -> 252 | X79: =IF($B79="","",IF($U79>0,"Event attendee",IF($G79="Yes","Met (no event)",IF($T79>0,"Invited only",IF(OR($L79="Yes",$M79="Yes"),"Contacted only","Not yet contacted"))))) -> Event attendee | Y79: =IF($B79="","",COUNTIF(c_Firm,"<"&$D79)+COUNTIFS(c_Firm,$D79,c_Name,"<"&$B79)+COUNTIFS($D$2:$D79,$D79,$B$2:$B79,$B79)) -> 78 | Z79: =IF($B79="","",IF(AND(OR(Contacts!$C$3="(All)",$D79=Contacts!$C$3),OR(Contacts!$E$3="(All)",$G79=Contacts!$E$3),OR(Contacts!$G$3="(All)",ISNUMBER(SEARCH(Contacts!$G$3,$V79))),OR(Contacts!$I$3="(All)",$X79=Contacts!$I$3),OR(Contacts!$K$3="",ISNUMBER(SEARCH(Contacts!$K$3,$B79&" "&$C79&" "&$D79&" "&$S79)))),1,0)) -> 1 | AA79: =IF($Z79=1,COUNTIFS(c_Pass,1,c_Sort,"<="&$Y79),"") -> 78 | AB79: =IF(OR($G79<>"Yes",NOT(ISNUMBER($H79))),"",COUNTIFS(c_Met,"Yes",c_Date,"<"&$H79)+COUNTIFS($G$2:$G79,"Yes",$H$2:$H79,$H79)) -> 35
A80: =IF($B80="","",COUNTA($B$2:$B80)) -> 79 | B80: Bruce Tan | C80: brucetan@gyc.com.sg | D80: GYC Financial Advisory | E80: Adviser | F80: Meeting List + ILP Data | G80: Yes | H80: 45412 | I80: 1 | J80: TBC | N80: Declined | O80: Not Invited | P80: Invited | Q80: Not Invited | R80: Not Invited | S80: ILP: Investment | T80: =IF($B80="","",COUNTA($N80:$R80)-COUNTIF($N80:$R80,"Not Invited")) -> 2 | U80: =IF($B80="","",COUNTIF($N80:$R80,"Attended")) -> 0 | V80: =IF($B80="","",_xlfn.TEXTJOIN(", ",TRUE(),IF($N80="Attended",Setup!$D$15,""),IF($O80="Attended",Setup!$D$16,""),IF($P80="Attended",Setup!$D$17,""),IF($Q80="Attended",Setup!$D$18,""),IF($R80="Attended",Setup!$D$19,""))) | W80: =IF(OR($B80="",NOT(ISNUMBER($H80))),"",TODAY()-$H80) -> 829 | X80: =IF($B80="","",IF($U80>0,"Event attendee",IF($G80="Yes","Met (no event)",IF($T80>0,"Invited only",IF(OR($L80="Yes",$M80="Yes"),"Contacted only","Not yet contacted"))))) -> Met (no event) | Y80: =IF($B80="","",COUNTIF(c_Firm,"<"&$D80)+COUNTIFS(c_Firm,$D80,c_Name,"<"&$B80)+COUNTIFS($D$2:$D80,$D80,$B$2:$B80,$B80)) -> 79 | Z80: =IF($B80="","",IF(AND(OR(Contacts!$C$3="(All)",$D80=Contacts!$C$3),OR(Contacts!$E$3="(All)",$G80=Contacts!$E$3),OR(Contacts!$G$3="(All)",ISNUMBER(SEARCH(Contacts!$G$3,$V80))),OR(Contacts!$I$3="(All)",$X80=Contacts!$I$3),OR(Contacts!$K$3="",ISNUMBER(SEARCH(Contacts!$K$3,$B80&" "&$C80&" "&$D80&" "&$S80)))),1,0)) -> 1 | AA80: =IF($Z80=1,COUNTIFS(c_Pass,1,c_Sort,"<="&$Y80),"") -> 79 | AB80: =IF(OR($G80<>"Yes",NOT(ISNUMBER($H80))),"",COUNTIFS(c_Met,"Yes",c_Date,"<"&$H80)+COUNTIFS($G$2:$G80,"Yes",$H$2:$H80,$H80)) -> 1
A81: =IF($B81="","",COUNTA($B$2:$B81)) -> 80 | B81: Carl Chay | C81: carlchay@gyc.com.sg | D81: GYC Financial Advisory | E81: Adviser | F81: Meeting List + ILP Data | G81: Yes | H81: 45412 | I81: 1 | J81: TBC | N81: Declined | O81: Not Invited | P81: Invited | Q81: Not Invited | R81: Not Invited | S81: ILP: Investment | T81: =IF($B81="","",COUNTA($N81:$R81)-COUNTIF($N81:$R81,"Not Invited")) -> 2 | U81: =IF($B81="","",COUNTIF($N81:$R81,"Attended")) -> 0 | V81: =IF($B81="","",_xlfn.TEXTJOIN(", ",TRUE(),IF($N81="Attended",Setup!$D$15,""),IF($O81="Attended",Setup!$D$16,""),IF($P81="Attended",Setup!$D$17,""),IF($Q81="Attended",Setup!$D$18,""),IF($R81="Attended",Setup!$D$19,""))) | W81: =IF(OR($B81="",NOT(ISNUMBER($H81))),"",TODAY()-$H81) -> 829 | X81: =IF($B81="","",IF($U81>0,"Event attendee",IF($G81="Yes","Met (no event)",IF($T81>0,"Invited only",IF(OR($L81="Yes",$M81="Yes"),"Contacted only","Not yet contacted"))))) -> Met (no event) | Y81: =IF($B81="","",COUNTIF(c_Firm,"<"&$D81)+COUNTIFS(c_Firm,$D81,c_Name,"<"&$B81)+COUNTIFS($D$2:$D81,$D81,$B$2:$B81,$B81)) -> 80 | Z81: =IF($B81="","",IF(AND(OR(Contacts!$C$3="(All)",$D81=Contacts!$C$3),OR(Contacts!$E$3="(All)",$G81=Contacts!$E$3),OR(Contacts!$G$3="(All)",ISNUMBER(SEARCH(Contacts!$G$3,$V81))),OR(Contacts!$I$3="(All)",$X81=Contacts!$I$3),OR(Contacts!$K$3="",ISNUMBER(SEARCH(Contacts!$K$3,$B81&" "&$C81&" "&$D81&" "&$S81)))),1,0)) -> 1 | AA81: =IF($Z81=1,COUNTIFS(c_Pass,1,c_Sort,"<="&$Y81),"") -> 80 | AB81: =IF(OR($G81<>"Yes",NOT(ISNUMBER($H81))),"",COUNTIFS(c_Met,"Yes",c_Date,"<"&$H81)+COUNTIFS($G$2:$G81,"Yes",$H$2:$H81,$H81)) -> 2
A82: =IF($B82="","",COUNTA($B$2:$B82)) -> 81 | B82: Poh Choon | C82: pohchoon.lye@h2o-am.com | D82: H2O AM (internal) | E82: Adviser | F82: Meeting List | G82: No | I82: 0 | J82: No | N82: Not Invited | O82: Attended | P82: Not Invited | Q82: Not Invited | R82: Not Invited | T82: =IF($B82="","",COUNTA($N82:$R82)-COUNTIF($N82:$R82,"Not Invited")) -> 1 | U82: =IF($B82="","",COUNTIF($N82:$R82,"Attended")) -> 1 | V82: =IF($B82="","",_xlfn.TEXTJOIN(", ",TRUE(),IF($N82="Attended",Setup!$D$15,""),IF($O82="Attended",Setup!$D$16,""),IF($P82="Attended",Setup!$D$17,""),IF($Q82="Attended",Setup!$D$18,""),IF($R82="Attended",Setup!$D$19,""))) -> May-26 Symposium | W82: =IF(OR($B82="",NOT(ISNUMBER($H82))),"",TODAY()-$H82) | X82: =IF($B82="","",IF($U82>0,"Event attendee",IF($G82="Yes","Met (no event)",IF($T82>0,"Invited only",IF(OR($L82="Yes",$M82="Yes"),"Contacted only","Not yet contacted"))))) -> Event attendee | Y82: =IF($B82="","",COUNTIF(c_Firm,"<"&$D82)+COUNTIFS(c_Firm,$D82,c_Name,"<"&$B82)+COUNTIFS($D$2:$D82,$D82,$B$2:$B82,$B82)) -> 81 | Z82: =IF($B82="","",IF(AND(OR(Contacts!$C$3="(All)",$D82=Contacts!$C$3),OR(Contacts!$E$3="(All)",$G82=Contacts!$E$3),OR(Contacts!$G$3="(All)",ISNUMBER(SEARCH(Contacts!$G$3,$V82))),OR(Contacts!$I$3="(All)",$X82=Contacts!$I$3),OR(Contacts!$K$3="",ISNUMBER(SEARCH(Contacts!$K$3,$B82&" "&$C82&" "&$D82&" "&$S82)))),1,0)) -> 1 | AA82: =IF($Z82=1,COUNTIFS(c_Pass,1,c_Sort,"<="&$Y82),"") -> 81 | AB82: =IF(OR($G82<>"Yes",NOT(ISNUMBER($H82))),"",COUNTIFS(c_Met,"Yes",c_Date,"<"&$H82)+COUNTIFS($G$2:$G82,"Yes",$H$2:$H82,$H82))
A83: =IF($B83="","",COUNTA($B$2:$B83)) -> 82 | B83: Preston Hong | C83: preston.hong@hsbc.com.sg | D83: HSBC Life | E83: Adviser | F83: Meeting List + ILP Data | G83: Yes | H83: 46062 | I83: 1 | J83: No | K83: 5000000 | N83: No Reply | O83: Declined | P83: Not Invited | Q83: Not Invited | R83: Not Invited | S83: May-26: not available | T83: =IF($B83="","",COUNTA($N83:$R83)-COUNTIF($N83:$R83,"Not Invited")) -> 2 | U83: =IF($B83="","",COUNTIF($N83:$R83,"Attended")) -> 0 | V83: =IF($B83="","",_xlfn.TEXTJOIN(", ",TRUE(),IF($N83="Attended",Setup!$D$15,""),IF($O83="Attended",Setup!$D$16,""),IF($P83="Attended",Setup!$D$17,""),IF($Q83="Attended",Setup!$D$18,""),IF($R83="Attended",Setup!$D$19,""))) | W83: =IF(OR($B83="",NOT(ISNUMBER($H83))),"",TODAY()-$H83) -> 179 | X83: =IF($B83="","",IF($U83>0,"Event attendee",IF($G83="Yes","Met (no event)",IF($T83>0,"Invited only",IF(OR($L83="Yes",$M83="Yes"),"Contacted only","Not yet contacted"))))) -> Met (no event) | Y83: =IF($B83="","",COUNTIF(c_Firm,"<"&$D83)+COUNTIFS(c_Firm,$D83,c_Name,"<"&$B83)+COUNTIFS($D$2:$D83,$D83,$B$2:$B83,$B83)) -> 82 | Z83: =IF($B83="","",IF(AND(OR(Contacts!$C$3="(All)",$D83=Contacts!$C$3),OR(Contacts!$E$3="(All)",$G83=Contacts!$E$3),OR(Contacts!$G$3="(All)",ISNUMBER(SEARCH(Contacts!$G$3,$V83))),OR(Contacts!$I$3="(All)",$X83=Contacts!$I$3),OR(Contacts!$K$3="",ISNUMBER(SEARCH(Contacts!$K$3,$B83&" "&$C83&" "&$D83&" "&$S83)))),1,0)) -> 1 | AA83: =IF($Z83=1,COUNTIFS(c_Pass,1,c_Sort,"<="&$Y83),"") -> 82 | AB83: =IF(OR($G83<>"Yes",NOT(ISNUMBER($H83))),"",COUNTIFS(c_Met,"Yes",c_Date,"<"&$H83)+COUNTIFS($G$2:$G83,"Yes",$H$2:$H83,$H83)) -> 45
A84: =IF($B84="","",COUNTA($B$2:$B84)) -> 83 | B84: Aimee Tan | C84: aimee.tan@ifastgm.com | D84: iFast | E84: Adviser | F84: Meeting List + ILP Data | G84: No | I84: 0 | J84: No | K84: 18000000 | N84: Attended | O84: Declined | P84: Not Invited | Q84: Not Invited | R84: Not Invited | S84: May-26: not available | T84: =IF($B84="","",COUNTA($N84:$R84)-COUNTIF($N84:$R84,"Not Invited")) -> 2 | U84: =IF($B84="","",COUNTIF($N84:$R84,"Attended")) -> 1 | V84: =IF($B84="","",_xlfn.TEXTJOIN(", ",TRUE(),IF($N84="Attended",Setup!$D$15,""),IF($O84="Attended",Setup!$D$16,""),IF($P84="Attended",Setup!$D$17,""),IF($Q84="Attended",Setup!$D$18,""),IF($R84="Attended",Setup!$D$19,""))) -> Oct-25 Symposium | W84: =IF(OR($B84="",NOT(ISNUMBER($H84))),"",TODAY()-$H84) | X84: =IF($B84="","",IF($U84>0,"Event attendee",IF($G84="Yes","Met (no event)",IF($T84>0,"Invited only",IF(OR($L84="Yes",$M84="Yes"),"Contacted only","Not yet contacted"))))) -> Event attendee | Y84: =IF($B84="","",COUNTIF(c_Firm,"<"&$D84)+COUNTIFS(c_Firm,$D84,c_Name,"<"&$B84)+COUNTIFS($D$2:$D84,$D84,$B$2:$B84,$B84)) -> 83 | Z84: =IF($B84="","",IF(AND(OR(Contacts!$C$3="(All)",$D84=Contacts!$C$3),OR(Contacts!$E$3="(All)",$G84=Contacts!$E$3),OR(Contacts!$G$3="(All)",ISNUMBER(SEARCH(Contacts!$G$3,$V84))),OR(Contacts!$I$3="(All)",$X84=Contacts!$I$3),OR(Contacts!$K$3="",ISNUMBER(SEARCH(Contacts!$K$3,$B84&" "&$C84&" "&$D84&" "&$S84)))),1,0)) -> 1 | AA84: =IF($Z84=1,COUNTIFS(c_Pass,1,c_Sort,"<="&$Y84),"") -> 83 | AB84: =IF(OR($G84<>"Yes",NOT(ISNUMBER($H84))),"",COUNTIFS(c_Met,"Yes",c_Date,"<"&$H84)+COUNTIFS($G$2:$G84,"Yes",$H$2:$H84,$H84))
A85: =IF($B85="","",COUNTA($B$2:$B85)) -> 84 | B85: Amir Hamzah | D85: iFast | E85: Branch Director | F85: Branch Directors | G85: No | I85: 0 | J85: No | N85: Not Invited | O85: Not Invited | P85: Not Invited | Q85: Not Invited | R85: Not Invited | T85: =IF($B85="","",COUNTA($N85:$R85)-COUNTIF($N85:$R85,"Not Invited")) -> 0 | U85: =IF($B85="","",COUNTIF($N85:$R85,"Attended")) -> 0 | V85: =IF($B85="","",_xlfn.TEXTJOIN(", ",TRUE(),IF($N85="Attended",Setup!$D$15,""),IF($O85="Attended",Setup!$D$16,""),IF($P85="Attended",Setup!$D$17,""),IF($Q85="Attended",Setup!$D$18,""),IF($R85="Attended",Setup!$D$19,""))) | W85: =IF(OR($B85="",NOT(ISNUMBER($H85))),"",TODAY()-$H85) | X85: =IF($B85="","",IF($U85>0,"Event attendee",IF($G85="Yes","Met (no event)",IF($T85>0,"Invited only",IF(OR($L85="Yes",$M85="Yes"),"Contacted only","Not yet contacted"))))) -> Not yet contacted | Y85: =IF($B85="","",COUNTIF(c_Firm,"<"&$D85)+COUNTIFS(c_Firm,$D85,c_Name,"<"&$B85)+COUNTIFS($D$2:$D85,$D85,$B$2:$B85,$B85)) -> 84 | Z85: =IF($B85="","",IF(AND(OR(Contacts!$C$3="(All)",$D85=Contacts!$C$3),OR(Contacts!$E$3="(All)",$G85=Contacts!$E$3),OR(Contacts!$G$3="(All)",ISNUMBER(SEARCH(Contacts!$G$3,$V85))),OR(Contacts!$I$3="(All)",$X85=Contacts!$I$3),OR(Contacts!$K$3="",ISNUMBER(SEARCH(Contacts!$K$3,$B85&" "&$C85&" "&$D85&" "&$S85)))),1,0)) -> 1 | AA85: =IF($Z85=1,COUNTIFS(c_Pass,1,c_Sort,"<="&$Y85),"") -> 84 | AB85: =IF(OR($G85<>"Yes",NOT(ISNUMBER($H85))),"",COUNTIFS(c_Met,"Yes",c_Date,"<"&$H85)+COUNTIFS($G$2:$G85,"Yes",$H$2:$H85,$H85))
A86: =IF($B86="","",COUNTA($B$2:$B86)) -> 85 | B86: Bernard Chan | D86: iFast | E86: Branch Director | F86: Branch Directors | G86: No | I86: 0 | J86: No | N86: Not Invited | O86: Not Invited | P86: Not Invited | Q86: Not Invited | R86: Not Invited | T86: =IF($B86="","",COUNTA($N86:$R86)-COUNTIF($N86:$R86,"Not Invited")) -> 0 | U86: =IF($B86="","",COUNTIF($N86:$R86,"Attended")) -> 0 | V86: =IF($B86="","",_xlfn.TEXTJOIN(", ",TRUE(),IF($N86="Attended",Setup!$D$15,""),IF($O86="Attended",Setup!$D$16,""),IF($P86="Attended",Setup!$D$17,""),IF($Q86="Attended",Setup!$D$18,""),IF($R86="Attended",Setup!$D$19,""))) | W86: =IF(OR($B86="",NOT(ISNUMBER($H86))),"",TODAY()-$H86) | X86: =IF($B86="","",IF($U86>0,"Event attendee",IF($G86="Yes","Met (no event)",IF($T86>0,"Invited only",IF(OR($L86="Yes",$M86="Yes"),"Contacted only","Not yet contacted"))))) -> Not yet contacted | Y86: =IF($B86="","",COUNTIF(c_Firm,"<"&$D86)+COUNTIFS(c_Firm,$D86,c_Name,"<"&$B86)+COUNTIFS($D$2:$D86,$D86,$B$2:$B86,$B86)) -> 85 | Z86: =IF($B86="","",IF(AND(OR(Contacts!$C$3="(All)",$D86=Contacts!$C$3),OR(Contacts!$E$3="(All)",$G86=Contacts!$E$3),OR(Contacts!$G$3="(All)",ISNUMBER(SEARCH(Contacts!$G$3,$V86))),OR(Contacts!$I$3="(All)",$X86=Contacts!$I$3),OR(Contacts!$K$3="",ISNUMBER(SEARCH(Contacts!$K$3,$B86&" "&$C86&" "&$D86&" "&$S86)))),1,0)) -> 1 | AA86: =IF($Z86=1,COUNTIFS(c_Pass,1,c_Sort,"<="&$Y86),"") -> 85 | AB86: =IF(OR($G86<>"Yes",NOT(ISNUMBER($H86))),"",COUNTIFS(c_Met,"Yes",c_Date,"<"&$H86)+COUNTIFS($G$2:$G86,"Yes",$H$2:$H86,$H86))
A87: =IF($B87="","",COUNTA($B$2:$B87)) -> 86 | B87: Brenda Lee Sheue Yee | D87: iFast | E87: Consultant | F87: Branch Directors | G87: No | I87: 0 | J87: No | N87: Not Invited | O87: Not Invited | P87: Not Invited | Q87: Not Invited | R87: Not Invited | S87: Reports to Bernard Chan | T87: =IF($B87="","",COUNTA($N87:$R87)-COUNTIF($N87:$R87,"Not Invited")) -> 0 | U87: =IF($B87="","",COUNTIF($N87:$R87,"Attended")) -> 0 | V87: =IF($B87="","",_xlfn.TEXTJOIN(", ",TRUE(),IF($N87="Attended",Setup!$D$15,""),IF($O87="Attended",Setup!$D$16,""),IF($P87="Attended",Setup!$D$17,""),IF($Q87="Attended",Setup!$D$18,""),IF($R87="Attended",Setup!$D$19,""))) | W87: =IF(OR($B87="",NOT(ISNUMBER($H87))),"",TODAY()-$H87) | X87: =IF($B87="","",IF($U87>0,"Event attendee",IF($G87="Yes","Met (no event)",IF($T87>0,"Invited only",IF(OR($L87="Yes",$M87="Yes"),"Contacted only","Not yet contacted"))))) -> Not yet contacted | Y87: =IF($B87="","",COUNTIF(c_Firm,"<"&$D87)+COUNTIFS(c_Firm,$D87,c_Name,"<"&$B87)+COUNTIFS($D$2:$D87,$D87,$B$2:$B87,$B87)) -> 86 | Z87: =IF($B87="","",IF(AND(OR(Contacts!$C$3="(All)",$D87=Contacts!$C$3),OR(Contacts!$E$3="(All)",$G87=Contacts!$E$3),OR(Contacts!$G$3="(All)",ISNUMBER(SEARCH(Contacts!$G$3,$V87))),OR(Contacts!$I$3="(All)",$X87=Contacts!$I$3),OR(Contacts!$K$3="",ISNUMBER(SEARCH(Contacts!$K$3,$B87&" "&$C87&" "&$D87&" "&$S87)))),1,0)) -> 1 | AA87: =IF($Z87=1,COUNTIFS(c_Pass,1,c_Sort,"<="&$Y87),"") -> 86 | AB87: =IF(OR($G87<>"Yes",NOT(ISNUMBER($H87))),"",COUNTIFS(c_Met,"Yes",c_Date,"<"&$H87)+COUNTIFS($G$2:$G87,"Yes",$H$2:$H87,$H87))
A88: =IF($B88="","",COUNTA($B$2:$B88)) -> 87 | B88: Brian Koo Chew Sze | D88: iFast | E88: Branch Director | F88: Branch Directors | G88: No | I88: 0 | J88: No | N88: Not Invited | O88: Not Invited | P88: Not Invited | Q88: Not Invited | R88: Not Invited | T88: =IF($B88="","",COUNTA($N88:$R88)-COUNTIF($N88:$R88,"Not Invited")) -> 0 | U88: =IF($B88="","",COUNTIF($N88:$R88,"Attended")) -> 0 | V88: =IF($B88="","",_xlfn.TEXTJOIN(", ",TRUE(),IF($N88="Attended",Setup!$D$15,""),IF($O88="Attended",Setup!$D$16,""),IF($P88="Attended",Setup!$D$17,""),IF($Q88="Attended",Setup!$D$18,""),IF($R88="Attended",Setup!$D$19,""))) | W88: =IF(OR($B88="",NOT(ISNUMBER($H88))),"",TODAY()-$H88) | X88: =IF($B88="","",IF($U88>0,"Event attendee",IF($G88="Yes","Met (no event)",IF($T88>0,"Invited only",IF(OR($L88="Yes",$M88="Yes"),"Contacted only","Not yet contacted"))))) -> Not yet contacted | Y88: =IF($B88="","",COUNTIF(c_Firm,"<"&$D88)+COUNTIFS(c_Firm,$D88,c_Name,"<"&$B88)+COUNTIFS($D$2:$D88,$D88,$B$2:$B88,$B88)) -> 87 | Z88: =IF($B88="","",IF(AND(OR(Contacts!$C$3="(All)",$D88=Contacts!$C$3),OR(Contacts!$E$3="(All)",$G88=Contacts!$E$3),OR(Contacts!$G$3="(All)",ISNUMBER(SEARCH(Contacts!$G$3,$V88))),OR(Contacts!$I$3="(All)",$X88=Contacts!$I$3),OR(Contacts!$K$3="",ISNUMBER(SEARCH(Contacts!$K$3,$B88&" "&$C88&" "&$D88&" "&$S88)))),1,0)) -> 1 | AA88: =IF($Z88=1,COUNTIFS(c_Pass,1,c_Sort,"<="&$Y88),"") -> 87 | AB88: =IF(OR($G88<>"Yes",NOT(ISNUMBER($H88))),"",COUNTIFS(c_Met,"Yes",c_Date,"<"&$H88)+COUNTIFS($G$2:$G88,"Yes",$H$2:$H88,$H88))
A89: =IF($B89="","",COUNTA($B$2:$B89)) -> 88 | B89: Derek Ho Wee Teck | D89: iFast | E89: Consultant | F89: Branch Directors | G89: No | I89: 0 | J89: No | N89: Not Invited | O89: Not Invited | P89: Not Invited | Q89: Not Invited | R89: Not Invited | S89: Reports to Bernard Chan | T89: =IF($B89="","",COUNTA($N89:$R89)-COUNTIF($N89:$R89,"Not Invited")) -> 0 | U89: =IF($B89="","",COUNTIF($N89:$R89,"Attended")) -> 0 | V89: =IF($B89="","",_xlfn.TEXTJOIN(", ",TRUE(),IF($N89="Attended",Setup!$D$15,""),IF($O89="Attended",Setup!$D$16,""),IF($P89="Attended",Setup!$D$17,""),IF($Q89="Attended",Setup!$D$18,""),IF($R89="Attended",Setup!$D$19,""))) | W89: =IF(OR($B89="",NOT(ISNUMBER($H89))),"",TODAY()-$H89) | X89: =IF($B89="","",IF($U89>0,"Event attendee",IF($G89="Yes","Met (no event)",IF($T89>0,"Invited only",IF(OR($L89="Yes",$M89="Yes"),"Contacted only","Not yet contacted"))))) -> Not yet contacted | Y89: =IF($B89="","",COUNTIF(c_Firm,"<"&$D89)+COUNTIFS(c_Firm,$D89,c_Name,"<"&$B89)+COUNTIFS($D$2:$D89,$D89,$B$2:$B89,$B89)) -> 88 | Z89: =IF($B89="","",IF(AND(OR(Contacts!$C$3="(All)",$D89=Contacts!$C$3),OR(Contacts!$E$3="(All)",$G89=Contacts!$E$3),OR(Contacts!$G$3="(All)",ISNUMBER(SEARCH(Contacts!$G$3,$V89))),OR(Contacts!$I$3="(All)",$X89=Contacts!$I$3),OR(Contacts!$K$3="",ISNUMBER(SEARCH(Contacts!$K$3,$B89&" "&$C89&" "&$D89&" "&$S89)))),1,0)) -> 1 | AA89: =IF($Z89=1,COUNTIFS(c_Pass,1,c_Sort,"<="&$Y89),"") -> 88 | AB89: =IF(OR($G89<>"Yes",NOT(ISNUMBER($H89))),"",COUNTIFS(c_Met,"Yes",c_Date,"<"&$H89)+COUNTIFS($G$2:$G89,"Yes",$H$2:$H89,$H89))
A90: =IF($B90="","",COUNTA($B$2:$B90)) -> 89 | B90: Diana Tan | C90: diana.tan@ifastgm.com | D90: iFast | E90: Adviser | F90: Meeting List + Branch Directors | G90: No | I90: 0 | J90: No | N90: Not Invited | O90: Attended | P90: Not Invited | Q90: Not Invited | R90: Not Invited | T90: =IF($B90="","",COUNTA($N90:$R90)-COUNTIF($N90:$R90,"Not Invited")) -> 1 | U90: =IF($B90="","",COUNTIF($N90:$R90,"Attended")) -> 1 | V90: =IF($B90="","",_xlfn.TEXTJOIN(", ",TRUE(),IF($N90="Attended",Setup!$D$15,""),IF($O90="Attended",Setup!$D$16,""),IF($P90="Attended",Setup!$D$17,""),IF($Q90="Attended",Setup!$D$18,""),IF($R90="Attended",Setup!$D$19,""))) -> May-26 Symposium | W90: =IF(OR($B90="",NOT(ISNUMBER($H90))),"",TODAY()-$H90) | X90: =IF($B90="","",IF($U90>0,"Event attendee",IF($G90="Yes","Met (no event)",IF($T90>0,"Invited only",IF(OR($L90="Yes",$M90="Yes"),"Contacted only","Not yet contacted"))))) -> Event attendee | Y90: =IF($B90="","",COUNTIF(c_Firm,"<"&$D90)+COUNTIFS(c_Firm,$D90,c_Name,"<"&$B90)+COUNTIFS($D$2:$D90,$D90,$B$2:$B90,$B90)) -> 89 | Z90: =IF($B90="","",IF(AND(OR(Contacts!$C$3="(All)",$D90=Contacts!$C$3),OR(Contacts!$E$3="(All)",$G90=Contacts!$E$3),OR(Contacts!$G$3="(All)",ISNUMBER(SEARCH(Contacts!$G$3,$V90))),OR(Contacts!$I$3="(All)",$X90=Contacts!$I$3),OR(Contacts!$K$3="",ISNUMBER(SEARCH(Contacts!$K$3,$B90&" "&$C90&" "&$D90&" "&$S90)))),1,0)) -> 1 | AA90: =IF($Z90=1,COUNTIFS(c_Pass,1,c_Sort,"<="&$Y90),"") -> 89 | AB90: =IF(OR($G90<>"Yes",NOT(ISNUMBER($H90))),"",COUNTIFS(c_Met,"Yes",c_Date,"<"&$H90)+COUNTIFS($G$2:$G90,"Yes",$H$2:$H90,$H90))
A91: =IF($B91="","",COUNTA($B$2:$B91)) -> 90 | B91: Elise Tan Ee Fei | D91: iFast | E91: Consultant | F91: Branch Directors | G91: No | I91: 0 | J91: No | N91: Not Invited | O91: Not Invited | P91: Not Invited | Q91: Not Invited | R91: Not Invited | S91: Reports to Bernard Chan | T91: =IF($B91="","",COUNTA($N91:$R91)-COUNTIF($N91:$R91,"Not Invited")) -> 0 | U91: =IF($B91="","",COUNTIF($N91:$R91,"Attended")) -> 0 | V91: =IF($B91="","",_xlfn.TEXTJOIN(", ",TRUE(),IF($N91="Attended",Setup!$D$15,""),IF($O91="Attended",Setup!$D$16,""),IF($P91="Attended",Setup!$D$17,""),IF($Q91="Attended",Setup!$D$18,""),IF($R91="Attended",Setup!$D$19,""))) | W91: =IF(OR($B91="",NOT(ISNUMBER($H91))),"",TODAY()-$H91) | X91: =IF($B91="","",IF($U91>0,"Event attendee",IF($G91="Yes","Met (no event)",IF($T91>0,"Invited only",IF(OR($L91="Yes",$M91="Yes"),"Contacted only","Not yet contacted"))))) -> Not yet contacted | Y91: =IF($B91="","",COUNTIF(c_Firm,"<"&$D91)+COUNTIFS(c_Firm,$D91,c_Name,"<"&$B91)+COUNTIFS($D$2:$D91,$D91,$B$2:$B91,$B91)) -> 90 | Z91: =IF($B91="","",IF(AND(OR(Contacts!$C$3="(All)",$D91=Contacts!$C$3),OR(Contacts!$E$3="(All)",$G91=Contacts!$E$3),OR(Contacts!$G$3="(All)",ISNUMBER(SEARCH(Contacts!$G$3,$V91))),OR(Contacts!$I$3="(All)",$X91=Contacts!$I$3),OR(Contacts!$K$3="",ISNUMBER(SEARCH(Contacts!$K$3,$B91&" "&$C91&" "&$D91&" "&$S91)))),1,0)) -> 1 | AA91: =IF($Z91=1,COUNTIFS(c_Pass,1,c_Sort,"<="&$Y91),"") -> 90 | AB91: =IF(OR($G91<>"Yes",NOT(ISNUMBER($H91))),"",COUNTIFS(c_Met,"Yes",c_Date,"<"&$H91)+COUNTIFS($G$2:$G91,"Yes",$H$2:$H91,$H91))
A92: =IF($B92="","",COUNTA($B$2:$B92)) -> 91 | B92: Francis Khew Guan Jie | D92: iFast | E92: Consultant | F92: Branch Directors | G92: No | I92: 0 | J92: No | N92: Not Invited | O92: Not Invited | P92: Not Invited | Q92: Not Invited | R92: Not Invited | S92: Reports to Bernard Chan | T92: =IF($B92="","",COUNTA($N92:$R92)-COUNTIF($N92:$R92,"Not Invited")) -> 0 | U92: =IF($B92="","",COUNTIF($N92:$R92,"Attended")) -> 0 | V92: =IF($B92="","",_xlfn.TEXTJOIN(", ",TRUE(),IF($N92="Attended",Setup!$D$15,""),IF($O92="Attended",Setup!$D$16,""),IF($P92="Attended",Setup!$D$17,""),IF($Q92="Attended",Setup!$D$18,""),IF($R92="Attended",Setup!$D$19,""))) | W92: =IF(OR($B92="",NOT(ISNUMBER($H92))),"",TODAY()-$H92) | X92: =IF($B92="","",IF($U92>0,"Event attendee",IF($G92="Yes","Met (no event)",IF($T92>0,"Invited only",IF(OR($L92="Yes",$M92="Yes"),"Contacted only","Not yet contacted"))))) -> Not yet contacted | Y92: =IF($B92="","",COUNTIF(c_Firm,"<"&$D92)+COUNTIFS(c_Firm,$D92,c_Name,"<"&$B92)+COUNTIFS($D$2:$D92,$D92,$B$2:$B92,$B92)) -> 91 | Z92: =IF($B92="","",IF(AND(OR(Contacts!$C$3="(All)",$D92=Contacts!$C$3),OR(Contacts!$E$3="(All)",$G92=Contacts!$E$3),OR(Contacts!$G$3="(All)",ISNUMBER(SEARCH(Contacts!$G$3,$V92))),OR(Contacts!$I$3="(All)",$X92=Contacts!$I$3),OR(Contacts!$K$3="",ISNUMBER(SEARCH(Contacts!$K$3,$B92&" "&$C92&" "&$D92&" "&$S92)))),1,0)) -> 1 | AA92: =IF($Z92=1,COUNTIFS(c_Pass,1,c_Sort,"<="&$Y92),"") -> 91 | AB92: =IF(OR($G92<>"Yes",NOT(ISNUMBER($H92))),"",COUNTIFS(c_Met,"Yes",c_Date,"<"&$H92)+COUNTIFS($G$2:$G92,"Yes",$H$2:$H92,$H92))
A93: =IF($B93="","",COUNTA($B$2:$B93)) -> 92 | B93: Giau Kim Low | C93: giaukim.low@ifastgm.com | D93: iFast | E93: Adviser | F93: Meeting List + ILP Data | G93: Yes | H93: 45985 | I93: 1 | J93: Yes | K93: 70000000 | N93: Attended | O93: Declined | P93: Not Invited | Q93: Not Invited | R93: Not Invited | S93: May-26: not available | T93: =IF($B93="","",COUNTA($N93:$R93)-COUNTIF($N93:$R93,"Not Invited")) -> 2 | U93: =IF($B93="","",COUNTIF($N93:$R93,"Attended")) -> 1 | V93: =IF($B93="","",_xlfn.TEXTJOIN(", ",TRUE(),IF($N93="Attended",Setup!$D$15,""),IF($O93="Attended",Setup!$D$16,""),IF($P93="Attended",Setup!$D$17,""),IF($Q93="Attended",Setup!$D$18,""),IF($R93="Attended",Setup!$D$19,""))) -> Oct-25 Symposium | W93: =IF(OR($B93="",NOT(ISNUMBER($H93))),"",TODAY()-$H93) -> 256 | X93: =IF($B93="","",IF($U93>0,"Event attendee",IF($G93="Yes","Met (no event)",IF($T93>0,"Invited only",IF(OR($L93="Yes",$M93="Yes"),"Contacted only","Not yet contacted"))))) -> Event attendee | Y93: =IF($B93="","",COUNTIF(c_Firm,"<"&$D93)+COUNTIFS(c_Firm,$D93,c_Name,"<"&$B93)+COUNTIFS($D$2:$D93,$D93,$B$2:$B93,$B93)) -> 92 | Z93: =IF($B93="","",IF(AND(OR(Contacts!$C$3="(All)",$D93=Contacts!$C$3),OR(Contacts!$E$3="(All)",$G93=Contacts!$E$3),OR(Contacts!$G$3="(All)",ISNUMBER(SEARCH(Contacts!$G$3,$V93))),OR(Contacts!$I$3="(All)",$X93=Contacts!$I$3),OR(Contacts!$K$3="",ISNUMBER(SEARCH(Contacts!$K$3,$B93&" "&$C93&" "&$D93&" "&$S93)))),1,0)) -> 1 | AA93: =IF($Z93=1,COUNTIFS(c_Pass,1,c_Sort,"<="&$Y93),"") -> 92 | AB93: =IF(OR($G93<>"Yes",NOT(ISNUMBER($H93))),"",COUNTIFS(c_Met,"Yes",c_Date,"<"&$H93)+COUNTIFS($G$2:$G93,"Yes",$H$2:$H93,$H93)) -> 32
A94: =IF($B94="","",COUNTA($B$2:$B94)) -> 93 | B94: Joe Lin Xiaohan | D94: iFast | E94: Consultant | F94: Branch Directors | G94: No | I94: 0 | J94: No | N94: Not Invited | O94: Not Invited | P94: Not Invited | Q94: Not Invited | R94: Not Invited | S94: Reports to Bernard Chan | T94: =IF($B94="","",COUNTA($N94:$R94)-COUNTIF($N94:$R94,"Not Invited")) -> 0 | U94: =IF($B94="","",COUNTIF($N94:$R94,"Attended")) -> 0 | V94: =IF($B94="","",_xlfn.TEXTJOIN(", ",TRUE(),IF($N94="Attended",Setup!$D$15,""),IF($O94="Attended",Setup!$D$16,""),IF($P94="Attended",Setup!$D$17,""),IF($Q94="Attended",Setup!$D$18,""),IF($R94="Attended",Setup!$D$19,""))) | W94: =IF(OR($B94="",NOT(ISNUMBER($H94))),"",TODAY()-$H94) | X94: =IF($B94="","",IF($U94>0,"Event attendee",IF($G94="Yes","Met (no event)",IF($T94>0,"Invited only",IF(OR($L94="Yes",$M94="Yes"),"Contacted only","Not yet contacted"))))) -> Not yet contacted | Y94: =IF($B94="","",COUNTIF(c_Firm,"<"&$D94)+COUNTIFS(c_Firm,$D94,c_Name,"<"&$B94)+COUNTIFS($D$2:$D94,$D94,$B$2:$B94,$B94)) -> 93 | Z94: =IF($B94="","",IF(AND(OR(Contacts!$C$3="(All)",$D94=Contacts!$C$3),OR(Contacts!$E$3="(All)",$G94=Contacts!$E$3),OR(Contacts!$G$3="(All)",ISNUMBER(SEARCH(Contacts!$G$3,$V94))),OR(Contacts!$I$3="(All)",$X94=Contacts!$I$3),OR(Contacts!$K$3="",ISNUMBER(SEARCH(Contacts!$K$3,$B94&" "&$C94&" "&$D94&" "&$S94)))),1,0)) -> 1 | AA94: =IF($Z94=1,COUNTIFS(c_Pass,1,c_Sort,"<="&$Y94),"") -> 93 | AB94: =IF(OR($G94<>"Yes",NOT(ISNUMBER($H94))),"",COUNTIFS(c_Met,"Yes",c_Date,"<"&$H94)+COUNTIFS($G$2:$G94,"Yes",$H$2:$H94,$H94))
A95: =IF($B95="","",COUNTA($B$2:$B95)) -> 94 | B95: Joel Yong Sheng Jun | D95: iFast | E95: Consultant | F95: Branch Directors | G95: No | I95: 0 | J95: No | N95: Not Invited | O95: Not Invited | P95: Not Invited | Q95: Not Invited | R95: Not Invited | S95: Reports to Bernard Chan | T95: =IF($B95="","",COUNTA($N95:$R95)-COUNTIF($N95:$R95,"Not Invited")) -> 0 | U95: =IF($B95="","",COUNTIF($N95:$R95,"Attended")) -> 0 | V95: =IF($B95="","",_xlfn.TEXTJOIN(", ",TRUE(),IF($N95="Attended",Setup!$D$15,""),IF($O95="Attended",Setup!$D$16,""),IF($P95="Attended",Setup!$D$17,""),IF($Q95="Attended",Setup!$D$18,""),IF($R95="Attended",Setup!$D$19,""))) | W95: =IF(OR($B95="",NOT(ISNUMBER($H95))),"",TODAY()-$H95) | X95: =IF($B95="","",IF($U95>0,"Event attendee",IF($G95="Yes","Met (no event)",IF($T95>0,"Invited only",IF(OR($L95="Yes",$M95="Yes"),"Contacted only","Not yet contacted"))))) -> Not yet contacted | Y95: =IF($B95="","",COUNTIF(c_Firm,"<"&$D95)+COUNTIFS(c_Firm,$D95,c_Name,"<"&$B95)+COUNTIFS($D$2:$D95,$D95,$B$2:$B95,$B95)) -> 94 | Z95: =IF($B95="","",IF(AND(OR(Contacts!$C$3="(All)",$D95=Contacts!$C$3),OR(Contacts!$E$3="(All)",$G95=Contacts!$E$3),OR(Contacts!$G$3="(All)",ISNUMBER(SEARCH(Contacts!$G$3,$V95))),OR(Contacts!$I$3="(All)",$X95=Contacts!$I$3),OR(Contacts!$K$3="",ISNUMBER(SEARCH(Contacts!$K$3,$B95&" "&$C95&" "&$D95&" "&$S95)))),1,0)) -> 1 | AA95: =IF($Z95=1,COUNTIFS(c_Pass,1,c_Sort,"<="&$Y95),"") -> 94 | AB95: =IF(OR($G95<>"Yes",NOT(ISNUMBER($H95))),"",COUNTIFS(c_Met,"Yes",c_Date,"<"&$H95)+COUNTIFS($G$2:$G95,"Yes",$H$2:$H95,$H95))
A96: =IF($B96="","",COUNTA($B$2:$B96)) -> 95 | B96: Jon Lim Wei Jie | D96: iFast | E96: Branch Director | F96: Branch Directors | G96: No | I96: 0 | J96: No | N96: Not Invited | O96: Not Invited | P96: Not Invited | Q96: Not Invited | R96: Not Invited | T96: =IF($B96="","",COUNTA($N96:$R96)-COUNTIF($N96:$R96,"Not Invited")) -> 0 | U96: =IF($B96="","",COUNTIF($N96:$R96,"Attended")) -> 0 | V96: =IF($B96="","",_xlfn.TEXTJOIN(", ",TRUE(),IF($N96="Attended",Setup!$D$15,""),IF($O96="Attended",Setup!$D$16,""),IF($P96="Attended",Setup!$D$17,""),IF($Q96="Attended",Setup!$D$18,""),IF($R96="Attended",Setup!$D$19,""))) | W96: =IF(OR($B96="",NOT(ISNUMBER($H96))),"",TODAY()-$H96) | X96: =IF($B96="","",IF($U96>0,"Event attendee",IF($G96="Yes","Met (no event)",IF($T96>0,"Invited only",IF(OR($L96="Yes",$M96="Yes"),"Contacted only","Not yet contacted"))))) -> Not yet contacted | Y96: =IF($B96="","",COUNTIF(c_Firm,"<"&$D96)+COUNTIFS(c_Firm,$D96,c_Name,"<"&$B96)+COUNTIFS($D$2:$D96,$D96,$B$2:$B96,$B96)) -> 95 | Z96: =IF($B96="","",IF(AND(OR(Contacts!$C$3="(All)",$D96=Contacts!$C$3),OR(Contacts!$E$3="(All)",$G96=Contacts!$E$3),OR(Contacts!$G$3="(All)",ISNUMBER(SEARCH(Contacts!$G$3,$V96))),OR(Contacts!$I$3="(All)",$X96=Contacts!$I$3),OR(Contacts!$K$3="",ISNUMBER(SEARCH(Contacts!$K$3,$B96&" "&$C96&" "&$D96&" "&$S96)))),1,0)) -> 1 | AA96: =IF($Z96=1,COUNTIFS(c_Pass,1,c_Sort,"<="&$Y96),"") -> 95 | AB96: =IF(OR($G96<>"Yes",NOT(ISNUMBER($H96))),"",COUNTIFS(c_Met,"Yes",c_Date,"<"&$H96)+COUNTIFS($G$2:$G96,"Yes",$H$2:$H96,$H96))
A97: =IF($B97="","",COUNTA($B$2:$B97)) -> 96 | B97: Jonathan Chua Chong Kheng | D97: iFast | E97: Consultant | F97: Branch Directors | G97: No | I97: 0 | J97: No | N97: Not Invited | O97: Not Invited | P97: Not Invited | Q97: Not Invited | R97: Not Invited | S97: Reports to Bernard Chan | T97: =IF($B97="","",COUNTA($N97:$R97)-COUNTIF($N97:$R97,"Not Invited")) -> 0 | U97: =IF($B97="","",COUNTIF($N97:$R97,"Attended")) -> 0 | V97: =IF($B97="","",_xlfn.TEXTJOIN(", ",TRUE(),IF($N97="Attended",Setup!$D$15,""),IF($O97="Attended",Setup!$D$16,""),IF($P97="Attended",Setup!$D$17,""),IF($Q97="Attended",Setup!$D$18,""),IF($R97="Attended",Setup!$D$19,""))) | W97: =IF(OR($B97="",NOT(ISNUMBER($H97))),"",TODAY()-$H97) | X97: =IF($B97="","",IF($U97>0,"Event attendee",IF($G97="Yes","Met (no event)",IF($T97>0,"Invited only",IF(OR($L97="Yes",$M97="Yes"),"Contacted only","Not yet contacted"))))) -> Not yet contacted | Y97: =IF($B97="","",COUNTIF(c_Firm,"<"&$D97)+COUNTIFS(c_Firm,$D97,c_Name,"<"&$B97)+COUNTIFS($D$2:$D97,$D97,$B$2:$B97,$B97)) -> 96 | Z97: =IF($B97="","",IF(AND(OR(Contacts!$C$3="(All)",$D97=Contacts!$C$3),OR(Contacts!$E$3="(All)",$G97=Contacts!$E$3),OR(Contacts!$G$3="(All)",ISNUMBER(SEARCH(Contacts!$G$3,$V97))),OR(Contacts!$I$3="(All)",$X97=Contacts!$I$3),OR(Contacts!$K$3="",ISNUMBER(SEARCH(Contacts!$K$3,$B97&" "&$C97&" "&$D97&" "&$S97)))),1,0)) -> 1 | AA97: =IF($Z97=1,COUNTIFS(c_Pass,1,c_Sort,"<="&$Y97),"") -> 96 | AB97: =IF(OR($G97<>"Yes",NOT(ISNUMBER($H97))),"",COUNTIFS(c_Met,"Yes",c_Date,"<"&$H97)+COUNTIFS($G$2:$G97,"Yes",$H$2:$H97,$H97))
A98: =IF($B98="","",COUNTA($B$2:$B98)) -> 97 | B98: Jonathan Gui Poh Jin | D98: iFast | E98: Consultant | F98: Branch Directors | G98: No | I98: 0 | J98: No | N98: Not Invited | O98: Not Invited | P98: Not Invited | Q98: Not Invited | R98: Not Invited | S98: Reports to Bernard Chan | T98: =IF($B98="","",COUNTA($N98:$R98)-COUNTIF($N98:$R98,"Not Invited")) -> 0 | U98: =IF($B98="","",COUNTIF($N98:$R98,"Attended")) -> 0 | V98: =IF($B98="","",_xlfn.TEXTJOIN(", ",TRUE(),IF($N98="Attended",Setup!$D$15,""),IF($O98="Attended",Setup!$D$16,""),IF($P98="Attended",Setup!$D$17,""),IF($Q98="Attended",Setup!$D$18,""),IF($R98="Attended",Setup!$D$19,""))) | W98: =IF(OR($B98="",NOT(ISNUMBER($H98))),"",TODAY()-$H98) | X98: =IF($B98="","",IF($U98>0,"Event attendee",IF($G98="Yes","Met (no event)",IF($T98>0,"Invited only",IF(OR($L98="Yes",$M98="Yes"),"Contacted only","Not yet contacted"))))) -> Not yet contacted | Y98: =IF($B98="","",COUNTIF(c_Firm,"<"&$D98)+COUNTIFS(c_Firm,$D98,c_Name,"<"&$B98)+COUNTIFS($D$2:$D98,$D98,$B$2:$B98,$B98)) -> 97 | Z98: =IF($B98="","",IF(AND(OR(Contacts!$C$3="(All)",$D98=Contacts!$C$3),OR(Contacts!$E$3="(All)",$G98=Contacts!$E$3),OR(Contacts!$G$3="(All)",ISNUMBER(SEARCH(Contacts!$G$3,$V98))),OR(Contacts!$I$3="(All)",$X98=Contacts!$I$3),OR(Contacts!$K$3="",ISNUMBER(SEARCH(Contacts!$K$3,$B98&" "&$C98&" "&$D98&" "&$S98)))),1,0)) -> 1 | AA98: =IF($Z98=1,COUNTIFS(c_Pass,1,c_Sort,"<="&$Y98),"") -> 97 | AB98: =IF(OR($G98<>"Yes",NOT(ISNUMBER($H98))),"",COUNTIFS(c_Met,"Yes",c_Date,"<"&$H98)+COUNTIFS($G$2:$G98,"Yes",$H$2:$H98,$H98))
A99: =IF($B99="","",COUNTA($B$2:$B99)) -> 98 | B99: Kenrick Mak Yao Zhang | D99: iFast | E99: Consultant | F99: Branch Directors | G99: No | I99: 0 | J99: No | N99: Not Invited | O99: Not Invited | P99: Not Invited | Q99: Not Invited | R99: Not Invited | S99: Reports to Bernard Chan | T99: =IF($B99="","",COUNTA($N99:$R99)-COUNTIF($N99:$R99,"Not Invited")) -> 0 | U99: =IF($B99="","",COUNTIF($N99:$R99,"Attended")) -> 0 | V99: =IF($B99="","",_xlfn.TEXTJOIN(", ",TRUE(),IF($N99="Attended",Setup!$D$15,""),IF($O99="Attended",Setup!$D$16,""),IF($P99="Attended",Setup!$D$17,""),IF($Q99="Attended",Setup!$D$18,""),IF($R99="Attended",Setup!$D$19,""))) | W99: =IF(OR($B99="",NOT(ISNUMBER($H99))),"",TODAY()-$H99) | X99: =IF($B99="","",IF($U99>0,"Event attendee",IF($G99="Yes","Met (no event)",IF($T99>0,"Invited only",IF(OR($L99="Yes",$M99="Yes"),"Contacted only","Not yet contacted"))))) -> Not yet contacted | Y99: =IF($B99="","",COUNTIF(c_Firm,"<"&$D99)+COUNTIFS(c_Firm,$D99,c_Name,"<"&$B99)+COUNTIFS($D$2:$D99,$D99,$B$2:$B99,$B99)) -> 98 | Z99: =IF($B99="","",IF(AND(OR(Contacts!$C$3="(All)",$D99=Contacts!$C$3),OR(Contacts!$E$3="(All)",$G99=Contacts!$E$3),OR(Contacts!$G$3="(All)",ISNUMBER(SEARCH(Contacts!$G$3,$V99))),OR(Contacts!$I$3="(All)",$X99=Contacts!$I$3),OR(Contacts!$K$3="",ISNUMBER(SEARCH(Contacts!$K$3,$B99&" "&$C99&" "&$D99&" "&$S99)))),1,0)) -> 1 | AA99: =IF($Z99=1,COUNTIFS(c_Pass,1,c_Sort,"<="&$Y99),"") -> 98 | AB99: =IF(OR($G99<>"Yes",NOT(ISNUMBER($H99))),"",COUNTIFS(c_Met,"Yes",c_Date,"<"&$H99)+COUNTIFS($G$2:$G99,"Yes",$H$2:$H99,$H99))
A100: =IF($B100="","",COUNTA($B$2:$B100)) -> 99 | B100: Kerk Xiao Jing | D100: iFast | E100: Branch Director | F100: Branch Directors | G100: No | I100: 0 | J100: No | N100: Not Invited | O100: Not Invited | P100: Not Invited | Q100: Not Invited | R100: Not Invited | T100: =IF($B100="","",COUNTA($N100:$R100)-COUNTIF($N100:$R100,"Not Invited")) -> 0 | U100: =IF($B100="","",COUNTIF($N100:$R100,"Attended")) -> 0 | V100: =IF($B100="","",_xlfn.TEXTJOIN(", ",TRUE(),IF($N100="Attended",Setup!$D$15,""),IF($O100="Attended",Setup!$D$16,""),IF($P100="Attended",Setup!$D$17,""),IF($Q100="Attended",Setup!$D$18,""),IF($R100="Attended",Setup!$D$19,""))) | W100: =IF(OR($B100="",NOT(ISNUMBER($H100))),"",TODAY()-$H100) | X100: =IF($B100="","",IF($U100>0,"Event attendee",IF($G100="Yes","Met (no event)",IF($T100>0,"Invited only",IF(OR($L100="Yes",$M100="Yes"),"Contacted only","Not yet contacted"))))) -> Not yet contacted | Y100: =IF($B100="","",COUNTIF(c_Firm,"<"&$D100)+COUNTIFS(c_Firm,$D100,c_Name,"<"&$B100)+COUNTIFS($D$2:$D100,$D100,$B$2:$B100,$B100)) -> 99 | Z100: =IF($B100="","",IF(AND(OR(Contacts!$C$3="(All)",$D100=Contacts!$C$3),OR(Contacts!$E$3="(All)",$G100=Contacts!$E$3),OR(Contacts!$G$3="(All)",ISNUMBER(SEARCH(Contacts!$G$3,$V100))),OR(Contacts!$I$3="(All)",$X100=Contacts!$I$3),OR(Contacts!$K$3="",ISNUMBER(SEARCH(Contacts!$K$3,$B100&" "&$C100&" "&$D100&" "&$S100)))),1,0)) -> 1 | AA100: =IF($Z100=1,COUNTIFS(c_Pass,1,c_Sort,"<="&$Y100),"") -> 99 | AB100: =IF(OR($G100<>"Yes",NOT(ISNUMBER($H100))),"",COUNTIFS(c_Met,"Yes",c_Date,"<"&$H100)+COUNTIFS($G$2:$G100,"Yes",$H$2:$H100,$H100))
...

Sheet Setup
B2: IFA CONTACT DATABASE — SETUP & USER GUIDE
B3: Everything in this workbook is driven by the RawData tab. Add a contact there and every other tab updates itself.
B5: 1. | C5: ADD A CONTACT | D5: Go to the RawData tab, scroll to the first empty row and type into the WHITE columns (Name .. Notes). The GREY columns to the right calculate themselves — never type in them.
B6: 2. | C6: DROPDOWNS | D6: Firm, Contact Type, Source, Met?, Invested?, Email Sent, LinkedIn and every event column are dropdowns. To add a new choice, add it to the lists on the right of this tab.
B7: 3. | C7: ADD AN EVENT | D7: Type the event name / short name / date into the EVENTS table below (rows 4 and 5 are free). A new column instantly appears in RawData and a new line appears on the Dashboard.
B8: 4. | C8: READ THE NUMBERS | D8: Dashboard = who they are and where they come from. Meeting Stats = how the meeting effort is going. Contacts = the searchable directory (use the filter boxes at the top).
B9: 5. | C9: CAPACITY | D9: The workbook is set up for 599 contacts. To go beyond that, select rows and use Formulas > Name Manager to extend the c_* ranges, or run the ExtendCapacity macro.
B10: 6. | C10: MACROS (optional) | D10: Everything above works with formulas only — no macros required. IFA_Contacts_Macros.bas adds one-click sorting, an add-contact form and a duplicate checker if you want them.
B13: EVENTS | C13: (blue cells are yours to edit — adding a row here adds an event everywhere) | M13: Firms | O13: Contact Type | Q13: Source | S13: Met? | U13: Event status | W13: Yes / No | Y13: LinkedIn | AA13: Engagement | AD13: Firm filter | AF13: Met filter | AH13: Event filter | AJ13: Engagement filter
B14: # | C14: Event name (full) | D14: Short name (used on charts) | E14: Date | M14: PIAS | O14: Adviser | Q14: Meeting List | S14: Yes | U14: Attended | W14: Yes | Y14: Yes | AA14: Event attendee | AD14: (All) | AF14: (All) | AH14: (All) | AJ14: (All)
B15: Event 1 | C15: H2O AM IFA Symposium (October 2025) | D15: Oct-25 Symposium | E15: 45931 | M15: Finexis Advisory | O15: Branch Director | Q15: Branch Directors | S15: No | U15: No Show | W15: No | Y15: No | AA15: Met (no event) | AD15: PIAS | AF15: Yes | AH15: =IF(Setup!$D$15="","",Setup!$D$15) -> Oct-25 Symposium | AJ15: Event attendee
B16: Event 2 | C16: 2nd Edition H2O AM IFA Symposium (May 2026) | D16: May-26 Symposium | E16: 46143 | M16: Manulife FA | O16: Consultant | Q16: Mass Email PIAS | S16: TBC | U16: Accepted | W16: TBC | Y16: No LinkedIn found | AA16: Invited only | AD16: Finexis Advisory | AF16: No | AH16: =IF(Setup!$D$16="","",Setup!$D$16) -> May-26 Symposium | AJ16: Met (no event)
B17: Event 3 | C17: Macro Lunch series | D17: Macro Lunch | E17: 46226 | M17: Synergy | O17: Product / Platform | Q17: ILP Data | U17: Invited | AA17: Contacted only | AD17: Manulife FA | AF17: TBC | AH17: =IF(Setup!$D$17="","",Setup!$D$17) -> Macro Lunch | AJ17: Invited only
B18: Event 4 | M18: iFast | O18: Other | Q18: Event | U18: No Reply | AA18: Not yet contacted | AD18: Synergy | AH18: =IF(Setup!$D$18="","",Setup!$D$18) | AJ18: Contacted only
B19: Event 5 | M19: Financial Alliance | Q19: Referral | U19: Declined | AD19: iFast | AH19: =IF(Setup!$D$19="","",Setup!$D$19) | AJ19: Not yet contacted
M20: Phillip Capital | Q20: LinkedIn | U20: Not Invited | AD20: Financial Alliance
B21: COLOUR LEGEND | M21: Singlife | Q21: Other | AD21: Phillip Capital
B22: White cell | C22: Type here — this is your data (RawData columns B to S). | M22: Infinity FA | AD22: Singlife
B23: Grey cell | C23: Calculated. Typing over it breaks the formula for that row. | M23: Income Advisory | AD23: Infinity FA
B24: Yellow cell | C24: A filter or a switch — change it to change what you see. | M24: PromiseLand | AD24: Income Advisory
B25: Green | C25: Good news: met, attended, invested. | M25: Alpha Wealth | AD25: PromiseLand
B26: Red | C26: Needs attention: declined, or over 120 days since the last meeting. | M26: GYC Financial Advisory | AD26: Alpha Wealth
M27: Franklin Templeton | AD27: GYC Financial Advisory
M28: Great Eastern Life | AD28: Franklin Templeton
B29: HOW THE ORIGINAL FILE WAS TRANSLATED (assumptions — change any cell in RawData if one is wrong) | M29: H2O AM (internal) | AD29: Great Eastern Life
B30: • Source workbook: IFA_Meeting_List.xlsx — tabs Meeting List, Attendance, Branch Directors, Mass Email PIAS, ILP Data. All five are kept unchanged at the end of this workbook. | M30: HSBC Life | AD30: H2O AM (internal)
B31: • Contacts were merged on name (case and spacing ignored). Two people with the same name at DIFFERENT firms were kept separate. | M31: IPP FA | AD31: HSBC Life
B32: • Oct-25 Symposium, from 'Meeting List' column D: Yes = Attended, Not Available = Declined, No = No Reply, blank = Not Invited. | M32: Maybank | AD32: IPP FA
B33: • May-26 Symposium: the 'Attendance' tab is that event's attendance sheet — 66 registered, 55 ticked = Attended, the other 11 = No Show. Column K 'Accepted' supplies Declined / No Reply for everyone else; column J blank = Not Invited. | M33: NEBA Private | AD33: Maybank
B34: • 'Macro Lunch' and 'Overseas' written in the Invited column were moved out: Macro Lunch became its own event, Overseas became a Declined + a note. | M34: Other / Client | AD34: NEBA Private
